Workbook

Sheet Index
C2: Оборотно-сальдовий баланс банку* | D2: відповідно до Додатку 1 до постанови Правління Національного банку України
D3: від 15 березня 2018 року № 11 "Про встановлення переліку інформації, що підлягає обов'язковому опублікуванню банками України" (зі змінами)
D4: за даними статистичної звітності з файлів 02X "Дані про обороти та залишки на рахунках".
A5: NKB | B5: Порядковий номер | C5: Назва банку | D5: МФО | E5: ПРОЦЕНТИ ЗА ДЕПОЗИТНИМИ СЕРТИФІКАТАМИ (ДС), тис. грн | F5: ПРОЦЕНТИ ЗА ОВДП (ОВДП), тис.грн | G5: ПРОЦЕНТИ ЗА КРЕДИТАМИ ЗДУ | H5: ПРОЦЕНТИ ЗА КРЕДИТАМИ БІЗНЕСУ | I5: ПРОЦЕНТИ ЗА КРЕДИТАМИ НАСЕЛЕННЮ | J5: ПРОЦЕНТНІ ДОХОДИ ВСЬОГО (ПД), тис. грн | K5: ДС/ПД, % | L5: ДС до підсумку, % | M5: (ДС+ОВДП)/ПД, % | N5: ОВДП/ПД, % | O5: ОВДП до підсумку | P5: Обсяг ДС дебит (середні, поділено на кількість банк.днів) | Q5: Обсяг ДС кредит (середні, поділено на кількість банк.днів) | R5: Кошти в НБУ (кор.рахунок) (кредит) (код 1200) | S5: Кошти в НБУ (УСЬОГО) (кредит) (розділ 12) | T5: Проценти за поточними вкладами ДГ (код 7040) | U5: Проценти за строковими вкладами ДГ (код 7041) | V5: Кредити субʼєктам господарювання (р.20, р.23, 260) | W5: Кредити ЗДУ (р.21) | X5: Кредити фізичним особам (р. 22, 24, 262) | Y5: Кредити небанківським установам (265) | Z5: Прибуток звітного року (5040) | AA5: Збиток звітного року (5041) | AB5: Податок на прибуток (7900) | AC5: Інші податки (741) | AD5: Відрахування в резерви (770) | AE5: Загальні доходи (6) | AF5: Загальні витрати (7)
A6: 2 | B6: 1 | C6: АТ "Укрексімбанк" | D6: 322313 | E6: =' 2АТ "Укрексімбанк" '!$P$1139 | F6: =' 2АТ "Укрексімбанк" '!$P$1138 | G6: =' 2АТ "Укрексімбанк" '!$P$1150 | H6: =' 2АТ "Укрексімбанк" '!$P$1148 | I6: =' 2АТ "Укрексімбанк" '!$P$1149 | J6: =' 2АТ "Укрексімбанк" '!$P$1144 | K6: =IFERROR(E6/J6*100,0) | L6: =IFERROR(E6/SUM(E6:E10)*100,0) | M6: =IFERROR((E6+F6)/J6*100,0) | N6: =IFERROR(F6/J6*100,0) | O6: =IFERROR(F6/SUM(F6:F10)*100,0) | P6: =' 2АТ "Укрексімбанк" '!$J$1140 | Q6: =' 2АТ "Укрексімбанк" '!$N$1141 | R6: =' 2АТ "Укрексімбанк" '!$M$1142 | S6: =' 2АТ "Укрексімбанк" '!$M$1143 | T6: =' 2АТ "Укрексімбанк" '!$P$1151 | U6: =' 2АТ "Укрексімбанк" '!$P$1152 | V6: =' 2АТ "Укрексімбанк" '!$P$1154 | W6: =' 2АТ "Укрексімбанк" '!$P$1155 | X6: =' 2АТ "Укрексімбанк" '!$P$1156 | Y6: =' 2АТ "Укрексімбанк" '!$P$1157 | Z6: =' 2АТ "Укрексімбанк" '!$P$1158 | AA6: =' 2АТ "Укрексімбанк" '!$P$1159 | AB6: =' 2АТ "Укрексімбанк" '!$P$1160 | AC6: =' 2АТ "Укрексімбанк" '!$P$1161 | AD6: =' 2АТ "Укрексімбанк" '!$P$1162 | AE6: =' 2АТ "Укрексімбанк" '!$P$1163 | AF6: =' 2АТ "Укрексімбанк" '!$P$1164
A7: 6 | B7: 2 | C7: АТ "Ощадбанк" | D7: 300465 | E7: =' 6АТ "Ощадбанк" '!$P$1139 | F7: =' 6АТ "Ощадбанк" '!$P$1138 | G7: =' 6АТ "Ощадбанк" '!$P$1150 | H7: =' 6АТ "Ощадбанк" '!$P$1148 | I7: =' 6АТ "Ощадбанк" '!$P$1149 | J7: =' 6АТ "Ощадбанк" '!$P$1144 | K7: =IFERROR(E7/J7*100,0) | L7: =IFERROR(E7/SUM(E6:E10)*100,0) | M7: =IFERROR((E7+F7)/J7*100,0) | N7: =IFERROR(F7/J7*100,0) | O7: =IFERROR(F7/SUM(F6:F10)*100,0) | P7: =' 6АТ "Ощадбанк" '!$J$1140 | Q7: =' 6АТ "Ощадбанк" '!$N$1141 | R7: =' 6АТ "Ощадбанк" '!$M$1142 | S7: =' 6АТ "Ощадбанк" '!$M$1143 | T7: =' 6АТ "Ощадбанк" '!$P$1151 | U7: =' 6АТ "Ощадбанк" '!$P$1152 | V7: =' 6АТ "Ощадбанк" '!$P$1154 | W7: =' 6АТ "Ощадбанк" '!$P$1155 | X7: =' 6АТ "Ощадбанк" '!$P$1156 | Y7: =' 6АТ "Ощадбанк" '!$P$1157 | Z7: =' 6АТ "Ощадбанк" '!$P$1158 | AA7: =' 6АТ "Ощадбанк" '!$P$1159 | AB7: =' 6АТ "Ощадбанк" '!$P$1160 | AC7: =' 6АТ "Ощадбанк" '!$P$1161 | AD7: =' 6АТ "Ощадбанк" '!$P$1162 | AE7: =' 6АТ "Ощадбанк" '!$P$1163 | AF7: =' 6АТ "Ощадбанк" '!$P$1164
A8: 29 | B8: 3 | C8: АТ "БАНК АЛЬЯНС" | D8: 300119 | E8: =' 29АТ "БАНК АЛЬЯНС" '!$P$1139 | F8: =' 29АТ "БАНК АЛЬЯНС" '!$P$1138 | G8: =' 29АТ "БАНК АЛЬЯНС" '!$P$1150 | H8: =' 29АТ "БАНК АЛЬЯНС" '!$P$1148 | I8: =' 29АТ "БАНК АЛЬЯНС" '!$P$1149 | J8: =' 29АТ "БАНК АЛЬЯНС" '!$P$1144 | K8: =IFERROR(E8/J8*100,0) | L8: =IFERROR(E8/SUM(E6:E10)*100,0) | M8: =IFERROR((E8+F8)/J8*100,0) | N8: =IFERROR(F8/J8*100,0) | O8: =IFERROR(F8/SUM(F6:F10)*100,0) | P8: =' 29АТ "БАНК АЛЬЯНС" '!$J$1140 | Q8: =' 29АТ "БАНК АЛЬЯНС" '!$N$1141 | R8: =' 29АТ "БАНК АЛЬЯНС" '!$M$1142 | S8: =' 29АТ "БАНК АЛЬЯНС" '!$M$1143 | T8: =' 29АТ "БАНК АЛЬЯНС" '!$P$1151 | U8: =' 29АТ "БАНК АЛЬЯНС" '!$P$1152 | V8: =' 29АТ "БАНК АЛЬЯНС" '!$P$1154 | W8: =' 29АТ "БАНК АЛЬЯНС" '!$P$1155 | X8: =' 29АТ "БАНК АЛЬЯНС" '!$P$1156 | Y8: =' 29АТ "БАНК АЛЬЯНС" '!$P$1157 | Z8: =' 29АТ "БАНК АЛЬЯНС" '!$P$1158 | AA8: =' 29АТ "БАНК АЛЬЯНС" '!$P$1159 | AB8: =' 29АТ "БАНК АЛЬЯНС" '!$P$1160 | AC8: =' 29АТ "БАНК АЛЬЯНС" '!$P$1161 | AD8: =' 29АТ "БАНК АЛЬЯНС" '!$P$1162 | AE8: =' 29АТ "БАНК АЛЬЯНС" '!$P$1163 | AF8: =' 29АТ "БАНК АЛЬЯНС" '!$P$1164
A9: 36 | B9: 4 | C9: АТ "Райффайзен Банк" | D9: 300335 | E9: =' 36АТ "Райффайзен Банк" '!$P$1139 | F9: =' 36АТ "Райффайзен Банк" '!$P$1138 | G9: =' 36АТ "Райффайзен Банк" '!$P$1150 | H9: =' 36АТ "Райффайзен Банк" '!$P$1148 | I9: =' 36АТ "Райффайзен Банк" '!$P$1149 | J9: =' 36АТ "Райффайзен Банк" '!$P$1144 | K9: =IFERROR(E9/J9*100,0) | L9: =IFERROR(E9/SUM(E6:E10)*100,0) | M9: =IFERROR((E9+F9)/J9*100,0) | N9: =IFERROR(F9/J9*100,0) | O9: =IFERROR(F9/SUM(F6:F10)*100,0) | P9: =' 36АТ "Райффайзен Банк" '!$J$1140 | Q9: =' 36АТ "Райффайзен Банк" '!$N$1141 | R9: =' 36АТ "Райффайзен Банк" '!$M$1142 | S9: =' 36АТ "Райффайзен Банк" '!$M$1143 | T9: =' 36АТ "Райффайзен Банк" '!$P$1151 | U9: =' 36АТ "Райффайзен Банк" '!$P$1152 | V9: =' 36АТ "Райффайзен Банк" '!$P$1154 | W9: =' 36АТ "Райффайзен Банк" '!$P$1155 | X9: =' 36АТ "Райффайзен Банк" '!$P$1156 | Y9: =' 36АТ "Райффайзен Банк" '!$P$1157 | Z9: =' 36АТ "Райффайзен Банк" '!$P$1158 | AA9: =' 36АТ "Райффайзен Банк" '!$P$1159 | AB9: =' 36АТ "Райффайзен Банк" '!$P$1160 | AC9: =' 36АТ "Райффайзен Банк" '!$P$1161 | AD9: =' 36АТ "Райффайзен Банк" '!$P$1162 | AE9: =' 36АТ "Райффайзен Банк" '!$P$1163 | AF9: =' 36АТ "Райффайзен Банк" '!$P$1164
A10: 43 | B10: 5 | C10: АТ "АЛЬТБАНК" | D10: 320940 | E10: =' 43АТ "АЛЬТБАНК" '!$P$1139 | F10: =' 43АТ "АЛЬТБАНК" '!$P$1138 | G10: =' 43АТ "АЛЬТБАНК" '!$P$1150 | H10: =' 43АТ "АЛЬТБАНК" '!$P$1148 | I10: =' 43АТ "АЛЬТБАНК" '!$P$1149 | J10: =' 43АТ "АЛЬТБАНК" '!$P$1144 | K10: =IFERROR(E10/J10*100,0) | L10: =IFERROR(E10/SUM(E6:E10)*100,0) | M10: =IFERROR((E10+F10)/J10*100,0) | N10: =IFERROR(F10/J10*100,0) | O10: =IFERROR(F10/SUM(F6:F10)*100,0) | P10: =' 43АТ "АЛЬТБАНК" '!$J$1140 | Q10: =' 43АТ "АЛЬТБАНК" '!$N$1141 | R10: =' 43АТ "АЛЬТБАНК" '!$M$1142 | S10: =' 43АТ "АЛЬТБАНК" '!$M$1143 | T10: =' 43АТ "АЛЬТБАНК" '!$P$1151 | U10: =' 43АТ "АЛЬТБАНК" '!$P$1152 | V10: =' 43АТ "АЛЬТБАНК" '!$P$1154 | W10: =' 43АТ "АЛЬТБАНК" '!$P$1155 | X10: =' 43АТ "АЛЬТБАНК" '!$P$1156 | Y10: =' 43АТ "АЛЬТБАНК" '!$P$1157 | Z10: =' 43АТ "АЛЬТБАНК" '!$P$1158 | AA10: =' 43АТ "АЛЬТБАНК" '!$P$1159 | AB10: =' 43АТ "АЛЬТБАНК" '!$P$1160 | AC10: =' 43АТ "АЛЬТБАНК" '!$P$1161 | AD10: =' 43АТ "АЛЬТБАНК" '!$P$1162 | AE10: =' 43АТ "АЛЬТБАНК" '!$P$1163 | AF10: =' 43АТ "АЛЬТБАНК" '!$P$1164
A11: Всього | E11: =IFERROR(SUM(E6:E10),0) | F11: =IFERROR(SUM(F6:F10),0) | G11: =IFERROR(SUM(G6:G10),0) | H11: =IFERROR(SUM(H6:H10),0) | I11: =IFERROR(SUM(I6:I10),0) | J11: =IFERROR(SUM(J6:J10),0) | K11: =IFERROR(E11/J11*100,0) | L11: =IFERROR(E11/SUM(E6:E10)*100,0) | M11: =IFERROR((E11+F11)/J11*100,0) | N11: =IFERROR(F11/J11*100,0) | O11: =IFERROR(F11/SUM(F6:F10)*100,0) | P11: =IFERROR(SUM(P6:P10),0) | Q11: =IFERROR(SUM(Q6:Q10),0) | R11: =IFERROR(SUM(R6:R10),0) | S11: =IFERROR(SUM(S6:S10),0) | T11: =IFERROR(SUM(T6:T10),0) | U11: =IFERROR(SUM(U6:U10),0) | V11: =IFERROR(SUM(V6:V10),0) | W11: =IFERROR(SUM(W6:W10),0) | ... AF11: =IFERROR(SUM(AF6:AF10),0)
A12: Державні банки | E12: =IFERROR(SUM(E6,E7),0) | F12: =IFERROR(SUM(F6,F7),0) | G12: =IFERROR(SUM(G6,G7),0) | H12: =IFERROR(SUM(H6,H7),0) | I12: =IFERROR(SUM(I6,I7),0) | J12: =IFERROR(SUM(J6,J7),0) | K12: =IFERROR(E12/J12*100,0) | L12: =IFERROR(E12/E11*100,0) | M12: =IFERROR(SUM(M6,M7),0) | N12: =IFERROR(SUM(N6,N7),0) | O12: =IFERROR(F12/F11*100,0) | P12: =IFERROR(SUM(P6,P7),0) | Q12: =IFERROR(SUM(Q6,Q7),0) | R12: =IFERROR(SUM(R6,R7),0) | S12: =IFERROR(SUM(S6,S7),0) | T12: =IFERROR(SUM(T6,T7),0) | U12: =IFERROR(SUM(U6,U7),0) | V12: =IFERROR(SUM(V6,V7),0) | W12: =IFERROR(SUM(W6,W7),0) | ... AF12: =IFERROR(SUM(AF6,AF7),0)
A13: Банки з іноземним капіталом | E13: =IFERROR(SUM(E9),0) | F13: =IFERROR(SUM(F9),0) | G13: =IFERROR(SUM(G9),0) | H13: =IFERROR(SUM(H9),0) | I13: =IFERROR(SUM(I9),0) | J13: =IFERROR(SUM(J9),0) | K13: =IFERROR(E13/J13*100,0) | L13: =IFERROR(E13/E11*100,0) | M13: =IFERROR(SUM(M9),0) | N13: =IFERROR(SUM(N9),0) | O13: =IFERROR(F13/F11*100,0) | P13: =IFERROR(SUM(P9),0) | Q13: =IFERROR(SUM(Q9),0) | R13: =IFERROR(SUM(R9),0) | S13: =IFERROR(SUM(S9),0) | T13: =IFERROR(SUM(T9),0) | U13: =IFERROR(SUM(U9),0) | V13: =IFERROR(SUM(V9),0) | W13: =IFERROR(SUM(W9),0) | ... AF13: =IFERROR(SUM(AF9),0)
A14: Банки з українським приватним капіталом | E14: =IFERROR(E11-E12-E13,0) | F14: =IFERROR(F11-F12-F13,0) | G14: =IFERROR(G11-G12-G13,0) | H14: =IFERROR(H11-H12-H13,0) | I14: =IFERROR(I11-I12-I13,0) | J14: =IFERROR(J11-J12-J13,0) | K14: =IFERROR(E14/J14*100,0) | L14: =IFERROR(E14/E11*100,0) | M14: =IFERROR(M11-M12-M13,0) | N14: =IFERROR(N11-N12-N13,0) | O14: =IFERROR(F14/F11*100,0) | P14: =IFERROR(P11-P12-P13,0) | Q14: =IFERROR(Q11-Q12-Q13,0) | R14: =IFERROR(R11-R12-R13,0) | S14: =IFERROR(S11-S12-S13,0) | T14: =IFERROR(T11-T12-T13,0) | U14: =IFERROR(U11-U12-U13,0) | V14: =IFERROR(V11-V12-V13,0) | W14: =IFERROR(W11-W12-W13,0) | ... AF14: =IFERROR(AF11-AF12-AF13,0)
B16: Категорія | C16: ДС/ПД, % | H16: Категорія | I16: ДС до підсумку, %
B17: =A12 | C17: =IFERROR(K12,0) | H17: =A12 | I17: =IFERROR(L12,0)
B18: =A13 | C18: =IFERROR(K13,0) | H18: =A13 | I18: =IFERROR(L13,0)
B19: =A14 | C19: =IFERROR(K14,0) | H19: =A14 | I19: =IFERROR(L14,0)

Sheet Indicator_Summary
A1: ПРОЦЕНТНІ ДОХОДИ банків
B2: млрд | C2: %
A3: Депозитні сертифікати | B3: =SUM(Index!E6:E10)/1000000 | C3: =B3/B8 * 100
A4: ОВДП | B4: =SUM(Index!F6:F10)/1000000 | C4: =B4/B8 * 100
A5: Кредити бізнесу | B5: =SUM(Index!H6:H10)/1000000 | C5: =B5/B8 * 100
A6: Кредити населенню | B6: =SUM(Index!I6:I10)/1000000 | C6: =B6/B8 * 100
A7: Інші процентні доходи | B7: =B8 - (B3 +B4 +B5 +B6) | C7: =B7/B8 * 100
A8: ВСЬОГО | B8: =SUM(Index!J6:J10)/1000000 | C8: 100

Sheet Pivot_Data
A1: bank_code | B1: bank_name | C1: bank_class | D1: id | E1: indicator | F1: name | G1: category | H1: debit_total | I1: debit_nc | J1: debit_ic | K1: credit_total | L1: credit_nc | M1: credit_ic | N1: balance_total | O1: balance_nc | P1: balance_ic
A2: 2 | B2: АТ "Укрексімбанк" | C2: Державний | D2: 1001 | E2: (без привʼязки) | F2: Банкноти та монети в касі банку | G2: А | H2: 2881154.5 | I2: 1258377.3 | J2: 1622777.2 | K2: 2741564.6 | L2: 1220518.4 | M2: 1521046.2 | N2: 827366.58 | O2: 181416.63 | P2: 645949.94
A3: 2 | B3: АТ "Укрексімбанк" | C3: Державний | D3: 1002 | E3: (без привʼязки) | F3: Банкноти та монети в касі відділень банку | G3: А | H3: 421596.77 | I3: 177262.1 | J3: 244334.67 | K3: 420605.54 | L3: 178404.18 | M3: 242201.35 | N3: 68413.231 | O3: 15938.651 | P3: 52474.58
A4: 2 | B4: АТ "Укрексімбанк" | C4: Державний | D4: 1004 | E4: (без привʼязки) | F4: Банкноти та монети в банкоматах | G4: А | H4: 1424777.4 | I4: 1424777.4 | J4: 0 | K4: 1427186.2 | L4: 1427186.2 | M4: 0 | N4: 345970.89 | O4: 345970.89 | P4: 0
A5: 2 | B5: АТ "Укрексімбанк" | C5: Державний | D5: 1005 | E5: (без привʼязки) | F5: Банкноти та монети, інкасовані до перерахування | G5: А | H5: 94970.078 | I5: 94970.078 | J5: 0 | K5: 94970.078 | L5: 94970.078 | M5: 0 | N5: 0 | O5: 0 | P5: 0
A6: 2 | B6: АТ "Укрексімбанк" | C6: Державний | D6: 1006 | E6: (без привʼязки) | F6: Банкноти та монети на зберіганні в інкасаторській компанії | G6: А | H6: 0 | I6: 0 | J6: 0 | K6: 0 | L6: 0 | M6: 0 | N6: 0 | O6: 0 | P6: 0
A7: 2 | B7: АТ "Укрексімбанк" | C7: Державний | D7: 1007 | E7: (без привʼязки) | F7: Банкноти та монети в дорозі | G7: А | H7: 880991.48 | I7: 256979.65 | J7: 624011.83 | K7: 911560.8 | L7: 261956.45 | M7: 649604.35 | N7: 0 | O7: 0 | P7: 0
A8: 2 | B8: АТ "Укрексімбанк" | C8: Державний | D8: 1011 | E8: (без привʼязки) | F8: Дорожні чеки в касі банку | G8: А | H8: 0 | I8: 0 | J8: 0 | K8: 0 | L8: 0 | M8: 0 | N8: 0 | O8: 0 | P8: 0
A9: 2 | B9: АТ "Укрексімбанк" | C9: Державний | D9: 1012 | E9: (без привʼязки) | F9: Дорожні чеки в касі відділень банку | G9: А | H9: 0 | I9: 0 | J9: 0 | K9: 0 | L9: 0 | M9: 0 | N9: 0 | O9: 0 | P9: 0
A10: 2 | B10: АТ "Укрексімбанк" | C10: Державний | D10: 1090 | E10: (без привʼязки) | F10: Резерви за готівковими коштами, наявність яких є непідтвердженою | G10: П | H10: 533.62252 | I10: 0 | J10: 533.62252 | K10: 785.03309 | L10: 0 | M10: 785.03309 | N10: -50810.589 | O10: -5377.8999 | P10: -45432.689
A11: 2 | B11: АТ "Укрексімбанк" | C11: Державний | D11: 1101 | E11: (без привʼязки) | F11: Банківські метали в банку | G11: А | H11: 0 | I11: 0 | J11: 0 | K11: 0 | L11: 0 | M11: 0 | N11: 0 | O11: 0 | P11: 0
A12: 2 | B12: АТ "Укрексімбанк" | C12: Державний | D12: 1102 | E12: (без привʼязки) | F12: Банківські метали у відділенні банку | G12: А | H12: 0 | I12: 0 | J12: 0 | K12: 0 | L12: 0 | M12: 0 | N12: 0 | O12: 0 | P12: 0
A13: 2 | B13: АТ "Укрексімбанк" | C13: Державний | D13: 1107 | E13: (без привʼязки) | F13: Банківські метали в дорозі | G13: А | H13: 0 | I13: 0 | J13: 0 | K13: 0 | L13: 0 | M13: 0 | N13: 0 | O13: 0 | P13: 0
... A6516: 43 | B6516: АТ "АЛЬТБАНК" | C6516: Приватний капітал | D6516: 9916 | E6516: (без привʼязки) | F6516: 0 | G6516: П | H6516: 0 | I6516: 0 | J6516: 0 | K6516: 0 | L6516: 0 | M6516: 0 | N6516: 0 | O6516: 0 | P6516: 0

Sheet Зміст
B2: Оборотно-сальдовий баланс банку | C2: відповідно до підпункту 1 пункту 2 постанови Правління Національного банку України
C3: від 15 березня 2018 року № 11 “Про встановлення переліку інформації, що підлягає обов'язковому опублікуванню банками України” (зі змінами)
C4: за даними статистичної звітності з файлу 02X “Дані про обороти та залишки на рахунках”.
A6: NKB | B6: Назва | C6: МФО
A7: 2 | B7: АТ "Укрексімбанк" | C7: 322313
A8: 6 | B8: АТ "ОЩАДБАНК" | C8: 300465
A9: 29 | B9: АТ "БАНК АЛЬЯНС" | C9: 300119
A10: 36 | B10: АТ "Райффайзен Банк" | C10: 300335
A11: 43 | B11: АТ "АЛЬТБАНК" | C11: 320940
A12: 46 | B12: АТ КБ "ПриватБанк" | C12: 305299
A13: 49 | B13: Полікомбанк | C13: 353100
A14: 62 | B14: АТ "ТАСКОМБАНК" | C14: 339500
A15: 72 | B15: ПрАТ "БАНК ФАМІЛЬНИЙ" | C15: 334840
A16: 88 | B16: АТ "КРЕДОБАНК" | C16: 325365
A17: 91 | B17: АТ АКБ "Львів" | C17: 325268
... A66: 774 | B66: АТ "РВС БАНК"* | C66: 339072
A68: * Неплатоспроможний банк.

Sheet   2АТ "Укрексімбанк" 
A1: Зміст
B2: Оборотно-сальдовий баланс банку АТ "Укрексімбанк" за станом на 01.12.2025
B3: (тис грн)
A4: Номер з/п | B4: Клас/ розділ/ група/ рахунок | I4: Актив/ пасив | J4: Обороти за місяць | Q4: Сальдо
J5: дебет | M5: кредит | Q5: усього | R5: НВ | S5: ІВ
B6: номер | F6: назва | J6: усього | K6: НВ | L6: ІВ | M6: усього | O6: НВ | P6: ІВ
A7: 1 | B7: 2 | F7: 3 | I7: 4 | J7: 5 | K7: 6 | L7: 7 | M7: 8 | O7: 9 | P7: 10 | Q7: 11 | R7: 12 | S7: 13
A8: 1 | B8: Балансові рахунки
A9: 2 | B9: Активи
A10: 3 | B10: Класи 1 - 4
A11: 4 | B11: Клас 1 | C11: 10 | D11: 100 | F11: 1001 | H11: Банкноти та монети в касі банку | I11: А | J11: 2881154.5 | K11: 1258377.3 | L11: 1622777.2 | M11: 2741564.6 | O11: 1220518.4 | P11: 1521046.2 | Q11: 827366.58 | R11: 181416.63 | S11: 645949.94
A12: 5 | F12: 1002 | H12: Банкноти та монети в касі відділень банку | I12: А | J12: 421596.77 | K12: 177262.1 | L12: 244334.67 | M12: 420605.54 | O12: 178404.18 | P12: 242201.35 | Q12: 68413.231 | R12: 15938.651 | S12: 52474.58
A13: 6 | F13: 1004 | H13: Банкноти та монети в банкоматах | I13: А | J13: 1424777.4 | K13: 1424777.4 | L13: 0 | M13: 1427186.2 | O13: 1427186.2 | P13: 0 | Q13: 345970.89 | R13: 345970.89 | S13: 0
A14: 7 | F14: 1005 | H14: Банкноти та монети, інкасовані до перерахування | I14: А | J14: 94970.078 | K14: 94970.078 | L14: 0 | M14: 94970.078 | O14: 94970.078 | P14: 0 | Q14: 0 | R14: 0 | S14: 0
A15: 8 | F15: 1006 | H15: Банкноти та монети на зберіганні в інкасаторській компанії | I15: А | J15: 0 | K15: 0 | L15: 0 | M15: 0 | O15: 0 | P15: 0 | Q15: 0 | R15: 0 | S15: 0
A16: 9 | F16: 1007 | H16: Банкноти та монети в дорозі | I16: А | J16: 880991.48 | K16: 256979.65 | L16: 624011.83 | M16: 911560.8 | O16: 261956.45 | P16: 649604.35 | Q16: 0 | R16: 0 | S16: 0
A17: 10 | F17: Група 100 - Усього | J17: 5703490.3 | K17: 3212366.5 | L17: 2491123.7 | M17: 5595887.3 | O17: 3183035.4 | P17: 2412851.9 | Q17: 1241750.7 | R17: 543326.17 | S17: 698424.52
A18: 11 | D18: 101 | F18: 1011 | H18: Дорожні чеки в касі банку | I18: А | J18: 0 | K18: 0 | L18: 0 | M18: 0 | O18: 0 | P18: 0 | Q18: 0 | R18: 0 | S18: 0
A19: 12 | F19: 1012 | H19: Дорожні чеки в касі відділень банку | I19: А | J19: 0 | K19: 0 | L19: 0 | M19: 0 | O19: 0 | P19: 0 | Q19: 0 | R19: 0 | S19: 0
A20: 13 | F20: Група 101 - Усього | J20: 0 | K20: 0 | L20: 0 | M20: 0 | O20: 0 | P20: 0 | Q20: 0 | R20: 0 | S20: 0
A21: 14 | D21: 109 | F21: 1090 | H21: Резерви за готівковими коштами, наявність яких є непідтвердженою | I21: П | J21: 533.62252 | K21: 0 | L21: 533.62252 | M21: 785.03309 | O21: 0 | P21: 785.03309 | Q21: -50810.589 | R21: -5377.8999 | S21: -45432.689
A22: 15 | F22: Група 109 - Усього | J22: 533.62252 | K22: 0 | L22: 533.62252 | M22: 785.03309 | O22: 0 | P22: 785.03309 | Q22: -50810.589 | R22: -5377.8999 | S22: -45432.689
A23: 16 | D23: Розділ 10 - Усього | J23: 5704023.9 | K23: 3212366.5 | L23: 2491657.3 | M23: 5596672.3 | O23: 3183035.4 | P23: 2413636.9 | Q23: 1190940.1 | R23: 537948.27 | S23: 652991.84
A24: 17 | C24: 11 | D24: 110 | F24: 1101 | H24: Банківські метали в банку | I24: А | J24: 0 | K24: 0 | L24: 0 | M24: 0 | O24: 0 | P24: 0 | Q24: 0 | R24: 0 | S24: 0
A25: 18 | F25: 1102 | H25: Банківські метали у відділенні банку | I25: А | J25: 0 | K25: 0 | L25: 0 | M25: 0 | O25: 0 | P25: 0 | Q25: 0 | R25: 0 | S25: 0
A26: 19 | F26: 1107 | H26: Банківські метали в дорозі | I26: А | J26: 0 | K26: 0 | L26: 0 | M26: 0 | O26: 0 | P26: 0 | Q26: 0 | R26: 0 | S26: 0
A27: 20 | F27: Група 110 - Усього | J27: 0 | K27: 0 | L27: 0 | M27: 0 | O27: 0 | P27: 0 | Q27: 0 | R27: 0 | S27: 0
A28: 21 | D28: 119 | F28: 1190 | H28: Резерви за банківськими металами, наявність яких є непідтвердженою | I28: П | J28: 0 | K28: 0 | L28: 0 | M28: 0 | O28: 0 | P28: 0 | Q28: 0 | R28: 0 | S28: 0
A29: 22 | F29: Група 119 - Усього | J29: 0 | K29: 0 | L29: 0 | M29: 0 | O29: 0 | P29: 0 | Q29: 0 | R29: 0 | S29: 0
A30: 23 | D30: Розділ 11 - Усього | J30: 0 | K30: 0 | L30: 0 | M30: 0 | O30: 0 | P30: 0 | Q30: 0 | R30: 0 | S30: 0
A31: 24 | C31: 12 | D31: 120 | F31: 1200 | H31: Кореспондентський рахунок банку в Національному банку України | I31: А | J31: 5.6606691e+08 | K31: 5.6606691e+08 | L31: 0 | M31: 5.616171e+08 | O31: 5.616171e+08 | P31: 0 | Q31: 22042210 | R31: 22042210 | S31: 0
A32: 25 | F32: 1202 | H32: Кошти банків за рахунками умовного зберігання (ескроу) у Національному банку України | I32: А | J32: 0 | K32: 0 | L32: 0 | M32: 0 | O32: 0 | P32: 0 | Q32: 0 | R32: 0 | S32: 0
A33: 26 | F33: 1205 | H33: Кошти банків для забезпечення виконання зобов’язань перед Національним банком України за кредитами, наданими банкам, та операціями своп процентної ставки | I33: А | J33: 0 | K33: 0 | L33: 0 | M33: 0 | O33: 0 | P33: 0 | Q33: 0 | R33: 0 | S33: 0
A34: 27 | F34: 1208 | H34: Нараховані доходи за коштами на вимогу в Національному банку України | I34: А | J34: 0 | K34: 0 | L34: 0 | M34: 0 | O34: 0 | P34: 0 | Q34: 0 | R34: 0 | S34: 0
A35: 28 | F35: Група 120 - Усього | J35: 5.6606691e+08 | K35: 5.6606691e+08 | L35: 0 | M35: 5.616171e+08 | O35: 5.616171e+08 | P35: 0 | Q35: 22042210 | R35: 22042210 | S35: 0
A36: 29 | D36: Розділ 12 - Усього | J36: 5.6606691e+08 | K36: 5.6606691e+08 | L36: 0 | M36: 5.616171e+08 | O36: 5.616171e+08 | P36: 0 | Q36: 22042210 | R36: 22042210 | S36: 0
A37: 30 | C37: 14 | D37: 140 | F37: 1400 | H37: Облігації внутрішньої державної позики, що рефінансуються Національним банком України, які обліковуються за справедливою вартістю через прибутки/збитки | I37: А | J37: 9461457.4 | K37: 5951813 | L37: 3509644.4 | M37: 12068323 | O37: 8995306 | P37: 3073017.2 | Q37: 13863168 | R37: 13246549 | S37: 616618.88
A38: 31 | F38: 1405 | H38: Переоцінка боргових цінних паперів, що рефінансуються Національним банком України, які обліковуються за справедливою вартістю через прибутки/збитки | I38: А | J38: 374584.69 | K38: 372410.19 | L38: 2174.4995 | M38: 2627750.8 | O38: 2625165.2 | P38: 2585.535 | Q38: 6054103.6 | R38: 6053531 | S38: 572.58176
A39: 32 | I39: П | J39: 0 | K39: 0 | L39: 0 | M39: 0 | O39: 0 | P39: 0 | Q39: -57653.272 | R39: -57281.832 | S39: -371.44051
A40: 33 | F40: 1406 | H40: Неамортизована премія/дисконт за борговими цінними паперами, що рефінансуються Національним банком України, які обліковуються за справедливою вартістю через прибутки/збитки | I40: А | J40: 76966.686 | K40: 72049.045 | L40: 4917.6409 | M40: 60453.482 | O40: 56658.297 | P40: 3795.1846 | Q40: 704401.07 | R40: 703238.51 | S40: 1162.5606
A41: 34 | I41: П | J41: 0 | K41: 0 | L41: 0 | M41: 0 | O41: 0 | P41: 0 | Q41: -15932.686 | R41: -15929.243 | S41: -3.44265
A42: 35 | F42: 1408 | H42: Нараховані доходи за борговими цінними паперами, що рефінансуються Національним банком України, які обліковуються за справедливою вартістю через прибутки/збитки | I42: А | J42: 412462 | K42: 356747.44 | L42: 55714.563 | M42: 447665.85 | O42: 400664.44 | P42: 47001.414 | Q42: 385140.92 | R42: 375182.2 | S42: 9958.7297
A43: 36 | F43: Група 140 - Усього | J43: 10325471 | K43: 6753019.7 | L43: 3572451.1 | M43: 15204193 | O43: 12077794 | P43: 3126399.4 | Q43: 20933228 | R43: 20305290 | S43: 627937.87
A44: 37 | D44: 141 | F44: 1410 | H44: Облігації внутрішньої державної позики, що рефінансуються Національним банком України, які обліковуються за справедливою вартістю через інший сукупний дохід | I44: А | J44: 0 | K44: 0 | L44: 0 | M44: 720998 | O44: 720998 | P44: 0 | Q44: 19225235 | R44: 19225235 | S44: 0
A45: 38 | F45: 1411 | H45: Облігації зовнішньої державної позики, що рефінансуються Національним банком України, які обліковуються за справедливою вартістю через інший сукупний дохід | I45: А | J45: 0 | K45: 0 | L45: 0 | M45: 0 | O45: 0 | P45: 0 | Q45: 0 | R45: 0 | S45: 0
A46: 39 | F46: 1412 | H46: Боргові цінні папери органів державної влади та місцевого самоврядування, що рефінансуються Національним банком України, які обліковуються за справедливою вартістю через інший сукупний дохід | I46: А | J46: 0 | K46: 0 | L46: 0 | M46: 0 | O46: 0 | P46: 0 | Q46: 0 | R46: 0 | S46: 0
A47: 40 | F47: 1415 | H47: Переоцінка боргових цінних паперів, що рефінансуються Національним банком України, які обліковуються за справедливою вартістю через інший сукупний дохід | I47: А | J47: 116132.23 | K47: 116132.23 | L47: 0 | M47: 126706.95 | O47: 126706.95 | P47: 0 | Q47: 483199.92 | R47: 483199.92 | S47: 0
A48: 41 | I48: П | J48: 0 | K48: 0 | L48: 0 | M48: 0 | O48: 0 | P48: 0 | Q48: -387951.2 | R48: -387951.2 | S48: 0
A49: 42 | F49: 1416 | H49: Неамортизована премія/дисконт за борговими цінними паперами, що рефінансуються Національним банком України, які обліковуються за справедливою вартістю через інший сукупний дохід | I49: А | J49: 1309.7475 | K49: 1309.7475 | L49: 0 | M49: 7620.9061 | O49: 7620.9061 | P49: 0 | Q49: 113011.67 | R49: 113011.67 | S49: 0
A50: 43 | I50: П | J50: 0 | K50: 0 | L50: 0 | M50: 0 | O50: 0 | P50: 0 | Q50: -4001.6549 | R50: -4001.6549 | S50: 0
A51: 44 | F51: 1418 | H51: Нараховані доходи за борговими цінними паперами, що рефінансуються Національним банком України, які обліковуються за справедливою вартістю через інший сукупний дохід | I51: А | J51: 251493.08 | K51: 251493.08 | L51: 0 | M51: 114050.99 | O51: 114050.99 | P51: 0 | Q51: 861921.33 | R51: 861921.33 | S51: 0
A52: 45 | F52: 1419 | H52: Резерв за борговими цінними паперами,що рефінансуються Національним банком України, які обліковуються за справедливою вартістю через інший сукупний дохід | I52: П | J52: 15901.213 | K52: 15901.213 | L52: 0 | M52: 5274.7307 | O52: 5274.7307 | P52: 0 | Q52: -847399.97 | R52: -847399.97 | S52: 0
A53: 46 | F53: Група 141 - Усього | J53: 384836.28 | K53: 384836.28 | L53: 0 | M53: 974651.57 | O53: 974651.57 | P53: 0 | Q53: 19444015 | R53: 19444015 | S53: 0
A54: 47 | D54: 142 | F54: 1420 | H54: Облігації внутрішньої державної позики, що рефінансуються Національним банком України, які обліковуються за амортизованою собівартістю | I54: А | J54: 0 | K54: 0 | L54: 0 | M54: 0 | O54: 0 | P54: 0 | Q54: 26489557 | R54: 26489557 | S54: 0
A55: 48 | F55: 1426 | H55: Неамортизована премія/дисконт за борговими цінними паперами, що рефінансуються Національним банком України, які обліковуються за амортизованою собівартістю | I55: А | J55: 1421.729 | K55: 1421.729 | L55: 0 | M55: 6213.554 | O55: 6213.554 | P55: 0 | Q55: 145146.68 | R55: 145146.68 | S55: 0
A56: 49 | I56: П | J56: 0 | K56: 0 | L56: 0 | M56: 0 | O56: 0 | P56: 0 | Q56: -28830.501 | R56: -28830.501 | S56: 0
A57: 50 | F57: 1428 | H57: Нараховані доходи за борговими цінними паперами, що рефінансуються Національним банком України, які обліковуються за амортизованою собівартістю | I57: А | J57: 304571.1 | K57: 304571.1 | L57: 0 | M57: 50273.415 | O57: 50273.415 | P57: 0 | Q57: 824636.77 | R57: 824636.77 | S57: 0
A58: 51 | F58: 1429 | H58: Резерв за борговими цінними паперами,що рефінансуються Національним банком України, які обліковуються за амортизованою собівартістю | I58: П | J58: 18908.285 | K58: 18908.285 | L58: 0 | M58: 8973.7314 | O58: 8973.7314 | P58: 0 | Q58: -1319100.4 | R58: -1319100.4 | S58: 0
A59: 52 | F59: Група 142 - Усього | J59: 324901.11 | K59: 324901.11 | L59: 0 | M59: 65460.701 | O59: 65460.701 | P59: 0 | Q59: 26111410 | R59: 26111410 | S59: 0
A60: 53 | D60: 143 | F60: 1430 | H60: Депозитні сертифікати Національного банку України, розміщені в банках України, що обліковуються за справедливою вартістю через інший сукупний дохід | I60: А | J60: 0 | K60: 0 | L60: 0 | M60: 0 | O60: 0 | P60: 0 | Q60: 0 | R60: 0 | S60: 0
A61: 54 | F61: 1435 | H61: Переоцінка депозитних сертифікатів Національного банку України, розміщених у банках України, що обліковуються за справедливою вартістю через інший сукупний дохід | I61: А | J61: 0 | K61: 0 | L61: 0 | M61: 0 | O61: 0 | P61: 0 | Q61: 0 | R61: 0 | S61: 0
A62: 55 | F62: 1436 | H62: Неамортизована премія/дисконт за депозитними сертифікатами Національного банку України, розміщеними в банках України, що обліковуються за справедливою вартістю через інший сукупний дохід | I62: А | J62: 0 | K62: 0 | L62: 0 | M62: 0 | O62: 0 | P62: 0 | Q62: 0 | R62: 0 | S62: 0
A63: 56 | I63: П | J63: 0 | K63: 0 | L63: 0 | M63: 0 | O63: 0 | P63: 0 | Q63: 0 | R63: 0 | S63: 0
A64: 57 | F64: 1438 | H64: Нараховані доходи за депозитними сертифікатами Національного банку України, розміщеними в банках України, що обліковуються за справедливою вартістю через інший сукупний дохід | I64: А | J64: 0 | K64: 0 | L64: 0 | M64: 0 | O64: 0 | P64: 0 | Q64: 0 | R64: 0 | S64: 0
A65: 58 | F65: Група 143 - Усього | J65: 0 | K65: 0 | L65: 0 | M65: 0 | O65: 0 | P65: 0 | Q65: 0 | R65: 0 | S65: 0
A66: 59 | D66: 144 | F66: 1440 | H66: Депозитні сертифікати Національного банку України, розміщені в банках України, що обліковуються за амортизованою собівартістю | I66: А | J66: 304000000 | K66: 304000000 | L66: 0 | M66: 299000000 | O66: 299000000 | P66: 0 | Q66: 25000000 | R66: 25000000 | S66: 0
A67: 60 | F67: 1446 | H67: Неамортизована премія/дисконт за депозитними сертифікатами Національного банку України, розміщеними в банках України, що обліковуються за амортизованою собівартістю | I67: А | J67: 17.385 | K67: 17.385 | L67: 0 | M67: 13.785 | O67: 13.785 | P67: 0 | Q67: 0 | R67: 0 | S67: 0
A68: 61 | I68: П | J68: 0 | K68: 0 | L68: 0 | M68: 0 | O68: 0 | P68: 0 | Q68: 0 | R68: 0 | S68: 0
A69: 62 | F69: 1448 | H69: Нараховані доходи за депозитними сертифікатами Національного банку України, розміщеними в банках України, що обліковуються за амортизованою собівартістю | I69: А | J69: 206808.51 | K69: 206808.51 | L69: 0 | M69: 183452.45 | O69: 183452.45 | P69: 0 | Q69: 31849.25 | R69: 31849.25 | S69: 0
A70: 63 | F70: Група 144 - Усього | J70: 3.0420683e+08 | K70: 3.0420683e+08 | L70: 0 | M70: 2.9918347e+08 | O70: 2.9918347e+08 | P70: 0 | Q70: 25031849 | R70: 25031849 | S70: 0
A71: 64 | D71: Розділ 14 - Усього | J71: 3.1524203e+08 | K71: 3.1166958e+08 | L71: 3572451.1 | M71: 3.1542777e+08 | O71: 3.1230137e+08 | P71: 3126399.4 | Q71: 91520501 | R71: 90892564 | S71: 627937.87
A72: 65 | C72: 15 | D72: 150 | F72: 1500 | H72: Кореспондентські рахунки, що відкриті в інших банках | I72: А | J72: 3.1363892e+08 | K72: 0 | L72: 3.1363892e+08 | M72: 3.2641004e+08 | O72: 0 | P72: 3.2641004e+08 | Q72: 19367439 | R72: 0 | S72: 19367439
A73: 66 | F73: 1508 | H73: Нараховані доходи за коштами на вимогу в інших банках | I73: А | J73: 0 | K73: 0 | L73: 0 | M73: 0 | O73: 0 | P73: 0 | Q73: 0 | R73: 0 | S73: 0
A74: 67 | F74: 1509 | H74: Резерв за коштами на вимогу в інших банках | I74: П | J74: 9061.1933 | K74: 0 | L74: 9061.1933 | M74: 1399.0083 | O74: 0 | P74: 1399.0083 | Q74: -48755.225 | R74: 0 | S74: -48755.225
A75: 68 | F75: Група 150 - Усього | J75: 3.1364798e+08 | K75: 0 | L75: 3.1364798e+08 | M75: 3.2641144e+08 | O75: 0 | P75: 3.2641144e+08 | Q75: 19318684 | R75: 0 | S75: 19318684
A76: 69 | D76: 151 | F76: 1510 | H76: Депозити овернайт, що розміщені в інших банках, які обліковуються за амортизованою собівартістю | I76: А | J76: 74603214 | K76: 0 | L76: 74603214 | M76: 72046728 | O76: 0 | P76: 72046728 | Q76: 4142955.3 | R76: 0 | S76: 4142955.3
A77: 70 | F77: 1513 | H77: Строкові вклади (депозити), що розміщені в інших банках, які обліковуються за амортизованою собівартістю | I77: А | J77: 86228495 | K77: 0 | L77: 86228495 | M77: 91098120 | O77: 0 | P77: 91098120 | Q77: 17639998 | R77: 0 | S77: 17639998
A78: 71 | F78: 1516 | H78: Неамортизована премія/дисконт за строковими вкладами (депозитами), що розміщені в інших банках, які обліковуються за амортизованою собівартістю | I78: А | J78: 4.0487 | K78: 0 | L78: 4.0487 | M78: 3.80429 | O78: 0 | P78: 3.80429 | Q78: 0 | R78: 0 | S78: 0
A79: 72 | I79: П | J79: 0 | K79: 0 | L79: 0 | M79: 0 | O79: 0 | P79: 0 | Q79: -0.41685 | R79: 0 | S79: -0.41685
A80: 73 | F80: 1518 | H80: Нараховані доходи за строковими вкладами (депозитами), що розміщені в інших банках, які обліковуються за амортизованою собівартістю | I80: А | J80: 52849.531 | K80: 0 | L80: 52849.531 | M80: 49276.997 | O80: 0 | P80: 49276.997 | Q80: 8688.0442 | R80: 0 | S80: 8688.0442
A81: 74 | F81: 1519 | H81: Резерв за строковими вкладами (депозитами), що розміщені в інших банках, які обліковуються за амортизованою собівартістю | I81: П | J81: 17599.6 | K81: 0 | L81: 17599.6 | M81: 15879.439 | O81: 0 | P81: 15879.439 | Q81: -15515.792 | R81: 0 | S81: -15515.792
A82: 75 | F82: Група 151 - Усього | J82: 1.6090216e+08 | K82: 0 | L82: 1.6090216e+08 | M82: 1.6321001e+08 | O82: 0 | P82: 1.6321001e+08 | Q82: 21776125 | R82: 0 | S82: 21776125
A83: 76 | D83: 152 | F83: 1521 | H83: Кредити овернайт, що надані іншим банкам,які обліковуються за амортизованою собівартістю | I83: А | J83: 0 | K83: 0 | L83: 0 | M83: 0 | O83: 0 | P83: 0 | Q83: 0 | R83: 0 | S83: 0
A84: 77 | F84: 1522 | H84: Кредити, що надані іншим банкам за операціями репо, які обліковуються за амортизованою собівартістю | I84: А | J84: 0 | K84: 0 | L84: 0 | M84: 0 | O84: 0 | P84: 0 | Q84: 0 | R84: 0 | S84: 0
A85: 78 | F85: 1524 | H85: Інші кредити, що надані іншим банкам, які обліковуються за амортизованою собівартістю | I85: А | J85: 2.02856 | K85: 0 | L85: 2.02856 | M85: 1.34819 | O85: 0 | P85: 1.34819 | Q85: 128.90196 | R85: 0 | S85: 128.90196
A86: 79 | F86: 1526 | H86: Неамортизована премія/дисконт за кредитами, що надані іншим банкам, які обліковуються за амортизованою собівартістю | I86: А | J86: 0 | K86: 0 | L86: 0 | M86: 0 | O86: 0 | P86: 0 | Q86: 0 | R86: 0 | S86: 0
A87: 80 | I87: П | J87: 0 | K87: 0 | L87: 0 | M87: 0 | O87: 0 | P87: 0 | Q87: 0 | R87: 0 | S87: 0
A88: 81 | F88: 1528 | H88: Нараховані доходи за кредитами, що надані іншим банкам, які обліковуються за амортизованою собівартістю | I88: А | J88: 0 | K88: 0 | L88: 0 | M88: 0 | O88: 0 | P88: 0 | Q88: 0 | R88: 0 | S88: 0
A89: 82 | F89: 1529 | H89: Резерв за кредитами, що надані іншим банкам, які обліковуються за амортизованою собівартістю | I89: П | J89: 1.34819 | K89: 0 | L89: 1.34819 | M89: 2.02856 | O89: 0 | P89: 2.02856 | Q89: -128.90196 | R89: 0 | S89: -128.90196
A90: 83 | F90: Група 152 - Усього | J90: 3.37675 | K90: 0 | L90: 3.37675 | M90: 3.37675 | O90: 0 | P90: 3.37675 | Q90: 0 | R90: 0 | S90: 0
A91: 84 | D91: Розділ 15 - Усього | J91: 4.7455014e+08 | K91: 0 | L91: 4.7455014e+08 | M91: 4.8962145e+08 | O91: 0 | P91: 4.8962145e+08 | Q91: 41094809 | R91: 0 | S91: 41094809
A92: 85 | C92: 16 | D92: 160 | F92: 1600 | H92: Кореспондентські рахунки інших банків | I92: А | J92: 1.7744514e+08 | K92: 1.1679258e+08 | L92: 60652553 | M92: 1.7927967e+08 | O92: 1.1871715e+08 | P92: 60562517 | Q92: 0 | R92: 0 | S92: 0
A93: 86 | F93: Група 160 - Усього | J93: 1.7744514e+08 | K93: 1.1679258e+08 | L93: 60652553 | M93: 1.7927967e+08 | O93: 1.1871715e+08 | P93: 60562517 | Q93: 0 | R93: 0 | S93: 0
A94: 87 | D94: Розділ 16 - Усього | J94: 1.7744514e+08 | K94: 1.1679258e+08 | L94: 60652553 | M94: 1.7927967e+08 | O94: 1.1871715e+08 | P94: 60562517 | Q94: 0 | R94: 0 | S94: 0
A95: 88 | C95: 18 | D95: 181 | F95: 1811 | H95: Дебіторська заборгованість за операціями з готівкою | I95: А | J95: 2967453.3 | K95: 1944259 | L95: 1023194.3 | M95: 2967553.3 | O95: 1944359 | P95: 1023194.3 | Q95: 4200 | R95: 4200 | S95: 0
A96: 89 | F96: 1819 | H96: Інша дебіторська заборгованість за операціями з банками | I96: А | J96: 34369.644 | K96: 2968.9512 | L96: 31400.693 | M96: 14188.135 | O96: 2375.0529 | P96: 11813.083 | Q96: 20181.508 | R96: 593.89829 | S96: 19587.61
A97: 90 | F97: Група 181 - Усього | J97: 3001823 | K97: 1947228 | L97: 1054595 | M97: 2981741.5 | O97: 1946734.1 | P97: 1035007.4 | Q97: 24381.508 | R97: 4793.8983 | S97: 19587.61
A98: 91 | D98: 183 | F98: 1832 | H98: Кошти банків у розрахунках | I98: А | J98: 18562.838 | K98: 0 | L98: 18562.838 | M98: 20387.93 | O98: 0 | P98: 20387.93 | Q98: 954406.21 | R98: 20 | S98: 954386.21
A99: 92 | F99: 1839 | H99: Резерви за коштами банків у розрахунках | I99: П | J99: 17.24608 | K99: 0 | L99: 17.24608 | M99: 18.66862 | O99: 0 | P99: 18.66862 | Q99: -1049.6683 | R99: 0 | S99: -1049.6683
A100: 93 | F100: Група 183 - Усього | J100: 18580.084 | K100: 0 | L100: 18580.084 | M100: 20406.598 | O100: 0 | P100: 20406.598 | Q100: 953356.54 | R100: 20 | S100: 953336.54
...

Sheet   6АТ "Ощадбанк" 
A1: Зміст
B2: Оборотно-сальдовий баланс банку АТ "Ощадбанк" за станом на 01.12.2025
B3: (тис грн)
A4: Номер з/п | B4: Клас/ розділ/ група/ рахунок | I4: Актив/ пасив | J4: Обороти за місяць | Q4: Сальдо
J5: дебет | M5: кредит | Q5: усього | R5: НВ | S5: ІВ
B6: номер | F6: назва | J6: усього | K6: НВ | L6: ІВ | M6: усього | O6: НВ | P6: ІВ
A7: 1 | B7: 2 | F7: 3 | I7: 4 | J7: 5 | K7: 6 | L7: 7 | M7: 8 | O7: 9 | P7: 10 | Q7: 11 | R7: 12 | S7: 13
A8: 1 | B8: Балансові рахунки
A9: 2 | B9: Активи
A10: 3 | B10: Класи 1 - 4
A11: 4 | B11: Клас 1 | C11: 10 | D11: 100 | F11: 1001 | H11: Банкноти та монети в касі банку | I11: А | J11: 3.4685127e+08 | K11: 2.4845102e+08 | L11: 98400245 | M11: 3.5018686e+08 | O11: 2.4865152e+08 | P11: 1.0153534e+08 | Q11: 11370724 | R11: 4710103.9 | S11: 6660620.3
A12: 5 | F12: 1002 | H12: Банкноти та монети в касі відділень банку | I12: А | J12: 31969781 | K12: 22111338 | L12: 9858442.6 | M12: 31953367 | O12: 22110933 | P12: 9842434.8 | Q12: 1614023.6 | R12: 1006363.3 | S12: 607660.37
A13: 6 | F13: 1004 | H13: Банкноти та монети в банкоматах | I13: А | J13: 29224510 | K13: 29224510 | L13: 0 | M13: 29744829 | O13: 29744829 | P13: 0 | Q13: 3450082.5 | R13: 3450082.5 | S13: 0
A14: 7 | F14: 1005 | H14: Банкноти та монети, інкасовані до перерахування | I14: А | J14: 47127459 | K14: 47127459 | L14: 0 | M14: 47127459 | O14: 47127459 | P14: 0 | Q14: 0 | R14: 0 | S14: 0
A15: 8 | F15: 1006 | H15: Банкноти та монети на зберіганні в інкасаторській компанії | I15: А | J15: 0 | K15: 0 | L15: 0 | M15: 0 | O15: 0 | P15: 0 | Q15: 0 | R15: 0 | S15: 0
A16: 9 | F16: 1007 | H16: Банкноти та монети в дорозі | I16: А | J16: 1.4916987e+08 | K16: 1.0183119e+08 | L16: 47338684 | M16: 1.4921505e+08 | O16: 1.0185275e+08 | P16: 47362306 | Q16: 56256.937 | R16: 39168.454 | S16: 17088.483
A17: 10 | F17: Група 100 - Усього | J17: 6.0434289e+08 | K17: 4.4874552e+08 | L17: 1.5559737e+08 | M17: 6.0822757e+08 | O17: 4.4948749e+08 | P17: 1.5874008e+08 | Q17: 16491087 | R17: 9205718.1 | S17: 7285369.1
A18: 11 | D18: 101 | F18: 1011 | H18: Дорожні чеки в касі банку | I18: А | J18: 0 | K18: 0 | L18: 0 | M18: 0 | O18: 0 | P18: 0 | Q18: 0 | R18: 0 | S18: 0
A19: 12 | F19: 1012 | H19: Дорожні чеки в касі відділень банку | I19: А | J19: 0 | K19: 0 | L19: 0 | M19: 0 | O19: 0 | P19: 0 | Q19: 0 | R19: 0 | S19: 0
A20: 13 | F20: Група 101 - Усього | J20: 0 | K20: 0 | L20: 0 | M20: 0 | O20: 0 | P20: 0 | Q20: 0 | R20: 0 | S20: 0
A21: 14 | D21: 109 | F21: 1090 | H21: Резерви за готівковими коштами, наявність яких є непідтвердженою | I21: П | J21: 237.41988 | K21: 0 | L21: 237.41988 | M21: 355.90706 | O21: 0 | P21: 355.90706 | Q21: -95002.152 | R21: -73346.687 | S21: -21655.464
A22: 15 | F22: Група 109 - Усього | J22: 237.41988 | K22: 0 | L22: 237.41988 | M22: 355.90706 | O22: 0 | P22: 355.90706 | Q22: -95002.152 | R22: -73346.687 | S22: -21655.464
A23: 16 | D23: Розділ 10 - Усього | J23: 6.0434313e+08 | K23: 4.4874552e+08 | L23: 1.5559761e+08 | M23: 6.0822792e+08 | O23: 4.4948749e+08 | P23: 1.5874043e+08 | Q23: 16396085 | R23: 9132371.4 | S23: 7263713.6
A24: 17 | C24: 11 | D24: 110 | F24: 1101 | H24: Банківські метали в банку | I24: А | J24: 353637.25 | K24: 0 | L24: 353637.25 | M24: 350748.1 | O24: 0 | P24: 350748.1 | Q24: 55025.842 | R24: 0 | S24: 55025.842
A25: 18 | F25: 1102 | H25: Банківські метали у відділенні банку | I25: А | J25: 7770.1245 | K25: 0 | L25: 7770.1245 | M25: 10121.918 | O25: 0 | P25: 10121.918 | Q25: 19871.401 | R25: 0 | S25: 19871.401
A26: 19 | F26: 1107 | H26: Банківські метали в дорозі | I26: А | J26: 11032.816 | K26: 0 | L26: 11032.816 | M26: 11032.816 | O26: 0 | P26: 11032.816 | Q26: 0 | R26: 0 | S26: 0
A27: 20 | F27: Група 110 - Усього | J27: 372440.19 | K27: 0 | L27: 372440.19 | M27: 371902.84 | O27: 0 | P27: 371902.84 | Q27: 74897.243 | R27: 0 | S27: 74897.243
A28: 21 | D28: 119 | F28: 1190 | H28: Резерви за банківськими металами, наявність яких є непідтвердженою | I28: П | J28: 141.65131 | K28: 0 | L28: 141.65131 | M28: 238.78803 | O28: 0 | P28: 238.78803 | Q28: -1517.55 | R28: 0 | S28: -1517.55
A29: 22 | F29: Група 119 - Усього | J29: 141.65131 | K29: 0 | L29: 141.65131 | M29: 238.78803 | O29: 0 | P29: 238.78803 | Q29: -1517.55 | R29: 0 | S29: -1517.55
A30: 23 | D30: Розділ 11 - Усього | J30: 372581.84 | K30: 0 | L30: 372581.84 | M30: 372141.62 | O30: 0 | P30: 372141.62 | Q30: 73379.693 | R30: 0 | S30: 73379.693
A31: 24 | C31: 12 | D31: 120 | F31: 1200 | H31: Кореспондентський рахунок банку в Національному банку України | I31: А | J31: 1.0789626e+09 | K31: 1.0789626e+09 | L31: 0 | M31: 1.0803335e+09 | O31: 1.0803335e+09 | P31: 0 | Q31: 27081639 | R31: 27081639 | S31: 0
A32: 25 | F32: 1202 | H32: Кошти банків за рахунками умовного зберігання (ескроу) у Національному банку України | I32: А | J32: 3329.2404 | K32: 0 | L32: 3329.2404 | M32: 14823.453 | O32: 0 | P32: 14823.453 | Q32: 215803.38 | R32: 8000 | S32: 207803.38
A33: 26 | F33: 1205 | H33: Кошти банків для забезпечення виконання зобов’язань перед Національним банком України за кредитами, наданими банкам, та операціями своп процентної ставки | I33: А | J33: 0 | K33: 0 | L33: 0 | M33: 0 | O33: 0 | P33: 0 | Q33: 0 | R33: 0 | S33: 0
A34: 27 | F34: 1208 | H34: Нараховані доходи за коштами на вимогу в Національному банку України | I34: А | J34: 811.15567 | K34: 0 | L34: 811.15567 | M34: 811.15567 | O34: 0 | P34: 811.15567 | Q34: 0 | R34: 0 | S34: 0
A35: 28 | F35: Група 120 - Усього | J35: 1.0789667e+09 | K35: 1.0789626e+09 | L35: 4140.3961 | M35: 1.0803491e+09 | O35: 1.0803335e+09 | P35: 15634.608 | Q35: 27297443 | R35: 27089639 | S35: 207803.38
A36: 29 | D36: Розділ 12 - Усього | J36: 1.0789667e+09 | K36: 1.0789626e+09 | L36: 4140.3961 | M36: 1.0803491e+09 | O36: 1.0803335e+09 | P36: 15634.608 | Q36: 27297443 | R36: 27089639 | S36: 207803.38
A37: 30 | C37: 14 | D37: 140 | F37: 1400 | H37: Облігації внутрішньої державної позики, що рефінансуються Національним банком України, які обліковуються за справедливою вартістю через прибутки/збитки | I37: А | J37: 402056.77 | K37: 76007 | L37: 326049.77 | M37: 2679493.6 | O37: 2465739 | P37: 213754.59 | Q37: 9443620.9 | R37: 9299484 | S37: 144136.92
A38: 31 | F38: 1405 | H38: Переоцінка боргових цінних паперів, що рефінансуються Національним банком України, які обліковуються за справедливою вартістю через прибутки/збитки | I38: А | J38: 23052699 | K38: 23044353 | L38: 8346.2078 | M38: 24877155 | O38: 24868699 | P38: 8456.1116 | Q38: 6439810.9 | R38: 6439610.5 | S38: 200.37088
A39: 32 | I39: П | J39: 0 | K39: 0 | L39: 0 | M39: 0 | O39: 0 | P39: 0 | Q39: -1020862.9 | R39: -1020455.3 | S39: -407.55967
A40: 33 | F40: 1406 | H40: Неамортизована премія/дисконт за борговими цінними паперами, що рефінансуються Національним банком України, які обліковуються за справедливою вартістю через прибутки/збитки | I40: А | J40: 25594.433 | K40: 25481.393 | L40: 113.03955 | M40: 152.61538 | O40: 28.25133 | P40: 124.36405 | Q40: 18.27385 | R40: 18.27385 | S40: 0
A41: 34 | I41: П | J41: 0 | K41: 0 | L41: 0 | M41: 0 | O41: 0 | P41: 0 | Q41: -1179755.9 | R41: -1179742.7 | S41: -13.25933
A42: 35 | F42: 1408 | H42: Нараховані доходи за борговими цінними паперами, що рефінансуються Національним банком України, які обліковуються за справедливою вартістю через прибутки/збитки | I42: А | J42: 60216.512 | K42: 54999.389 | L42: 5217.1223 | M42: 89738.799 | O42: 86296.267 | P42: 3442.5327 | Q42: 158244.51 | R42: 155993.68 | S42: 2250.8322
A43: 36 | F43: Група 140 - Усього | J43: 23540567 | K43: 23200841 | L43: 339726.14 | M43: 27646540 | O43: 27420762 | P43: 225777.6 | Q43: 13841076 | R43: 13694908 | S43: 146167.31
A44: 37 | D44: 141 | F44: 1410 | H44: Облігації внутрішньої державної позики, що рефінансуються Національним банком України, які обліковуються за справедливою вартістю через інший сукупний дохід | I44: А | J44: 0 | K44: 0 | L44: 0 | M44: 0 | O44: 0 | P44: 0 | Q44: 0 | R44: 0 | S44: 0
A45: 38 | F45: 1411 | H45: Облігації зовнішньої державної позики, що рефінансуються Національним банком України, які обліковуються за справедливою вартістю через інший сукупний дохід | I45: А | J45: 0 | K45: 0 | L45: 0 | M45: 0 | O45: 0 | P45: 0 | Q45: 0 | R45: 0 | S45: 0
A46: 39 | F46: 1412 | H46: Боргові цінні папери органів державної влади та місцевого самоврядування, що рефінансуються Національним банком України, які обліковуються за справедливою вартістю через інший сукупний дохід | I46: А | J46: 0 | K46: 0 | L46: 0 | M46: 0 | O46: 0 | P46: 0 | Q46: 0 | R46: 0 | S46: 0
A47: 40 | F47: 1415 | H47: Переоцінка боргових цінних паперів, що рефінансуються Національним банком України, які обліковуються за справедливою вартістю через інший сукупний дохід | I47: А | J47: 0 | K47: 0 | L47: 0 | M47: 0 | O47: 0 | P47: 0 | Q47: 0 | R47: 0 | S47: 0
A48: 41 | I48: П | J48: 0 | K48: 0 | L48: 0 | M48: 0 | O48: 0 | P48: 0 | Q48: 0 | R48: 0 | S48: 0
A49: 42 | F49: 1416 | H49: Неамортизована премія/дисконт за борговими цінними паперами, що рефінансуються Національним банком України, які обліковуються за справедливою вартістю через інший сукупний дохід | I49: А | J49: 0 | K49: 0 | L49: 0 | M49: 0 | O49: 0 | P49: 0 | Q49: 0 | R49: 0 | S49: 0
A50: 43 | I50: П | J50: 0 | K50: 0 | L50: 0 | M50: 0 | O50: 0 | P50: 0 | Q50: 0 | R50: 0 | S50: 0
A51: 44 | F51: 1418 | H51: Нараховані доходи за борговими цінними паперами, що рефінансуються Національним банком України, які обліковуються за справедливою вартістю через інший сукупний дохід | I51: А | J51: 0 | K51: 0 | L51: 0 | M51: 0 | O51: 0 | P51: 0 | Q51: 0 | R51: 0 | S51: 0
A52: 45 | F52: 1419 | H52: Резерв за борговими цінними паперами,що рефінансуються Національним банком України, які обліковуються за справедливою вартістю через інший сукупний дохід | I52: П | J52: 0 | K52: 0 | L52: 0 | M52: 0 | O52: 0 | P52: 0 | Q52: 0 | R52: 0 | S52: 0
A53: 46 | F53: Група 141 - Усього | J53: 0 | K53: 0 | L53: 0 | M53: 0 | O53: 0 | P53: 0 | Q53: 0 | R53: 0 | S53: 0
A54: 47 | D54: 142 | F54: 1420 | H54: Облігації внутрішньої державної позики, що рефінансуються Національним банком України, які обліковуються за амортизованою собівартістю | I54: А | J54: 6188314.2 | K54: 4765117 | L54: 1423197.2 | M54: 606851.79 | O54: 500000 | P54: 106851.79 | Q54: 1.7197093e+08 | R54: 161271552 | S54: 10699381
A55: 48 | F55: 1426 | H55: Неамортизована премія/дисконт за борговими цінними паперами, що рефінансуються Національним банком України, які обліковуються за амортизованою собівартістю | I55: А | J55: 12004.823 | K55: 6449.5663 | L55: 5555.2569 | M55: 14354.146 | O55: 13847.788 | P55: 506.35825 | Q55: 143996.94 | R55: 143847.82 | S55: 149.12497
A56: 49 | I56: П | J56: 0 | K56: 0 | L56: 0 | M56: 0 | O56: 0 | P56: 0 | Q56: -214341.87 | R56: -187561.43 | S56: -26780.439
A57: 50 | F57: 1428 | H57: Нараховані доходи за борговими цінними паперами, що рефінансуються Національним банком України, які обліковуються за амортизованою собівартістю | I57: А | J57: 2361720.6 | K57: 2312602.5 | L57: 49118.167 | M57: 2458317.1 | O57: 2457584.5 | P57: 732.52838 | Q57: 5846430.8 | R57: 5739488.5 | S57: 106942.28
A58: 51 | F58: 1429 | H58: Резерв за борговими цінними паперами,що рефінансуються Національним банком України, які обліковуються за амортизованою собівартістю | I58: П | J58: 874262.74 | K58: 817862.74 | L58: 56400.003 | M58: 901707.33 | O58: 811387.02 | P58: 90320.309 | Q58: -2121424.6 | R58: -1851252.3 | S58: -270172.26
A59: 52 | F59: Група 142 - Усього | J59: 9436302.5 | K59: 7902031.8 | L59: 1534270.7 | M59: 3981230.3 | O59: 3782819.3 | P59: 198410.99 | Q59: 1.7562559e+08 | R59: 1.6511607e+08 | S59: 10509519
A60: 53 | D60: 143 | F60: 1430 | H60: Депозитні сертифікати Національного банку України, розміщені в банках України, що обліковуються за справедливою вартістю через інший сукупний дохід | I60: А | J60: 0 | K60: 0 | L60: 0 | M60: 0 | O60: 0 | P60: 0 | Q60: 0 | R60: 0 | S60: 0
A61: 54 | F61: 1435 | H61: Переоцінка депозитних сертифікатів Національного банку України, розміщених у банках України, що обліковуються за справедливою вартістю через інший сукупний дохід | I61: А | J61: 0 | K61: 0 | L61: 0 | M61: 0 | O61: 0 | P61: 0 | Q61: 0 | R61: 0 | S61: 0
A62: 55 | F62: 1436 | H62: Неамортизована премія/дисконт за депозитними сертифікатами Національного банку України, розміщеними в банках України, що обліковуються за справедливою вартістю через інший сукупний дохід | I62: А | J62: 0 | K62: 0 | L62: 0 | M62: 0 | O62: 0 | P62: 0 | Q62: 0 | R62: 0 | S62: 0
A63: 56 | I63: П | J63: 0 | K63: 0 | L63: 0 | M63: 0 | O63: 0 | P63: 0 | Q63: 0 | R63: 0 | S63: 0
A64: 57 | F64: 1438 | H64: Нараховані доходи за депозитними сертифікатами Національного банку України, розміщеними в банках України, що обліковуються за справедливою вартістю через інший сукупний дохід | I64: А | J64: 0 | K64: 0 | L64: 0 | M64: 0 | O64: 0 | P64: 0 | Q64: 0 | R64: 0 | S64: 0
A65: 58 | F65: Група 143 - Усього | J65: 0 | K65: 0 | L65: 0 | M65: 0 | O65: 0 | P65: 0 | Q65: 0 | R65: 0 | S65: 0
A66: 59 | D66: 144 | F66: 1440 | H66: Депозитні сертифікати Національного банку України, розміщені в банках України, що обліковуються за амортизованою собівартістю | I66: А | J66: 607600000 | K66: 607600000 | L66: 0 | M66: 602600000 | O66: 602600000 | P66: 0 | Q66: 29800000 | R66: 29800000 | S66: 0
A67: 60 | F67: 1446 | H67: Неамортизована премія/дисконт за депозитними сертифікатами Національного банку України, розміщеними в банках України, що обліковуються за амортизованою собівартістю | I67: А | J67: 0 | K67: 0 | L67: 0 | M67: 0 | O67: 0 | P67: 0 | Q67: 0 | R67: 0 | S67: 0
A68: 61 | I68: П | J68: 0 | K68: 0 | L68: 0 | M68: 0 | O68: 0 | P68: 0 | Q68: 0 | R68: 0 | S68: 0
A69: 62 | F69: 1448 | H69: Нараховані доходи за депозитними сертифікатами Національного банку України, розміщеними в банках України, що обліковуються за амортизованою собівартістю | I69: А | J69: 446239.16 | K69: 446239.16 | L69: 0 | M69: 542648.85 | O69: 542648.85 | P69: 0 | Q69: 86714.999 | R69: 86714.999 | S69: 0
A70: 63 | F70: Група 144 - Усього | J70: 6.0804624e+08 | K70: 6.0804624e+08 | L70: 0 | M70: 6.0314265e+08 | O70: 6.0314265e+08 | P70: 0 | Q70: 29886715 | R70: 29886715 | S70: 0
A71: 64 | D71: Розділ 14 - Усього | J71: 6.4102311e+08 | K71: 6.3914911e+08 | L71: 1873996.8 | M71: 6.3477042e+08 | O71: 6.3434623e+08 | P71: 424188.59 | Q71: 2.1935338e+08 | R71: 2.086977e+08 | S71: 10655687
A72: 65 | C72: 15 | D72: 150 | F72: 1500 | H72: Кореспондентські рахунки, що відкриті в інших банках | I72: А | J72: 3.8006853e+08 | K72: 14186834 | L72: 3.658817e+08 | M72: 3.9397445e+08 | O72: 14186842 | P72: 3.7978761e+08 | Q72: 24162903 | R72: 400025.42 | S72: 23762878
A73: 66 | F73: 1508 | H73: Нараховані доходи за коштами на вимогу в інших банках | I73: А | J73: 95880.139 | K73: 0 | L73: 95880.139 | M73: 87809.74 | O73: 0 | P73: 87809.74 | Q73: 8070.3987 | R73: 0 | S73: 8070.3987
A74: 67 | F74: 1509 | H74: Резерв за коштами на вимогу в інших банках | I74: П | J74: 29.61437 | K74: 0.00154 | L74: 29.61283 | M74: 1.81257 | O74: 0 | P74: 1.81257 | Q74: -167.13693 | R74: -74.82697 | S74: -92.30996
A75: 68 | F75: Група 150 - Усього | J75: 3.8016444e+08 | K75: 14186834 | L75: 3.6597761e+08 | M75: 3.9406227e+08 | O75: 14186842 | P75: 3.7987542e+08 | Q75: 24170807 | R75: 399950.59 | S75: 23770856
A76: 69 | D76: 151 | F76: 1510 | H76: Депозити овернайт, що розміщені в інших банках, які обліковуються за амортизованою собівартістю | I76: А | J76: 0 | K76: 0 | L76: 0 | M76: 0 | O76: 0 | P76: 0 | Q76: 0 | R76: 0 | S76: 0
A77: 70 | F77: 1513 | H77: Строкові вклади (депозити), що розміщені в інших банках, які обліковуються за амортизованою собівартістю | I77: А | J77: 0 | K77: 0 | L77: 0 | M77: 0 | O77: 0 | P77: 0 | Q77: 0 | R77: 0 | S77: 0
A78: 71 | F78: 1516 | H78: Неамортизована премія/дисконт за строковими вкладами (депозитами), що розміщені в інших банках, які обліковуються за амортизованою собівартістю | I78: А | J78: 0 | K78: 0 | L78: 0 | M78: 0 | O78: 0 | P78: 0 | Q78: 0 | R78: 0 | S78: 0
A79: 72 | I79: П | J79: 0 | K79: 0 | L79: 0 | M79: 0 | O79: 0 | P79: 0 | Q79: 0 | R79: 0 | S79: 0
A80: 73 | F80: 1518 | H80: Нараховані доходи за строковими вкладами (депозитами), що розміщені в інших банках, які обліковуються за амортизованою собівартістю | I80: А | J80: 0 | K80: 0 | L80: 0 | M80: 0 | O80: 0 | P80: 0 | Q80: 0 | R80: 0 | S80: 0
A81: 74 | F81: 1519 | H81: Резерв за строковими вкладами (депозитами), що розміщені в інших банках, які обліковуються за амортизованою собівартістю | I81: П | J81: 0 | K81: 0 | L81: 0 | M81: 0 | O81: 0 | P81: 0 | Q81: 0 | R81: 0 | S81: 0
A82: 75 | F82: Група 151 - Усього | J82: 0 | K82: 0 | L82: 0 | M82: 0 | O82: 0 | P82: 0 | Q82: 0 | R82: 0 | S82: 0
A83: 76 | D83: 152 | F83: 1521 | H83: Кредити овернайт, що надані іншим банкам,які обліковуються за амортизованою собівартістю | I83: А | J83: 2.2109571e+08 | K83: 0 | L83: 2.2109571e+08 | M83: 2.0982096e+08 | O83: 0 | P83: 2.0982096e+08 | Q83: 11274747 | R83: 0 | S83: 11274747
A84: 77 | F84: 1522 | H84: Кредити, що надані іншим банкам за операціями репо, які обліковуються за амортизованою собівартістю | I84: А | J84: 0 | K84: 0 | L84: 0 | M84: 0 | O84: 0 | P84: 0 | Q84: 0 | R84: 0 | S84: 0
A85: 78 | F85: 1524 | H85: Інші кредити, що надані іншим банкам, які обліковуються за амортизованою собівартістю | I85: А | J85: 0 | K85: 0 | L85: 0 | M85: 0 | O85: 0 | P85: 0 | Q85: 0 | R85: 0 | S85: 0
A86: 79 | F86: 1526 | H86: Неамортизована премія/дисконт за кредитами, що надані іншим банкам, які обліковуються за амортизованою собівартістю | I86: А | J86: 0 | K86: 0 | L86: 0 | M86: 0 | O86: 0 | P86: 0 | Q86: 0 | R86: 0 | S86: 0
A87: 80 | I87: П | J87: 0 | K87: 0 | L87: 0 | M87: 0 | O87: 0 | P87: 0 | Q87: 0 | R87: 0 | S87: 0
A88: 81 | F88: 1528 | H88: Нараховані доходи за кредитами, що надані іншим банкам, які обліковуються за амортизованою собівартістю | I88: А | J88: 15802.229 | K88: 0 | L88: 15802.229 | M88: 14111.017 | O88: 0 | P88: 14111.017 | Q88: 1691.2121 | R88: 0 | S88: 1691.2121
A89: 82 | F89: 1529 | H89: Резерв за кредитами, що надані іншим банкам, які обліковуються за амортизованою собівартістю | I89: П | J89: 0 | K89: 0 | L89: 0 | M89: 16.12626 | O89: 0 | P89: 16.12626 | Q89: -16.12626 | R89: 0 | S89: -16.12626
A90: 83 | F90: Група 152 - Усього | J90: 2.2111151e+08 | K90: 0 | L90: 2.2111151e+08 | M90: 2.0983509e+08 | O90: 0 | P90: 2.0983509e+08 | Q90: 11276422 | R90: 0 | S90: 11276422
A91: 84 | D91: Розділ 15 - Усього | J91: 6.0127595e+08 | K91: 14186834 | L91: 5.8708912e+08 | M91: 6.0389735e+08 | O91: 14186842 | P91: 5.8971051e+08 | Q91: 35447229 | R91: 399950.59 | S91: 35047278
A92: 85 | C92: 16 | D92: 160 | F92: 1600 | H92: Кореспондентські рахунки інших банків | I92: А | J92: 3830429.1 | K92: 101.23389 | L92: 3830327.8 | M92: 4005131.8 | O92: 40.28656 | P92: 4005091.6 | Q92: 0 | R92: 0 | S92: 0
A93: 86 | F93: Група 160 - Усього | J93: 3830429.1 | K93: 101.23389 | L93: 3830327.8 | M93: 4005131.8 | O93: 40.28656 | P93: 4005091.6 | Q93: 0 | R93: 0 | S93: 0
A94: 87 | D94: Розділ 16 - Усього | J94: 3830429.1 | K94: 101.23389 | L94: 3830327.8 | M94: 4005131.8 | O94: 40.28656 | P94: 4005091.6 | Q94: 0 | R94: 0 | S94: 0
A95: 88 | C95: 18 | D95: 181 | F95: 1811 | H95: Дебіторська заборгованість за операціями з готівкою | I95: А | J95: 75396669 | K95: 54415570 | L95: 20981099 | M95: 75396669 | O95: 54415570 | P95: 20981099 | Q95: 0 | R95: 0 | S95: 0
A96: 89 | F96: 1819 | H96: Інша дебіторська заборгованість за операціями з банками | I96: А | J96: 1.3212026e+08 | K96: 13115588 | L96: 1.1900467e+08 | M96: 1.3212026e+08 | O96: 13115588 | P96: 1.1900467e+08 | Q96: 0 | R96: 0 | S96: 0
A97: 90 | F97: Група 181 - Усього | J97: 2.0751693e+08 | K97: 67531158 | L97: 1.3998577e+08 | M97: 2.0751693e+08 | O97: 67531158 | P97: 1.3998577e+08 | Q97: 0 | R97: 0 | S97: 0
A98: 91 | D98: 183 | F98: 1832 | H98: Кошти банків у розрахунках | I98: А | J98: 0 | K98: 0 | L98: 0 | M98: 0 | O98: 0 | P98: 0 | Q98: 100 | R98: 100 | S98: 0
A99: 92 | F99: 1839 | H99: Резерви за коштами банків у розрахунках | I99: П | J99: 0 | K99: 0 | L99: 0 | M99: 0 | O99: 0 | P99: 0 | Q99: 0 | R99: 0 | S99: 0
A100: 93 | F100: Група 183 - Усього | J100: 0 | K100: 0 | L100: 0 | M100: 0 | O100: 0 | P100: 0 | Q100: 100 | R100: 100 | S100: 0
...

Sheet  29АТ "БАНК АЛЬЯНС" 
A1: Зміст
B2: Оборотно-сальдовий баланс банку АТ "БАНК АЛЬЯНС" за станом на 01.12.2025
B3: (тис грн)
A4: Номер з/п | B4: Клас/ розділ/ група/ рахунок | I4: Актив/ пасив | J4: Обороти за місяць | Q4: Сальдо
J5: дебет | M5: кредит | Q5: усього | R5: НВ | S5: ІВ
B6: номер | F6: назва | J6: усього | K6: НВ | L6: ІВ | M6: усього | O6: НВ | P6: ІВ
A7: 1 | B7: 2 | F7: 3 | I7: 4 | J7: 5 | K7: 6 | L7: 7 | M7: 8 | O7: 9 | P7: 10 | Q7: 11 | R7: 12 | S7: 13
A8: 1 | B8: Балансові рахунки
A9: 2 | B9: Активи
A10: 3 | B10: Класи 1 - 4
A11: 4 | B11: Клас 1 | C11: 10 | D11: 100 | F11: 1001 | H11: Банкноти та монети в касі банку | I11: А | J11: 0 | K11: 0 | L11: 0 | M11: 0 | O11: 0 | P11: 0 | Q11: 0 | R11: 0 | S11: 0
A12: 5 | F12: 1002 | H12: Банкноти та монети в касі відділень банку | I12: А | J12: 2593930.3 | K12: 1334258.6 | L12: 1259671.7 | M12: 2598171.3 | O12: 1369257 | P12: 1228914.4 | Q12: 334285.1 | R12: 261019.39 | S12: 73265.712
A13: 6 | F13: 1004 | H13: Банкноти та монети в банкоматах | I13: А | J13: 706213.23 | K13: 370477.18 | L13: 335736.05 | M13: 686788.71 | O13: 345935.06 | P13: 340853.65 | Q13: 60657.867 | R13: 40737.359 | S13: 19920.508
A14: 7 | F14: 1005 | H14: Банкноти та монети, інкасовані до перерахування | I14: А | J14: 10646.788 | K14: 10646.788 | L14: 0 | M14: 10646.788 | O14: 10646.788 | P14: 0 | Q14: 0 | R14: 0 | S14: 0
A15: 8 | F15: 1006 | H15: Банкноти та монети на зберіганні в інкасаторській компанії | I15: А | J15: 0 | K15: 0 | L15: 0 | M15: 0 | O15: 0 | P15: 0 | Q15: 0 | R15: 0 | S15: 0
A16: 9 | F16: 1007 | H16: Банкноти та монети в дорозі | I16: А | J16: 865633.92 | K16: 461294.02 | L16: 404339.9 | M16: 865633.92 | O16: 461294.02 | P16: 404339.9 | Q16: 0 | R16: 0 | S16: 0
A17: 10 | F17: Група 100 - Усього | J17: 4176424.2 | K17: 2176676.6 | L17: 1999747.7 | M17: 4161240.8 | O17: 2187132.8 | P17: 1974107.9 | Q17: 394942.97 | R17: 301756.75 | S17: 93186.219
A18: 11 | D18: 101 | F18: 1011 | H18: Дорожні чеки в касі банку | I18: А | J18: 0 | K18: 0 | L18: 0 | M18: 0 | O18: 0 | P18: 0 | Q18: 0 | R18: 0 | S18: 0
A19: 12 | F19: 1012 | H19: Дорожні чеки в касі відділень банку | I19: А | J19: 0 | K19: 0 | L19: 0 | M19: 0 | O19: 0 | P19: 0 | Q19: 0 | R19: 0 | S19: 0
A20: 13 | F20: Група 101 - Усього | J20: 0 | K20: 0 | L20: 0 | M20: 0 | O20: 0 | P20: 0 | Q20: 0 | R20: 0 | S20: 0
A21: 14 | D21: 109 | F21: 1090 | H21: Резерви за готівковими коштами, наявність яких є непідтвердженою | I21: П | J21: 0 | K21: 0 | L21: 0 | M21: 0 | O21: 0 | P21: 0 | Q21: 0 | R21: 0 | S21: 0
A22: 15 | F22: Група 109 - Усього | J22: 0 | K22: 0 | L22: 0 | M22: 0 | O22: 0 | P22: 0 | Q22: 0 | R22: 0 | S22: 0
A23: 16 | D23: Розділ 10 - Усього | J23: 4176424.2 | K23: 2176676.6 | L23: 1999747.7 | M23: 4161240.8 | O23: 2187132.8 | P23: 1974107.9 | Q23: 394942.97 | R23: 301756.75 | S23: 93186.219
A24: 17 | C24: 11 | D24: 110 | F24: 1101 | H24: Банківські метали в банку | I24: А | J24: 0 | K24: 0 | L24: 0 | M24: 0 | O24: 0 | P24: 0 | Q24: 0 | R24: 0 | S24: 0
A25: 18 | F25: 1102 | H25: Банківські метали у відділенні банку | I25: А | J25: 10979.895 | K25: 0 | L25: 10979.895 | M25: 5905.9972 | O25: 0 | P25: 5905.9972 | Q25: 5073.8979 | R25: 0 | S25: 5073.8979
A26: 19 | F26: 1107 | H26: Банківські метали в дорозі | I26: А | J26: 5012.4947 | K26: 0 | L26: 5012.4947 | M26: 5012.4947 | O26: 0 | P26: 5012.4947 | Q26: 0 | R26: 0 | S26: 0
A27: 20 | F27: Група 110 - Усього | J27: 15992.39 | K27: 0 | L27: 15992.39 | M27: 10918.492 | O27: 0 | P27: 10918.492 | Q27: 5073.8979 | R27: 0 | S27: 5073.8979
A28: 21 | D28: 119 | F28: 1190 | H28: Резерви за банківськими металами, наявність яких є непідтвердженою | I28: П | J28: 0 | K28: 0 | L28: 0 | M28: 0 | O28: 0 | P28: 0 | Q28: 0 | R28: 0 | S28: 0
A29: 22 | F29: Група 119 - Усього | J29: 0 | K29: 0 | L29: 0 | M29: 0 | O29: 0 | P29: 0 | Q29: 0 | R29: 0 | S29: 0
A30: 23 | D30: Розділ 11 - Усього | J30: 15992.39 | K30: 0 | L30: 15992.39 | M30: 10918.492 | O30: 0 | P30: 10918.492 | Q30: 5073.8979 | R30: 0 | S30: 5073.8979
A31: 24 | C31: 12 | D31: 120 | F31: 1200 | H31: Кореспондентський рахунок банку в Національному банку України | I31: А | J31: 68964021 | K31: 68964021 | L31: 0 | M31: 69354428 | O31: 69354428 | P31: 0 | Q31: 193019.52 | R31: 193019.52 | S31: 0
A32: 25 | F32: 1202 | H32: Кошти банків за рахунками умовного зберігання (ескроу) у Національному банку України | I32: А | J32: 0 | K32: 0 | L32: 0 | M32: 0 | O32: 0 | P32: 0 | Q32: 0 | R32: 0 | S32: 0
A33: 26 | F33: 1205 | H33: Кошти банків для забезпечення виконання зобов’язань перед Національним банком України за кредитами, наданими банкам, та операціями своп процентної ставки | I33: А | J33: 0 | K33: 0 | L33: 0 | M33: 0 | O33: 0 | P33: 0 | Q33: 0 | R33: 0 | S33: 0
A34: 27 | F34: 1208 | H34: Нараховані доходи за коштами на вимогу в Національному банку України | I34: А | J34: 0 | K34: 0 | L34: 0 | M34: 0 | O34: 0 | P34: 0 | Q34: 0 | R34: 0 | S34: 0
A35: 28 | F35: Група 120 - Усього | J35: 68964021 | K35: 68964021 | L35: 0 | M35: 69354428 | O35: 69354428 | P35: 0 | Q35: 193019.52 | R35: 193019.52 | S35: 0
A36: 29 | D36: Розділ 12 - Усього | J36: 68964021 | K36: 68964021 | L36: 0 | M36: 69354428 | O36: 69354428 | P36: 0 | Q36: 193019.52 | R36: 193019.52 | S36: 0
A37: 30 | C37: 14 | D37: 140 | F37: 1400 | H37: Облігації внутрішньої державної позики, що рефінансуються Національним банком України, які обліковуються за справедливою вартістю через прибутки/збитки | I37: А | J37: 0 | K37: 0 | L37: 0 | M37: 0 | O37: 0 | P37: 0 | Q37: 0 | R37: 0 | S37: 0
A38: 31 | F38: 1405 | H38: Переоцінка боргових цінних паперів, що рефінансуються Національним банком України, які обліковуються за справедливою вартістю через прибутки/збитки | I38: А | J38: 0 | K38: 0 | L38: 0 | M38: 0 | O38: 0 | P38: 0 | Q38: 0 | R38: 0 | S38: 0
A39: 32 | I39: П | J39: 0 | K39: 0 | L39: 0 | M39: 0 | O39: 0 | P39: 0 | Q39: 0 | R39: 0 | S39: 0
A40: 33 | F40: 1406 | H40: Неамортизована премія/дисконт за борговими цінними паперами, що рефінансуються Національним банком України, які обліковуються за справедливою вартістю через прибутки/збитки | I40: А | J40: 0 | K40: 0 | L40: 0 | M40: 0 | O40: 0 | P40: 0 | Q40: 0 | R40: 0 | S40: 0
A41: 34 | I41: П | J41: 0 | K41: 0 | L41: 0 | M41: 0 | O41: 0 | P41: 0 | Q41: 0 | R41: 0 | S41: 0
A42: 35 | F42: 1408 | H42: Нараховані доходи за борговими цінними паперами, що рефінансуються Національним банком України, які обліковуються за справедливою вартістю через прибутки/збитки | I42: А | J42: 0 | K42: 0 | L42: 0 | M42: 0 | O42: 0 | P42: 0 | Q42: 0 | R42: 0 | S42: 0
A43: 36 | F43: Група 140 - Усього | J43: 0 | K43: 0 | L43: 0 | M43: 0 | O43: 0 | P43: 0 | Q43: 0 | R43: 0 | S43: 0
A44: 37 | D44: 141 | F44: 1410 | H44: Облігації внутрішньої державної позики, що рефінансуються Національним банком України, які обліковуються за справедливою вартістю через інший сукупний дохід | I44: А | J44: 0 | K44: 0 | L44: 0 | M44: 0 | O44: 0 | P44: 0 | Q44: 0 | R44: 0 | S44: 0
A45: 38 | F45: 1411 | H45: Облігації зовнішньої державної позики, що рефінансуються Національним банком України, які обліковуються за справедливою вартістю через інший сукупний дохід | I45: А | J45: 0 | K45: 0 | L45: 0 | M45: 0 | O45: 0 | P45: 0 | Q45: 0 | R45: 0 | S45: 0
A46: 39 | F46: 1412 | H46: Боргові цінні папери органів державної влади та місцевого самоврядування, що рефінансуються Національним банком України, які обліковуються за справедливою вартістю через інший сукупний дохід | I46: А | J46: 0 | K46: 0 | L46: 0 | M46: 0 | O46: 0 | P46: 0 | Q46: 0 | R46: 0 | S46: 0
A47: 40 | F47: 1415 | H47: Переоцінка боргових цінних паперів, що рефінансуються Національним банком України, які обліковуються за справедливою вартістю через інший сукупний дохід | I47: А | J47: 0 | K47: 0 | L47: 0 | M47: 0 | O47: 0 | P47: 0 | Q47: 0 | R47: 0 | S47: 0
A48: 41 | I48: П | J48: 0 | K48: 0 | L48: 0 | M48: 0 | O48: 0 | P48: 0 | Q48: 0 | R48: 0 | S48: 0
A49: 42 | F49: 1416 | H49: Неамортизована премія/дисконт за борговими цінними паперами, що рефінансуються Національним банком України, які обліковуються за справедливою вартістю через інший сукупний дохід | I49: А | J49: 0 | K49: 0 | L49: 0 | M49: 0 | O49: 0 | P49: 0 | Q49: 0 | R49: 0 | S49: 0
A50: 43 | I50: П | J50: 0 | K50: 0 | L50: 0 | M50: 0 | O50: 0 | P50: 0 | Q50: 0 | R50: 0 | S50: 0
A51: 44 | F51: 1418 | H51: Нараховані доходи за борговими цінними паперами, що рефінансуються Національним банком України, які обліковуються за справедливою вартістю через інший сукупний дохід | I51: А | J51: 0 | K51: 0 | L51: 0 | M51: 0 | O51: 0 | P51: 0 | Q51: 0 | R51: 0 | S51: 0
A52: 45 | F52: 1419 | H52: Резерв за борговими цінними паперами,що рефінансуються Національним банком України, які обліковуються за справедливою вартістю через інший сукупний дохід | I52: П | J52: 0 | K52: 0 | L52: 0 | M52: 0 | O52: 0 | P52: 0 | Q52: 0 | R52: 0 | S52: 0
A53: 46 | F53: Група 141 - Усього | J53: 0 | K53: 0 | L53: 0 | M53: 0 | O53: 0 | P53: 0 | Q53: 0 | R53: 0 | S53: 0
A54: 47 | D54: 142 | F54: 1420 | H54: Облігації внутрішньої державної позики, що рефінансуються Національним банком України, які обліковуються за амортизованою собівартістю | I54: А | J54: 0 | K54: 0 | L54: 0 | M54: 0 | O54: 0 | P54: 0 | Q54: 2793870 | R54: 2793870 | S54: 0
A55: 48 | F55: 1426 | H55: Неамортизована премія/дисконт за борговими цінними паперами, що рефінансуються Національним банком України, які обліковуються за амортизованою собівартістю | I55: А | J55: 3421.1066 | K55: 3421.1066 | L55: 0 | M55: 1910.312 | O55: 1910.312 | P55: 0 | Q55: 21934.386 | R55: 21934.386 | S55: 0
A56: 49 | I56: П | J56: 0 | K56: 0 | L56: 0 | M56: 0 | O56: 0 | P56: 0 | Q56: -62760.954 | R56: -62760.954 | S56: 0
A57: 50 | F57: 1428 | H57: Нараховані доходи за борговими цінними паперами, що рефінансуються Національним банком України, які обліковуються за амортизованою собівартістю | I57: А | J57: 34336.627 | K57: 34336.627 | L57: 0 | M57: 76453.087 | O57: 76453.087 | P57: 0 | Q57: 64444.573 | R57: 64444.573 | S57: 0
A58: 51 | F58: 1429 | H58: Резерв за борговими цінними паперами,що рефінансуються Національним банком України, які обліковуються за амортизованою собівартістю | I58: П | J58: 0 | K58: 0 | L58: 0 | M58: 0 | O58: 0 | P58: 0 | Q58: 0 | R58: 0 | S58: 0
A59: 52 | F59: Група 142 - Усього | J59: 37757.734 | K59: 37757.734 | L59: 0 | M59: 78363.399 | O59: 78363.399 | P59: 0 | Q59: 2817488 | R59: 2817488 | S59: 0
A60: 53 | D60: 143 | F60: 1430 | H60: Депозитні сертифікати Національного банку України, розміщені в банках України, що обліковуються за справедливою вартістю через інший сукупний дохід | I60: А | J60: 0 | K60: 0 | L60: 0 | M60: 0 | O60: 0 | P60: 0 | Q60: 0 | R60: 0 | S60: 0
A61: 54 | F61: 1435 | H61: Переоцінка депозитних сертифікатів Національного банку України, розміщених у банках України, що обліковуються за справедливою вартістю через інший сукупний дохід | I61: А | J61: 0 | K61: 0 | L61: 0 | M61: 0 | O61: 0 | P61: 0 | Q61: 0 | R61: 0 | S61: 0
A62: 55 | F62: 1436 | H62: Неамортизована премія/дисконт за депозитними сертифікатами Національного банку України, розміщеними в банках України, що обліковуються за справедливою вартістю через інший сукупний дохід | I62: А | J62: 0 | K62: 0 | L62: 0 | M62: 0 | O62: 0 | P62: 0 | Q62: 0 | R62: 0 | S62: 0
A63: 56 | I63: П | J63: 0 | K63: 0 | L63: 0 | M63: 0 | O63: 0 | P63: 0 | Q63: 0 | R63: 0 | S63: 0
A64: 57 | F64: 1438 | H64: Нараховані доходи за депозитними сертифікатами Національного банку України, розміщеними в банках України, що обліковуються за справедливою вартістю через інший сукупний дохід | I64: А | J64: 0 | K64: 0 | L64: 0 | M64: 0 | O64: 0 | P64: 0 | Q64: 0 | R64: 0 | S64: 0
A65: 58 | F65: Група 143 - Усього | J65: 0 | K65: 0 | L65: 0 | M65: 0 | O65: 0 | P65: 0 | Q65: 0 | R65: 0 | S65: 0
A66: 59 | D66: 144 | F66: 1440 | H66: Депозитні сертифікати Національного банку України, розміщені в банках України, що обліковуються за амортизованою собівартістю | I66: А | J66: 43140000 | K66: 43140000 | L66: 0 | M66: 40640000 | O66: 40640000 | P66: 0 | Q66: 2500000 | R66: 2500000 | S66: 0
A67: 60 | F67: 1446 | H67: Неамортизована премія/дисконт за депозитними сертифікатами Національного банку України, розміщеними в банках України, що обліковуються за амортизованою собівартістю | I67: А | J67: 0 | K67: 0 | L67: 0 | M67: 0 | O67: 0 | P67: 0 | Q67: 0 | R67: 0 | S67: 0
A68: 61 | I68: П | J68: 0 | K68: 0 | L68: 0 | M68: 0 | O68: 0 | P68: 0 | Q68: 0 | R68: 0 | S68: 0
A69: 62 | F69: 1448 | H69: Нараховані доходи за депозитними сертифікатами Національного банку України, розміщеними в банках України, що обліковуються за амортизованою собівартістю | I69: А | J69: 27291.286 | K69: 27291.286 | L69: 0 | M69: 23933.759 | O69: 23933.759 | P69: 0 | Q69: 3357.527 | R69: 3357.527 | S69: 0
A70: 63 | F70: Група 144 - Усього | J70: 43167291 | K70: 43167291 | L70: 0 | M70: 40663934 | O70: 40663934 | P70: 0 | Q70: 2503357.5 | R70: 2503357.5 | S70: 0
A71: 64 | D71: Розділ 14 - Усього | J71: 43205049 | K71: 43205049 | L71: 0 | M71: 40742297 | O71: 40742297 | P71: 0 | Q71: 5320845.5 | R71: 5320845.5 | S71: 0
A72: 65 | C72: 15 | D72: 150 | F72: 1500 | H72: Кореспондентські рахунки, що відкриті в інших банках | I72: А | J72: 38565038 | K72: 1077344.6 | L72: 37487694 | M72: 38525087 | O72: 1048954.8 | P72: 37476133 | Q72: 2628045.2 | R72: 28602.358 | S72: 2599442.8
A73: 66 | F73: 1508 | H73: Нараховані доходи за коштами на вимогу в інших банках | I73: А | J73: 0 | K73: 0 | L73: 0 | M73: 0 | O73: 0 | P73: 0 | Q73: 0 | R73: 0 | S73: 0
A74: 67 | F74: 1509 | H74: Резерв за коштами на вимогу в інших банках | I74: П | J74: 67345.485 | K74: 56.2372 | L74: 67289.247 | M74: 68647.485 | O74: 1270.8338 | P74: 67376.652 | Q74: -67789.815 | R74: -1270.8338 | S74: -66518.981
A75: 68 | F75: Група 150 - Усього | J75: 38632384 | K75: 1077400.8 | L75: 37554983 | M75: 38593735 | O75: 1050225.6 | P75: 37543509 | Q75: 2560255.4 | R75: 27331.524 | S75: 2532923.8
A76: 69 | D76: 151 | F76: 1510 | H76: Депозити овернайт, що розміщені в інших банках, які обліковуються за амортизованою собівартістю | I76: А | J76: 0 | K76: 0 | L76: 0 | M76: 0 | O76: 0 | P76: 0 | Q76: 0 | R76: 0 | S76: 0
A77: 70 | F77: 1513 | H77: Строкові вклади (депозити), що розміщені в інших банках, які обліковуються за амортизованою собівартістю | I77: А | J77: 0 | K77: 0 | L77: 0 | M77: 0 | O77: 0 | P77: 0 | Q77: 0 | R77: 0 | S77: 0
A78: 71 | F78: 1516 | H78: Неамортизована премія/дисконт за строковими вкладами (депозитами), що розміщені в інших банках, які обліковуються за амортизованою собівартістю | I78: А | J78: 0 | K78: 0 | L78: 0 | M78: 0 | O78: 0 | P78: 0 | Q78: 0 | R78: 0 | S78: 0
A79: 72 | I79: П | J79: 0 | K79: 0 | L79: 0 | M79: 0 | O79: 0 | P79: 0 | Q79: 0 | R79: 0 | S79: 0
A80: 73 | F80: 1518 | H80: Нараховані доходи за строковими вкладами (депозитами), що розміщені в інших банках, які обліковуються за амортизованою собівартістю | I80: А | J80: 0 | K80: 0 | L80: 0 | M80: 0 | O80: 0 | P80: 0 | Q80: 0 | R80: 0 | S80: 0
A81: 74 | F81: 1519 | H81: Резерв за строковими вкладами (депозитами), що розміщені в інших банках, які обліковуються за амортизованою собівартістю | I81: П | J81: 0 | K81: 0 | L81: 0 | M81: 0 | O81: 0 | P81: 0 | Q81: 0 | R81: 0 | S81: 0
A82: 75 | F82: Група 151 - Усього | J82: 0 | K82: 0 | L82: 0 | M82: 0 | O82: 0 | P82: 0 | Q82: 0 | R82: 0 | S82: 0
A83: 76 | D83: 152 | F83: 1521 | H83: Кредити овернайт, що надані іншим банкам,які обліковуються за амортизованою собівартістю | I83: А | J83: 2338299.6 | K83: 75000 | L83: 2263299.6 | M83: 2338299.6 | O83: 75000 | P83: 2263299.6 | Q83: 0 | R83: 0 | S83: 0
A84: 77 | F84: 1522 | H84: Кредити, що надані іншим банкам за операціями репо, які обліковуються за амортизованою собівартістю | I84: А | J84: 0 | K84: 0 | L84: 0 | M84: 0 | O84: 0 | P84: 0 | Q84: 0 | R84: 0 | S84: 0
A85: 78 | F85: 1524 | H85: Інші кредити, що надані іншим банкам, які обліковуються за амортизованою собівартістю | I85: А | J85: 0 | K85: 0 | L85: 0 | M85: 0 | O85: 0 | P85: 0 | Q85: 0 | R85: 0 | S85: 0
A86: 79 | F86: 1526 | H86: Неамортизована премія/дисконт за кредитами, що надані іншим банкам, які обліковуються за амортизованою собівартістю | I86: А | J86: 0 | K86: 0 | L86: 0 | M86: 0 | O86: 0 | P86: 0 | Q86: 0 | R86: 0 | S86: 0
A87: 80 | I87: П | J87: 0 | K87: 0 | L87: 0 | M87: 0 | O87: 0 | P87: 0 | Q87: 0 | R87: 0 | S87: 0
A88: 81 | F88: 1528 | H88: Нараховані доходи за кредитами, що надані іншим банкам, які обліковуються за амортизованою собівартістю | I88: А | J88: 208.84236 | K88: 69.24658 | L88: 139.59578 | M88: 208.84236 | O88: 69.24658 | P88: 139.59578 | Q88: 0 | R88: 0 | S88: 0
A89: 82 | F89: 1529 | H89: Резерв за кредитами, що надані іншим банкам, які обліковуються за амортизованою собівартістю | I89: П | J89: 0 | K89: 0 | L89: 0 | M89: 0 | O89: 0 | P89: 0 | Q89: 0 | R89: 0 | S89: 0
A90: 83 | F90: Група 152 - Усього | J90: 2338508.5 | K90: 75069.247 | L90: 2263439.2 | M90: 2338508.5 | O90: 75069.247 | P90: 2263439.2 | Q90: 0 | R90: 0 | S90: 0
A91: 84 | D91: Розділ 15 - Усього | J91: 40970892 | K91: 1152470 | L91: 39818422 | M91: 40932243 | O91: 1125294.9 | P91: 39806949 | Q91: 2560255.4 | R91: 27331.524 | S91: 2532923.8
A92: 85 | C92: 16 | D92: 160 | F92: 1600 | H92: Кореспондентські рахунки інших банків | I92: А | J92: 0 | K92: 0 | L92: 0 | M92: 0 | O92: 0 | P92: 0 | Q92: 0 | R92: 0 | S92: 0
A93: 86 | F93: Група 160 - Усього | J93: 0 | K93: 0 | L93: 0 | M93: 0 | O93: 0 | P93: 0 | Q93: 0 | R93: 0 | S93: 0
A94: 87 | D94: Розділ 16 - Усього | J94: 0 | K94: 0 | L94: 0 | M94: 0 | O94: 0 | P94: 0 | Q94: 0 | R94: 0 | S94: 0
A95: 88 | C95: 18 | D95: 181 | F95: 1811 | H95: Дебіторська заборгованість за операціями з готівкою | I95: А | J95: 2000896 | K95: 803561.4 | L95: 1197334.6 | M95: 2000896 | O95: 803561.4 | P95: 1197334.6 | Q95: 0 | R95: 0 | S95: 0
A96: 89 | F96: 1819 | H96: Інша дебіторська заборгованість за операціями з банками | I96: А | J96: 500 | K96: 500 | L96: 0 | M96: 500 | O96: 500 | P96: 0 | Q96: 0 | R96: 0 | S96: 0
A97: 90 | F97: Група 181 - Усього | J97: 2001396 | K97: 804061.4 | L97: 1197334.6 | M97: 2001396 | O97: 804061.4 | P97: 1197334.6 | Q97: 0 | R97: 0 | S97: 0
A98: 91 | D98: 183 | F98: 1832 | H98: Кошти банків у розрахунках | I98: А | J98: 0 | K98: 0 | L98: 0 | M98: 0 | O98: 0 | P98: 0 | Q98: 8100 | R98: 8100 | S98: 0
A99: 92 | F99: 1839 | H99: Резерви за коштами банків у розрахунках | I99: П | J99: 0.00162 | K99: 0 | L99: 0.00162 | M99: 0.00162 | O99: 0 | P99: 0.00162 | Q99: 0 | R99: 0 | S99: 0
A100: 93 | F100: Група 183 - Усього | J100: 0.00162 | K100: 0 | L100: 0.00162 | M100: 0.00162 | O100: 0 | P100: 0.00162 | Q100: 8100 | R100: 8100 | S100: 0
...

Sheet  36АТ "Райффайзен Банк" 
A1: Зміст
B2: Оборотно-сальдовий баланс банку АТ "Райффайзен Банк" за станом на 01.12.2025
B3: (тис грн)
A4: Номер з/п | B4: Клас/ розділ/ група/ рахунок | I4: Актив/ пасив | J4: Обороти за місяць | Q4: Сальдо
J5: дебет | M5: кредит | Q5: усього | R5: НВ | S5: ІВ
B6: номер | F6: назва | J6: усього | K6: НВ | L6: ІВ | M6: усього | O6: НВ | P6: ІВ
A7: 1 | B7: 2 | F7: 3 | I7: 4 | J7: 5 | K7: 6 | L7: 7 | M7: 8 | O7: 9 | P7: 10 | Q7: 11 | R7: 12 | S7: 13
A8: 1 | B8: Балансові рахунки
A9: 2 | B9: Активи
A10: 3 | B10: Класи 1 - 4
A11: 4 | B11: Клас 1 | C11: 10 | D11: 100 | F11: 1001 | H11: Банкноти та монети в касі банку | I11: А | J11: 32101678 | K11: 19820331 | L11: 12281347 | M11: 32555007 | O11: 20202094 | P11: 12352912 | Q11: 3352158 | R11: 1450726.7 | S11: 1901431.3
A12: 5 | F12: 1002 | H12: Банкноти та монети в касі відділень банку | I12: А | J12: 65058428 | K12: 29868817 | L12: 35189611 | M12: 64695342 | O12: 29589444 | P12: 35105898 | Q12: 4828600.7 | R12: 2718764.2 | S12: 2109836.5
A13: 6 | F13: 1004 | H13: Банкноти та монети в банкоматах | I13: А | J13: 19924497 | K13: 19818088 | L13: 106409.6 | M13: 20298249 | O13: 20187663 | P13: 110585.91 | Q13: 2484330.1 | R13: 2443379.2 | S13: 40950.874
A14: 7 | F14: 1005 | H14: Банкноти та монети, інкасовані до перерахування | I14: А | J14: 1421319.3 | K14: 1421319.3 | L14: 0 | M14: 1421319.3 | O14: 1421319.3 | P14: 0 | Q14: 0 | R14: 0 | S14: 0
A15: 8 | F15: 1006 | H15: Банкноти та монети на зберіганні в інкасаторській компанії | I15: А | J15: 0 | K15: 0 | L15: 0 | M15: 0 | O15: 0 | P15: 0 | Q15: 0 | R15: 0 | S15: 0
A16: 9 | F16: 1007 | H16: Банкноти та монети в дорозі | I16: А | J16: 87343053 | K16: 48587812 | L16: 38755241 | M16: 88657287 | O16: 48620577 | P16: 40036710 | Q16: 2501103.5 | R16: 635549.67 | S16: 1865553.8
A17: 10 | F17: Група 100 - Усього | J17: 2.0584898e+08 | K17: 1.1951637e+08 | L17: 86332608 | M17: 2.076272e+08 | O17: 1.200211e+08 | P17: 87606106 | Q17: 13166192 | R17: 7248419.7 | S17: 5917772.6
A18: 11 | D18: 101 | F18: 1011 | H18: Дорожні чеки в касі банку | I18: А | J18: 0 | K18: 0 | L18: 0 | M18: 0 | O18: 0 | P18: 0 | Q18: 0 | R18: 0 | S18: 0
A19: 12 | F19: 1012 | H19: Дорожні чеки в касі відділень банку | I19: А | J19: 0 | K19: 0 | L19: 0 | M19: 0 | O19: 0 | P19: 0 | Q19: 0 | R19: 0 | S19: 0
A20: 13 | F20: Група 101 - Усього | J20: 0 | K20: 0 | L20: 0 | M20: 0 | O20: 0 | P20: 0 | Q20: 0 | R20: 0 | S20: 0
A21: 14 | D21: 109 | F21: 1090 | H21: Резерви за готівковими коштами, наявність яких є непідтвердженою | I21: П | J21: 77440.92 | K21: 77440.92 | L21: 0 | M21: 54298.72 | O21: 54298.72 | P21: 0 | Q21: -54298.72 | R21: -54298.72 | S21: 0
A22: 15 | F22: Група 109 - Усього | J22: 77440.92 | K22: 77440.92 | L22: 0 | M22: 54298.72 | O22: 54298.72 | P22: 0 | Q22: -54298.72 | R22: -54298.72 | S22: 0
A23: 16 | D23: Розділ 10 - Усього | J23: 2.0592642e+08 | K23: 1.1959381e+08 | L23: 86332608 | M23: 2.076815e+08 | O23: 1.200754e+08 | P23: 87606106 | Q23: 13111894 | R23: 7194121 | S23: 5917772.6
A24: 17 | C24: 11 | D24: 110 | F24: 1101 | H24: Банківські метали в банку | I24: А | J24: 0 | K24: 0 | L24: 0 | M24: 0 | O24: 0 | P24: 0 | Q24: 0 | R24: 0 | S24: 0
A25: 18 | F25: 1102 | H25: Банківські метали у відділенні банку | I25: А | J25: 0 | K25: 0 | L25: 0 | M25: 0 | O25: 0 | P25: 0 | Q25: 0 | R25: 0 | S25: 0
A26: 19 | F26: 1107 | H26: Банківські метали в дорозі | I26: А | J26: 0 | K26: 0 | L26: 0 | M26: 0 | O26: 0 | P26: 0 | Q26: 0 | R26: 0 | S26: 0
A27: 20 | F27: Група 110 - Усього | J27: 0 | K27: 0 | L27: 0 | M27: 0 | O27: 0 | P27: 0 | Q27: 0 | R27: 0 | S27: 0
A28: 21 | D28: 119 | F28: 1190 | H28: Резерви за банківськими металами, наявність яких є непідтвердженою | I28: П | J28: 0 | K28: 0 | L28: 0 | M28: 0 | O28: 0 | P28: 0 | Q28: 0 | R28: 0 | S28: 0
A29: 22 | F29: Група 119 - Усього | J29: 0 | K29: 0 | L29: 0 | M29: 0 | O29: 0 | P29: 0 | Q29: 0 | R29: 0 | S29: 0
A30: 23 | D30: Розділ 11 - Усього | J30: 0 | K30: 0 | L30: 0 | M30: 0 | O30: 0 | P30: 0 | Q30: 0 | R30: 0 | S30: 0
A31: 24 | C31: 12 | D31: 120 | F31: 1200 | H31: Кореспондентський рахунок банку в Національному банку України | I31: А | J31: 8.0173461e+08 | K31: 8.0173461e+08 | L31: 0 | M31: 8.0090905e+08 | O31: 8.0090905e+08 | P31: 0 | Q31: 17682726 | R31: 17682726 | S31: 0
A32: 25 | F32: 1202 | H32: Кошти банків за рахунками умовного зберігання (ескроу) у Національному банку України | I32: А | J32: 0 | K32: 0 | L32: 0 | M32: 0 | O32: 0 | P32: 0 | Q32: 0 | R32: 0 | S32: 0
A33: 26 | F33: 1205 | H33: Кошти банків для забезпечення виконання зобов’язань перед Національним банком України за кредитами, наданими банкам, та операціями своп процентної ставки | I33: А | J33: 0 | K33: 0 | L33: 0 | M33: 0 | O33: 0 | P33: 0 | Q33: 0 | R33: 0 | S33: 0
A34: 27 | F34: 1208 | H34: Нараховані доходи за коштами на вимогу в Національному банку України | I34: А | J34: 0 | K34: 0 | L34: 0 | M34: 0 | O34: 0 | P34: 0 | Q34: 0 | R34: 0 | S34: 0
A35: 28 | F35: Група 120 - Усього | J35: 8.0173461e+08 | K35: 8.0173461e+08 | L35: 0 | M35: 8.0090905e+08 | O35: 8.0090905e+08 | P35: 0 | Q35: 17682726 | R35: 17682726 | S35: 0
A36: 29 | D36: Розділ 12 - Усього | J36: 8.0173461e+08 | K36: 8.0173461e+08 | L36: 0 | M36: 8.0090905e+08 | O36: 8.0090905e+08 | P36: 0 | Q36: 17682726 | R36: 17682726 | S36: 0
A37: 30 | C37: 14 | D37: 140 | F37: 1400 | H37: Облігації внутрішньої державної позики, що рефінансуються Національним банком України, які обліковуються за справедливою вартістю через прибутки/збитки | I37: А | J37: 413467.08 | K37: 366890 | L37: 46577.079 | M37: 517980.06 | O37: 499053 | P37: 18927.062 | Q37: 5267480.5 | R37: 5194758 | S37: 72722.55
A38: 31 | F38: 1405 | H38: Переоцінка боргових цінних паперів, що рефінансуються Національним банком України, які обліковуються за справедливою вартістю через прибутки/збитки | I38: А | J38: 2488491.7 | K38: 2454098 | L38: 34393.697 | M38: 2466917.9 | O38: 2431662.6 | P38: 35255.313 | Q38: 77252.277 | R38: 77252.277 | S38: 0
A39: 32 | I39: П | J39: 0 | K39: 0 | L39: 0 | M39: 0 | O39: 0 | P39: 0 | Q39: -47162.485 | R39: -44734.309 | S39: -2428.1759
A40: 33 | F40: 1406 | H40: Неамортизована премія/дисконт за борговими цінними паперами, що рефінансуються Національним банком України, які обліковуються за справедливою вартістю через прибутки/збитки | I40: А | J40: 15347.928 | K40: 15146.59 | L40: 201.33835 | M40: 13684.611 | O40: 13415.967 | P40: 268.644 | Q40: 108169.76 | R40: 108009.65 | S40: 160.11092
A41: 34 | I41: П | J41: 0 | K41: 0 | L41: 0 | M41: 0 | O41: 0 | P41: 0 | Q41: -11570.39 | R41: -11570.39 | S41: 0
A42: 35 | F42: 1408 | H42: Нараховані доходи за борговими цінними паперами, що рефінансуються Національним банком України, які обліковуються за справедливою вартістю через прибутки/збитки | I42: А | J42: 92197.634 | K42: 91750.01 | L42: 447.62434 | M42: 36567.857 | O42: 36451.605 | P42: 116.2517 | Q42: 255516.79 | R42: 254974.24 | S42: 542.54753
A43: 36 | F43: Група 140 - Усього | J43: 3009504.3 | K43: 2927884.6 | L43: 81619.739 | M43: 3035150.5 | O43: 2980583.2 | P43: 54567.271 | Q43: 5649686.5 | R43: 5578689.5 | S43: 70997.032
A44: 37 | D44: 141 | F44: 1410 | H44: Облігації внутрішньої державної позики, що рефінансуються Національним банком України, які обліковуються за справедливою вартістю через інший сукупний дохід | I44: А | J44: 0 | K44: 0 | L44: 0 | M44: 0 | O44: 0 | P44: 0 | Q44: 26685227 | R44: 26685227 | S44: 0
A45: 38 | F45: 1411 | H45: Облігації зовнішньої державної позики, що рефінансуються Національним банком України, які обліковуються за справедливою вартістю через інший сукупний дохід | I45: А | J45: 0 | K45: 0 | L45: 0 | M45: 0 | O45: 0 | P45: 0 | Q45: 0 | R45: 0 | S45: 0
A46: 39 | F46: 1412 | H46: Боргові цінні папери органів державної влади та місцевого самоврядування, що рефінансуються Національним банком України, які обліковуються за справедливою вартістю через інший сукупний дохід | I46: А | J46: 0 | K46: 0 | L46: 0 | M46: 0 | O46: 0 | P46: 0 | Q46: 0 | R46: 0 | S46: 0
A47: 40 | F47: 1415 | H47: Переоцінка боргових цінних паперів, що рефінансуються Національним банком України, які обліковуються за справедливою вартістю через інший сукупний дохід | I47: А | J47: 6423974 | K47: 6423974 | L47: 0 | M47: 6434153.3 | O47: 6434153.3 | P47: 0 | Q47: 3106655.6 | R47: 3106655.6 | S47: 0
A48: 41 | I48: П | J48: 0 | K48: 0 | L48: 0 | M48: 0 | O48: 0 | P48: 0 | Q48: 0 | R48: 0 | S48: 0
A49: 42 | F49: 1416 | H49: Неамортизована премія/дисконт за борговими цінними паперами, що рефінансуються Національним банком України, які обліковуються за справедливою вартістю через інший сукупний дохід | I49: А | J49: 5932.5207 | K49: 5932.5207 | L49: 0 | M49: 85007.548 | O49: 85007.548 | P49: 0 | Q49: 485741.07 | R49: 485741.07 | S49: 0
A50: 43 | I50: П | J50: 0 | K50: 0 | L50: 0 | M50: 0 | O50: 0 | P50: 0 | Q50: -58412.544 | R50: -58412.544 | S50: 0
A51: 44 | F51: 1418 | H51: Нараховані доходи за борговими цінними паперами, що рефінансуються Національним банком України, які обліковуються за справедливою вартістю через інший сукупний дохід | I51: А | J51: 418012.04 | K51: 418012.04 | L51: 0 | M51: 439276.35 | O51: 439276.35 | P51: 0 | Q51: 877390.99 | R51: 877390.99 | S51: 0
A52: 45 | F52: 1419 | H52: Резерв за борговими цінними паперами,що рефінансуються Національним банком України, які обліковуються за справедливою вартістю через інший сукупний дохід | I52: П | J52: 3573649.6 | K52: 3573649.6 | L52: 0 | M52: 3337108.6 | O52: 3337108.6 | P52: 0 | Q52: -3337108.6 | R52: -3337108.6 | S52: 0
A53: 46 | F53: Група 141 - Усього | J53: 10421568 | K53: 10421568 | L53: 0 | M53: 10295546 | O53: 10295546 | P53: 0 | Q53: 27759494 | R53: 27759494 | S53: 0
A54: 47 | D54: 142 | F54: 1420 | H54: Облігації внутрішньої державної позики, що рефінансуються Національним банком України, які обліковуються за амортизованою собівартістю | I54: А | J54: 0 | K54: 0 | L54: 0 | M54: 200000 | O54: 200000 | P54: 0 | Q54: 5969234 | R54: 5969234 | S54: 0
A55: 48 | F55: 1426 | H55: Неамортизована премія/дисконт за борговими цінними паперами, що рефінансуються Національним банком України, які обліковуються за амортизованою собівартістю | I55: А | J55: 2291.0181 | K55: 2291.0181 | L55: 0 | M55: 2240.8268 | O55: 2240.8268 | P55: 0 | Q55: 9623.2 | R55: 9623.2 | S55: 0
A56: 49 | I56: П | J56: 0 | K56: 0 | L56: 0 | M56: 0 | O56: 0 | P56: 0 | Q56: -47504.455 | R56: -47504.455 | S56: 0
A57: 50 | F57: 1428 | H57: Нараховані доходи за борговими цінними паперами, що рефінансуються Національним банком України, які обліковуються за амортизованою собівартістю | I57: А | J57: 89784.903 | K57: 89784.903 | L57: 0 | M57: 52650.274 | O57: 52650.274 | P57: 0 | Q57: 226836.44 | R57: 226836.44 | S57: 0
A58: 51 | F58: 1429 | H58: Резерв за борговими цінними паперами,що рефінансуються Національним банком України, які обліковуються за амортизованою собівартістю | I58: П | J58: 686627.97 | K58: 686627.97 | L58: 0 | M58: 613034.14 | O58: 613034.14 | P58: 0 | Q58: -609080.11 | R58: -609080.11 | S58: 0
A59: 52 | F59: Група 142 - Усього | J59: 778703.89 | K59: 778703.89 | L59: 0 | M59: 867925.24 | O59: 867925.24 | P59: 0 | Q59: 5549109.1 | R59: 5549109.1 | S59: 0
A60: 53 | D60: 143 | F60: 1430 | H60: Депозитні сертифікати Національного банку України, розміщені в банках України, що обліковуються за справедливою вартістю через інший сукупний дохід | I60: А | J60: 0 | K60: 0 | L60: 0 | M60: 0 | O60: 0 | P60: 0 | Q60: 0 | R60: 0 | S60: 0
A61: 54 | F61: 1435 | H61: Переоцінка депозитних сертифікатів Національного банку України, розміщених у банках України, що обліковуються за справедливою вартістю через інший сукупний дохід | I61: А | J61: 0 | K61: 0 | L61: 0 | M61: 0 | O61: 0 | P61: 0 | Q61: 0 | R61: 0 | S61: 0
A62: 55 | F62: 1436 | H62: Неамортизована премія/дисконт за депозитними сертифікатами Національного банку України, розміщеними в банках України, що обліковуються за справедливою вартістю через інший сукупний дохід | I62: А | J62: 0 | K62: 0 | L62: 0 | M62: 0 | O62: 0 | P62: 0 | Q62: 0 | R62: 0 | S62: 0
A63: 56 | I63: П | J63: 0 | K63: 0 | L63: 0 | M63: 0 | O63: 0 | P63: 0 | Q63: 0 | R63: 0 | S63: 0
A64: 57 | F64: 1438 | H64: Нараховані доходи за депозитними сертифікатами Національного банку України, розміщеними в банках України, що обліковуються за справедливою вартістю через інший сукупний дохід | I64: А | J64: 0 | K64: 0 | L64: 0 | M64: 0 | O64: 0 | P64: 0 | Q64: 0 | R64: 0 | S64: 0
A65: 58 | F65: Група 143 - Усього | J65: 0 | K65: 0 | L65: 0 | M65: 0 | O65: 0 | P65: 0 | Q65: 0 | R65: 0 | S65: 0
A66: 59 | D66: 144 | F66: 1440 | H66: Депозитні сертифікати Національного банку України, розміщені в банках України, що обліковуються за амортизованою собівартістю | I66: А | J66: 506022000 | K66: 506022000 | L66: 0 | M66: 512114000 | O66: 512114000 | P66: 0 | Q66: 11235000 | R66: 11235000 | S66: 0
A67: 60 | F67: 1446 | H67: Неамортизована премія/дисконт за депозитними сертифікатами Національного банку України, розміщеними в банках України, що обліковуються за амортизованою собівартістю | I67: А | J67: 0 | K67: 0 | L67: 0 | M67: 0 | O67: 0 | P67: 0 | Q67: 0 | R67: 0 | S67: 0
A68: 61 | I68: П | J68: 0 | K68: 0 | L68: 0 | M68: 0 | O68: 0 | P68: 0 | Q68: 0 | R68: 0 | S68: 0
A69: 62 | F69: 1448 | H69: Нараховані доходи за депозитними сертифікатами Національного банку України, розміщеними в банках України, що обліковуються за амортизованою собівартістю | I69: А | J69: 355490.3 | K69: 355490.3 | L69: 0 | M69: 374352.99 | O69: 374352.99 | P69: 0 | Q69: 65334.53 | R69: 65334.53 | S69: 0
A70: 63 | F70: Група 144 - Усього | J70: 5.0637749e+08 | K70: 5.0637749e+08 | L70: 0 | M70: 5.1248835e+08 | O70: 5.1248835e+08 | P70: 0 | Q70: 11300335 | R70: 11300335 | S70: 0
A71: 64 | D71: Розділ 14 - Усього | J71: 5.2058727e+08 | K71: 5.2050565e+08 | L71: 81619.739 | M71: 5.2668697e+08 | O71: 5.2663241e+08 | P71: 54567.271 | Q71: 50258624 | R71: 50187627 | S71: 70997.032
A72: 65 | C72: 15 | D72: 150 | F72: 1500 | H72: Кореспондентські рахунки, що відкриті в інших банках | I72: А | J72: 2.9473692e+08 | K72: 16842020 | L72: 2.778949e+08 | M72: 2.9317991e+08 | O72: 15340470 | P72: 2.7783944e+08 | Q72: 32396507 | R72: 1543669.5 | S72: 30852838
A73: 66 | F73: 1508 | H73: Нараховані доходи за коштами на вимогу в інших банках | I73: А | J73: 49556.108 | K73: 0 | L73: 49556.108 | M73: 52060.871 | O73: 0 | P73: 52060.871 | Q73: 25878.957 | R73: 0 | S73: 25878.957
A74: 67 | F74: 1509 | H74: Резерв за коштами на вимогу в інших банках | I74: П | J74: 58.4905 | K74: 7.51855 | L74: 50.97195 | M74: 51.49292 | O74: 44.09218 | P74: 7.40074 | Q74: -50.71042 | R74: -44.09218 | S74: -6.61824
A75: 68 | F75: Група 150 - Усього | J75: 2.9478654e+08 | K75: 16842028 | L75: 2.7794451e+08 | M75: 2.9323203e+08 | O75: 15340514 | P75: 2.7789151e+08 | Q75: 32422335 | R75: 1543625.4 | S75: 30878710
A76: 69 | D76: 151 | F76: 1510 | H76: Депозити овернайт, що розміщені в інших банках, які обліковуються за амортизованою собівартістю | I76: А | J76: 11193167 | K76: 0 | L76: 11193167 | M76: 10982589 | O76: 0 | P76: 10982589 | Q76: 636292.74 | R76: 0 | S76: 636292.74
A77: 70 | F77: 1513 | H77: Строкові вклади (депозити), що розміщені в інших банках, які обліковуються за амортизованою собівартістю | I77: А | J77: 0 | K77: 0 | L77: 0 | M77: 0 | O77: 0 | P77: 0 | Q77: 0 | R77: 0 | S77: 0
A78: 71 | F78: 1516 | H78: Неамортизована премія/дисконт за строковими вкладами (депозитами), що розміщені в інших банках, які обліковуються за амортизованою собівартістю | I78: А | J78: 0 | K78: 0 | L78: 0 | M78: 0 | O78: 0 | P78: 0 | Q78: 0 | R78: 0 | S78: 0
A79: 72 | I79: П | J79: 0 | K79: 0 | L79: 0 | M79: 0 | O79: 0 | P79: 0 | Q79: 0 | R79: 0 | S79: 0
A80: 73 | F80: 1518 | H80: Нараховані доходи за строковими вкладами (депозитами), що розміщені в інших банках, які обліковуються за амортизованою собівартістю | I80: А | J80: 365.79297 | K80: 0 | L80: 365.79297 | M80: 549.4094 | O80: 0 | P80: 549.4094 | Q80: 364.86772 | R80: 0 | S80: 364.86772
A81: 74 | F81: 1519 | H81: Резерв за строковими вкладами (депозитами), що розміщені в інших банках, які обліковуються за амортизованою собівартістю | I81: П | J81: 0.09224 | K81: 0 | L81: 0.09224 | M81: 0.06064 | O81: 0 | P81: 0.06064 | Q81: -0.05864 | R81: 0 | S81: -0.05864
A82: 75 | F82: Група 151 - Усього | J82: 11193532 | K82: 0 | L82: 11193532 | M82: 10983139 | O82: 0 | P82: 10983139 | Q82: 636657.55 | R82: 0 | S82: 636657.55
A83: 76 | D83: 152 | F83: 1521 | H83: Кредити овернайт, що надані іншим банкам,які обліковуються за амортизованою собівартістю | I83: А | J83: 60469453 | K83: 0 | L83: 60469453 | M83: 62943462 | O83: 0 | P83: 62943462 | Q83: 421928 | R83: 0 | S83: 421928
A84: 77 | F84: 1522 | H84: Кредити, що надані іншим банкам за операціями репо, які обліковуються за амортизованою собівартістю | I84: А | J84: 0 | K84: 0 | L84: 0 | M84: 0 | O84: 0 | P84: 0 | Q84: 0 | R84: 0 | S84: 0
A85: 78 | F85: 1524 | H85: Інші кредити, що надані іншим банкам, які обліковуються за амортизованою собівартістю | I85: А | J85: 5482063.8 | K85: 0 | L85: 5482063.8 | M85: 7222983.4 | O85: 0 | P85: 7222983.4 | Q85: 6246077.4 | R85: 2111183 | S85: 4134894.4
A86: 79 | F86: 1526 | H86: Неамортизована премія/дисконт за кредитами, що надані іншим банкам, які обліковуються за амортизованою собівартістю | I86: А | J86: 0 | K86: 0 | L86: 0 | M86: 0 | O86: 0 | P86: 0 | Q86: 0 | R86: 0 | S86: 0
A87: 80 | I87: П | J87: 0 | K87: 0 | L87: 0 | M87: 0 | O87: 0 | P87: 0 | Q87: 0 | R87: 0 | S87: 0
A88: 81 | F88: 1528 | H88: Нараховані доходи за кредитами, що надані іншим банкам, які обліковуються за амортизованою собівартістю | I88: А | J88: 36011.749 | K88: 9773.1266 | L88: 26238.622 | M88: 25783.198 | O88: 0 | P88: 25783.198 | Q88: 27256.619 | R88: 20369.347 | S88: 6887.2712
A89: 82 | F89: 1529 | H89: Резерв за кредитами, що надані іншим банкам, які обліковуються за амортизованою собівартістю | I89: П | J89: 214.74825 | K89: 128.3459 | L89: 86.40235 | M89: 52.41317 | O89: 40.57803 | P89: 11.83514 | Q89: -51.20005 | R89: -40.57803 | S89: -10.62202
A90: 83 | F90: Група 152 - Усього | J90: 65987743 | K90: 9901.4725 | L90: 65977842 | M90: 70192281 | O90: 40.57803 | P90: 70192240 | Q90: 6695210.8 | R90: 2131511.7 | S90: 4563699
A91: 84 | D91: Розділ 15 - Усього | J91: 3.7196781e+08 | K91: 16851929 | L91: 3.5511589e+08 | M91: 3.7440745e+08 | O91: 15340555 | P91: 3.5906689e+08 | Q91: 39754204 | R91: 3675137.1 | S91: 36079066
A92: 85 | C92: 16 | D92: 160 | F92: 1600 | H92: Кореспондентські рахунки інших банків | I92: А | J92: 2726217.7 | K92: 2490394.3 | L92: 235823.35 | M92: 1262087.1 | O92: 1026647.2 | P92: 235439.88 | Q92: 0 | R92: 0 | S92: 0
A93: 86 | F93: Група 160 - Усього | J93: 2726217.7 | K93: 2490394.3 | L93: 235823.35 | M93: 1262087.1 | O93: 1026647.2 | P93: 235439.88 | Q93: 0 | R93: 0 | S93: 0
A94: 87 | D94: Розділ 16 - Усього | J94: 2726217.7 | K94: 2490394.3 | L94: 235823.35 | M94: 1262087.1 | O94: 1026647.2 | P94: 235439.88 | Q94: 0 | R94: 0 | S94: 0
A95: 88 | C95: 18 | D95: 181 | F95: 1811 | H95: Дебіторська заборгованість за операціями з готівкою | I95: А | J95: 33851713 | K95: 11399570 | L95: 22452144 | M95: 33851350 | O95: 11399570 | P95: 22451780 | Q95: 2432047.6 | R95: 0 | S95: 2432047.6
A96: 89 | F96: 1819 | H96: Інша дебіторська заборгованість за операціями з банками | I96: А | J96: 1860970.4 | K96: 1860970.4 | L96: 0 | M96: 1876689.4 | O96: 1876689.4 | P96: 0 | Q96: 7572.9688 | R96: 7572.9688 | S96: 0
A97: 90 | F97: Група 181 - Усього | J97: 35712684 | K97: 13260540 | L97: 22452144 | M97: 35728039 | O97: 13276259 | P97: 22451780 | Q97: 2439620.6 | R97: 7572.9688 | S97: 2432047.6
A98: 91 | D98: 183 | F98: 1832 | H98: Кошти банків у розрахунках | I98: А | J98: 237093.94 | K98: 0 | L98: 237093.94 | M98: 499810.99 | O98: 0 | P98: 499810.99 | Q98: 1747690.8 | R98: 100 | S98: 1747590.8
A99: 92 | F99: 1839 | H99: Резерви за коштами банків у розрахунках | I99: П | J99: 3.86431 | K99: 0 | L99: 3.86431 | M99: 0.42351 | O99: 0 | P99: 0.42351 | Q99: -0.35029 | R99: 0 | S99: -0.35029
A100: 93 | F100: Група 183 - Усього | J100: 237097.8 | K100: 0 | L100: 237097.8 | M100: 499811.41 | O100: 0 | P100: 499811.41 | Q100: 1747690.4 | R100: 100 | S100: 1747590.4
...

Sheet  43АТ "АЛЬТБАНК" 
A1: Зміст
B2: Оборотно-сальдовий баланс банку АТ "АЛЬТБАНК" за станом на 01.12.2025
B3: (тис грн)
A4: Номер з/п | B4: Клас/ розділ/ група/ рахунок | I4: Актив/ пасив | J4: Обороти за місяць | Q4: Сальдо
J5: дебет | M5: кредит | Q5: усього | R5: НВ | S5: ІВ
B6: номер | F6: назва | J6: усього | K6: НВ | L6: ІВ | M6: усього | O6: НВ | P6: ІВ
A7: 1 | B7: 2 | F7: 3 | I7: 4 | J7: 5 | K7: 6 | L7: 7 | M7: 8 | O7: 9 | P7: 10 | Q7: 11 | R7: 12 | S7: 13
A8: 1 | B8: Балансові рахунки
A9: 2 | B9: Активи
A10: 3 | B10: Класи 1 - 4
A11: 4 | B11: Клас 1 | C11: 10 | D11: 100 | F11: 1001 | H11: Банкноти та монети в касі банку | I11: А | J11: 28154.385 | K11: 21779.658 | L11: 6374.7271 | M11: 29506.086 | O11: 20971.329 | P11: 8534.7572 | Q11: 9920.2462 | R11: 2915.2424 | S11: 7005.0038
A12: 5 | F12: 1002 | H12: Банкноти та монети в касі відділень банку | I12: А | J12: 30435.051 | K12: 21849.263 | L12: 8585.788 | M12: 37683.004 | O12: 23400.829 | P12: 14282.174 | Q12: 19994.412 | R12: 5674.948 | S12: 14319.464
A13: 6 | F13: 1004 | H13: Банкноти та монети в банкоматах | I13: А | J13: 17285.86 | K13: 17285.86 | L13: 0 | M13: 16009.91 | O13: 16009.91 | P13: 0 | Q13: 6850.8 | R13: 6850.8 | S13: 0
A14: 7 | F14: 1005 | H14: Банкноти та монети, інкасовані до перерахування | I14: А | J14: 0 | K14: 0 | L14: 0 | M14: 0 | O14: 0 | P14: 0 | Q14: 0 | R14: 0 | S14: 0
A15: 8 | F15: 1006 | H15: Банкноти та монети на зберіганні в інкасаторській компанії | I15: А | J15: 0 | K15: 0 | L15: 0 | M15: 0 | O15: 0 | P15: 0 | Q15: 0 | R15: 0 | S15: 0
A16: 9 | F16: 1007 | H16: Банкноти та монети в дорозі | I16: А | J16: 16839.968 | K16: 12298.06 | L16: 4541.9076 | M16: 16839.968 | O16: 12298.06 | P16: 4541.9076 | Q16: 0 | R16: 0 | S16: 0
A17: 10 | F17: Група 100 - Усього | J17: 92715.264 | K17: 73212.841 | L17: 19502.423 | M17: 100038.97 | O17: 72680.129 | P17: 27358.839 | Q17: 36765.458 | R17: 15440.99 | S17: 21324.467
A18: 11 | D18: 101 | F18: 1011 | H18: Дорожні чеки в касі банку | I18: А | J18: 0 | K18: 0 | L18: 0 | M18: 0 | O18: 0 | P18: 0 | Q18: 0 | R18: 0 | S18: 0
A19: 12 | F19: 1012 | H19: Дорожні чеки в касі відділень банку | I19: А | J19: 0 | K19: 0 | L19: 0 | M19: 0 | O19: 0 | P19: 0 | Q19: 0 | R19: 0 | S19: 0
A20: 13 | F20: Група 101 - Усього | J20: 0 | K20: 0 | L20: 0 | M20: 0 | O20: 0 | P20: 0 | Q20: 0 | R20: 0 | S20: 0
A21: 14 | D21: 109 | F21: 1090 | H21: Резерви за готівковими коштами, наявність яких є непідтвердженою | I21: П | J21: 0 | K21: 0 | L21: 0 | M21: 0 | O21: 0 | P21: 0 | Q21: 0 | R21: 0 | S21: 0
A22: 15 | F22: Група 109 - Усього | J22: 0 | K22: 0 | L22: 0 | M22: 0 | O22: 0 | P22: 0 | Q22: 0 | R22: 0 | S22: 0
A23: 16 | D23: Розділ 10 - Усього | J23: 92715.264 | K23: 73212.841 | L23: 19502.423 | M23: 100038.97 | O23: 72680.129 | P23: 27358.839 | Q23: 36765.458 | R23: 15440.99 | S23: 21324.467
A24: 17 | C24: 11 | D24: 110 | F24: 1101 | H24: Банківські метали в банку | I24: А | J24: 0 | K24: 0 | L24: 0 | M24: 0 | O24: 0 | P24: 0 | Q24: 0 | R24: 0 | S24: 0
A25: 18 | F25: 1102 | H25: Банківські метали у відділенні банку | I25: А | J25: 0 | K25: 0 | L25: 0 | M25: 0 | O25: 0 | P25: 0 | Q25: 0 | R25: 0 | S25: 0
A26: 19 | F26: 1107 | H26: Банківські метали в дорозі | I26: А | J26: 0 | K26: 0 | L26: 0 | M26: 0 | O26: 0 | P26: 0 | Q26: 0 | R26: 0 | S26: 0
A27: 20 | F27: Група 110 - Усього | J27: 0 | K27: 0 | L27: 0 | M27: 0 | O27: 0 | P27: 0 | Q27: 0 | R27: 0 | S27: 0
A28: 21 | D28: 119 | F28: 1190 | H28: Резерви за банківськими металами, наявність яких є непідтвердженою | I28: П | J28: 0 | K28: 0 | L28: 0 | M28: 0 | O28: 0 | P28: 0 | Q28: 0 | R28: 0 | S28: 0
A29: 22 | F29: Група 119 - Усього | J29: 0 | K29: 0 | L29: 0 | M29: 0 | O29: 0 | P29: 0 | Q29: 0 | R29: 0 | S29: 0
A30: 23 | D30: Розділ 11 - Усього | J30: 0 | K30: 0 | L30: 0 | M30: 0 | O30: 0 | P30: 0 | Q30: 0 | R30: 0 | S30: 0
A31: 24 | C31: 12 | D31: 120 | F31: 1200 | H31: Кореспондентський рахунок банку в Національному банку України | I31: А | J31: 6987129.7 | K31: 6987129.7 | L31: 0 | M31: 7053942.3 | O31: 7053942.3 | P31: 0 | Q31: 165603.41 | R31: 165603.41 | S31: 0
A32: 25 | F32: 1202 | H32: Кошти банків за рахунками умовного зберігання (ескроу) у Національному банку України | I32: А | J32: 0 | K32: 0 | L32: 0 | M32: 0 | O32: 0 | P32: 0 | Q32: 0 | R32: 0 | S32: 0
A33: 26 | F33: 1205 | H33: Кошти банків для забезпечення виконання зобов’язань перед Національним банком України за кредитами, наданими банкам, та операціями своп процентної ставки | I33: А | J33: 0 | K33: 0 | L33: 0 | M33: 0 | O33: 0 | P33: 0 | Q33: 0 | R33: 0 | S33: 0
A34: 27 | F34: 1208 | H34: Нараховані доходи за коштами на вимогу в Національному банку України | I34: А | J34: 0 | K34: 0 | L34: 0 | M34: 0 | O34: 0 | P34: 0 | Q34: 0 | R34: 0 | S34: 0
A35: 28 | F35: Група 120 - Усього | J35: 6987129.7 | K35: 6987129.7 | L35: 0 | M35: 7053942.3 | O35: 7053942.3 | P35: 0 | Q35: 165603.41 | R35: 165603.41 | S35: 0
A36: 29 | D36: Розділ 12 - Усього | J36: 6987129.7 | K36: 6987129.7 | L36: 0 | M36: 7053942.3 | O36: 7053942.3 | P36: 0 | Q36: 165603.41 | R36: 165603.41 | S36: 0
A37: 30 | C37: 14 | D37: 140 | F37: 1400 | H37: Облігації внутрішньої державної позики, що рефінансуються Національним банком України, які обліковуються за справедливою вартістю через прибутки/збитки | I37: А | J37: 0 | K37: 0 | L37: 0 | M37: 0 | O37: 0 | P37: 0 | Q37: 0 | R37: 0 | S37: 0
A38: 31 | F38: 1405 | H38: Переоцінка боргових цінних паперів, що рефінансуються Національним банком України, які обліковуються за справедливою вартістю через прибутки/збитки | I38: А | J38: 0 | K38: 0 | L38: 0 | M38: 0 | O38: 0 | P38: 0 | Q38: 0 | R38: 0 | S38: 0
A39: 32 | I39: П | J39: 0 | K39: 0 | L39: 0 | M39: 0 | O39: 0 | P39: 0 | Q39: 0 | R39: 0 | S39: 0
A40: 33 | F40: 1406 | H40: Неамортизована премія/дисконт за борговими цінними паперами, що рефінансуються Національним банком України, які обліковуються за справедливою вартістю через прибутки/збитки | I40: А | J40: 0 | K40: 0 | L40: 0 | M40: 0 | O40: 0 | P40: 0 | Q40: 0 | R40: 0 | S40: 0
A41: 34 | I41: П | J41: 0 | K41: 0 | L41: 0 | M41: 0 | O41: 0 | P41: 0 | Q41: 0 | R41: 0 | S41: 0
A42: 35 | F42: 1408 | H42: Нараховані доходи за борговими цінними паперами, що рефінансуються Національним банком України, які обліковуються за справедливою вартістю через прибутки/збитки | I42: А | J42: 0 | K42: 0 | L42: 0 | M42: 0 | O42: 0 | P42: 0 | Q42: 0 | R42: 0 | S42: 0
A43: 36 | F43: Група 140 - Усього | J43: 0 | K43: 0 | L43: 0 | M43: 0 | O43: 0 | P43: 0 | Q43: 0 | R43: 0 | S43: 0
A44: 37 | D44: 141 | F44: 1410 | H44: Облігації внутрішньої державної позики, що рефінансуються Національним банком України, які обліковуються за справедливою вартістю через інший сукупний дохід | I44: А | J44: 159956.88 | K44: 106281 | L44: 53675.88 | M44: 338903.56 | O44: 315016 | P44: 23887.564 | Q44: 819697.94 | R44: 778191 | S44: 41506.935
A45: 38 | F45: 1411 | H45: Облігації зовнішньої державної позики, що рефінансуються Національним банком України, які обліковуються за справедливою вартістю через інший сукупний дохід | I45: А | J45: 0 | K45: 0 | L45: 0 | M45: 0 | O45: 0 | P45: 0 | Q45: 0 | R45: 0 | S45: 0
A46: 39 | F46: 1412 | H46: Боргові цінні папери органів державної влади та місцевого самоврядування, що рефінансуються Національним банком України, які обліковуються за справедливою вартістю через інший сукупний дохід | I46: А | J46: 0 | K46: 0 | L46: 0 | M46: 0 | O46: 0 | P46: 0 | Q46: 0 | R46: 0 | S46: 0
A47: 40 | F47: 1415 | H47: Переоцінка боргових цінних паперів, що рефінансуються Національним банком України, які обліковуються за справедливою вартістю через інший сукупний дохід | I47: А | J47: 36998.842 | K47: 36391.031 | L47: 607.81076 | M47: 30614.525 | O47: 30067.496 | P47: 547.02947 | Q47: 19391.286 | R47: 19248.575 | S47: 142.71117
A48: 41 | I48: П | J48: 0 | K48: 0 | L48: 0 | M48: 0 | O48: 0 | P48: 0 | Q48: -3598.9684 | R48: -3541.3875 | S48: -57.58093
A49: 42 | F49: 1416 | H49: Неамортизована премія/дисконт за борговими цінними паперами, що рефінансуються Національним банком України, які обліковуються за справедливою вартістю через інший сукупний дохід | I49: А | J49: 3564.7227 | K49: 3046.5617 | L49: 518.16095 | M49: 5031.5889 | O49: 4723.4669 | P49: 308.12199 | Q49: 5106.8535 | R49: 4887.518 | S49: 219.33557
A50: 43 | I50: П | J50: 0 | K50: 0 | L50: 0 | M50: 0 | O50: 0 | P50: 0 | Q50: -1251.6985 | R50: -1251.6985 | S50: 0
A51: 44 | F51: 1418 | H51: Нараховані доходи за борговими цінними паперами, що рефінансуються Національним банком України, які обліковуються за справедливою вартістю через інший сукупний дохід | I51: А | J51: 29527.794 | K51: 29205.221 | L51: 322.57284 | M51: 26215.894 | O51: 26134.036 | P51: 81.85792 | Q51: 29157.481 | R51: 28874.361 | S51: 283.1201
A52: 45 | F52: 1419 | H52: Резерв за борговими цінними паперами,що рефінансуються Національним банком України, які обліковуються за справедливою вартістю через інший сукупний дохід | I52: П | J52: 0 | K52: 0 | L52: 0 | M52: 0 | O52: 0 | P52: 0 | Q52: 0 | R52: 0 | S52: 0
A53: 46 | F53: Група 141 - Усього | J53: 230048.24 | K53: 174923.81 | L53: 55124.425 | M53: 400765.57 | O53: 375941 | P53: 24824.573 | Q53: 868502.89 | R53: 826408.37 | S53: 42094.521
A54: 47 | D54: 142 | F54: 1420 | H54: Облігації внутрішньої державної позики, що рефінансуються Національним банком України, які обліковуються за амортизованою собівартістю | I54: А | J54: 0 | K54: 0 | L54: 0 | M54: 0 | O54: 0 | P54: 0 | Q54: 0 | R54: 0 | S54: 0
A55: 48 | F55: 1426 | H55: Неамортизована премія/дисконт за борговими цінними паперами, що рефінансуються Національним банком України, які обліковуються за амортизованою собівартістю | I55: А | J55: 0 | K55: 0 | L55: 0 | M55: 0 | O55: 0 | P55: 0 | Q55: 0 | R55: 0 | S55: 0
A56: 49 | I56: П | J56: 0 | K56: 0 | L56: 0 | M56: 0 | O56: 0 | P56: 0 | Q56: 0 | R56: 0 | S56: 0
A57: 50 | F57: 1428 | H57: Нараховані доходи за борговими цінними паперами, що рефінансуються Національним банком України, які обліковуються за амортизованою собівартістю | I57: А | J57: 0 | K57: 0 | L57: 0 | M57: 0 | O57: 0 | P57: 0 | Q57: 0 | R57: 0 | S57: 0
A58: 51 | F58: 1429 | H58: Резерв за борговими цінними паперами,що рефінансуються Національним банком України, які обліковуються за амортизованою собівартістю | I58: П | J58: 0 | K58: 0 | L58: 0 | M58: 0 | O58: 0 | P58: 0 | Q58: 0 | R58: 0 | S58: 0
A59: 52 | F59: Група 142 - Усього | J59: 0 | K59: 0 | L59: 0 | M59: 0 | O59: 0 | P59: 0 | Q59: 0 | R59: 0 | S59: 0
A60: 53 | D60: 143 | F60: 1430 | H60: Депозитні сертифікати Національного банку України, розміщені в банках України, що обліковуються за справедливою вартістю через інший сукупний дохід | I60: А | J60: 0 | K60: 0 | L60: 0 | M60: 0 | O60: 0 | P60: 0 | Q60: 0 | R60: 0 | S60: 0
A61: 54 | F61: 1435 | H61: Переоцінка депозитних сертифікатів Національного банку України, розміщених у банках України, що обліковуються за справедливою вартістю через інший сукупний дохід | I61: А | J61: 0 | K61: 0 | L61: 0 | M61: 0 | O61: 0 | P61: 0 | Q61: 0 | R61: 0 | S61: 0
A62: 55 | F62: 1436 | H62: Неамортизована премія/дисконт за депозитними сертифікатами Національного банку України, розміщеними в банках України, що обліковуються за справедливою вартістю через інший сукупний дохід | I62: А | J62: 0 | K62: 0 | L62: 0 | M62: 0 | O62: 0 | P62: 0 | Q62: 0 | R62: 0 | S62: 0
A63: 56 | I63: П | J63: 0 | K63: 0 | L63: 0 | M63: 0 | O63: 0 | P63: 0 | Q63: 0 | R63: 0 | S63: 0
A64: 57 | F64: 1438 | H64: Нараховані доходи за депозитними сертифікатами Національного банку України, розміщеними в банках України, що обліковуються за справедливою вартістю через інший сукупний дохід | I64: А | J64: 0 | K64: 0 | L64: 0 | M64: 0 | O64: 0 | P64: 0 | Q64: 0 | R64: 0 | S64: 0
A65: 58 | F65: Група 143 - Усього | J65: 0 | K65: 0 | L65: 0 | M65: 0 | O65: 0 | P65: 0 | Q65: 0 | R65: 0 | S65: 0
A66: 59 | D66: 144 | F66: 1440 | H66: Депозитні сертифікати Національного банку України, розміщені в банках України, що обліковуються за амортизованою собівартістю | I66: А | J66: 1667000 | K66: 1667000 | L66: 0 | M66: 1435000 | O66: 1435000 | P66: 0 | Q66: 616000 | R66: 616000 | S66: 0
A67: 60 | F67: 1446 | H67: Неамортизована премія/дисконт за депозитними сертифікатами Національного банку України, розміщеними в банках України, що обліковуються за амортизованою собівартістю | I67: А | J67: 0 | K67: 0 | L67: 0 | M67: 0 | O67: 0 | P67: 0 | Q67: 0 | R67: 0 | S67: 0
A68: 61 | I68: П | J68: 0 | K68: 0 | L68: 0 | M68: 0 | O68: 0 | P68: 0 | Q68: 0 | R68: 0 | S68: 0
A69: 62 | F69: 1448 | H69: Нараховані доходи за депозитними сертифікатами Національного банку України, розміщеними в банках України, що обліковуються за амортизованою собівартістю | I69: А | J69: 7016.6736 | K69: 7016.6736 | L69: 0 | M69: 6063.2903 | O69: 6063.2903 | P69: 0 | Q69: 10510.643 | R69: 10510.643 | S69: 0
A70: 63 | F70: Група 144 - Усього | J70: 1674016.7 | K70: 1674016.7 | L70: 0 | M70: 1441063.3 | O70: 1441063.3 | P70: 0 | Q70: 626510.64 | R70: 626510.64 | S70: 0
A71: 64 | D71: Розділ 14 - Усього | J71: 1904064.9 | K71: 1848940.5 | L71: 55124.425 | M71: 1841828.9 | O71: 1817004.3 | P71: 24824.573 | Q71: 1495013.5 | R71: 1452919 | S71: 42094.521
A72: 65 | C72: 15 | D72: 150 | F72: 1500 | H72: Кореспондентські рахунки, що відкриті в інших банках | I72: А | J72: 3983368 | K72: 47979.706 | L72: 3935388.3 | M72: 3926271.3 | O72: 47896.031 | P72: 3878375.3 | Q72: 125407.29 | R72: 198.3414 | S72: 125208.95
A73: 66 | F73: 1508 | H73: Нараховані доходи за коштами на вимогу в інших банках | I73: А | J73: 0 | K73: 0 | L73: 0 | M73: 0 | O73: 0 | P73: 0 | Q73: 0 | R73: 0 | S73: 0
A74: 67 | F74: 1509 | H74: Резерв за коштами на вимогу в інших банках | I74: П | J74: 17.10586 | K74: 0.00836 | L74: 17.0975 | M74: 9.95594 | O74: 0.01359 | P74: 9.94235 | Q74: -1367.3847 | R74: -0.03975 | S74: -1367.345
A75: 68 | F75: Група 150 - Усього | J75: 3983385.1 | K75: 47979.715 | L75: 3935405.4 | M75: 3926281.2 | O75: 47896.045 | P75: 3878385.2 | Q75: 124039.9 | R75: 198.30165 | S75: 123841.6
A76: 69 | D76: 151 | F76: 1510 | H76: Депозити овернайт, що розміщені в інших банках, які обліковуються за амортизованою собівартістю | I76: А | J76: 0 | K76: 0 | L76: 0 | M76: 0 | O76: 0 | P76: 0 | Q76: 0 | R76: 0 | S76: 0
A77: 70 | F77: 1513 | H77: Строкові вклади (депозити), що розміщені в інших банках, які обліковуються за амортизованою собівартістю | I77: А | J77: 0 | K77: 0 | L77: 0 | M77: 0 | O77: 0 | P77: 0 | Q77: 0 | R77: 0 | S77: 0
A78: 71 | F78: 1516 | H78: Неамортизована премія/дисконт за строковими вкладами (депозитами), що розміщені в інших банках, які обліковуються за амортизованою собівартістю | I78: А | J78: 0 | K78: 0 | L78: 0 | M78: 0 | O78: 0 | P78: 0 | Q78: 0 | R78: 0 | S78: 0
A79: 72 | I79: П | J79: 0 | K79: 0 | L79: 0 | M79: 0 | O79: 0 | P79: 0 | Q79: 0 | R79: 0 | S79: 0
A80: 73 | F80: 1518 | H80: Нараховані доходи за строковими вкладами (депозитами), що розміщені в інших банках, які обліковуються за амортизованою собівартістю | I80: А | J80: 0 | K80: 0 | L80: 0 | M80: 0 | O80: 0 | P80: 0 | Q80: 0 | R80: 0 | S80: 0
A81: 74 | F81: 1519 | H81: Резерв за строковими вкладами (депозитами), що розміщені в інших банках, які обліковуються за амортизованою собівартістю | I81: П | J81: 0 | K81: 0 | L81: 0 | M81: 0 | O81: 0 | P81: 0 | Q81: 0 | R81: 0 | S81: 0
A82: 75 | F82: Група 151 - Усього | J82: 0 | K82: 0 | L82: 0 | M82: 0 | O82: 0 | P82: 0 | Q82: 0 | R82: 0 | S82: 0
A83: 76 | D83: 152 | F83: 1521 | H83: Кредити овернайт, що надані іншим банкам,які обліковуються за амортизованою собівартістю | I83: А | J83: 126429 | K83: 0 | L83: 126429 | M83: 126429 | O83: 0 | P83: 126429 | Q83: 0 | R83: 0 | S83: 0
A84: 77 | F84: 1522 | H84: Кредити, що надані іншим банкам за операціями репо, які обліковуються за амортизованою собівартістю | I84: А | J84: 0 | K84: 0 | L84: 0 | M84: 0 | O84: 0 | P84: 0 | Q84: 0 | R84: 0 | S84: 0
A85: 78 | F85: 1524 | H85: Інші кредити, що надані іншим банкам, які обліковуються за амортизованою собівартістю | I85: А | J85: 0 | K85: 0 | L85: 0 | M85: 0 | O85: 0 | P85: 0 | Q85: 0 | R85: 0 | S85: 0
A86: 79 | F86: 1526 | H86: Неамортизована премія/дисконт за кредитами, що надані іншим банкам, які обліковуються за амортизованою собівартістю | I86: А | J86: 0 | K86: 0 | L86: 0 | M86: 0 | O86: 0 | P86: 0 | Q86: 0 | R86: 0 | S86: 0
A87: 80 | I87: П | J87: 0 | K87: 0 | L87: 0 | M87: 0 | O87: 0 | P87: 0 | Q87: 0 | R87: 0 | S87: 0
A88: 81 | F88: 1528 | H88: Нараховані доходи за кредитами, що надані іншим банкам, які обліковуються за амортизованою собівартістю | I88: А | J88: 15.58822 | K88: 0 | L88: 15.58822 | M88: 15.58822 | O88: 0 | P88: 15.58822 | Q88: 0 | R88: 0 | S88: 0
A89: 82 | F89: 1529 | H89: Резерв за кредитами, що надані іншим банкам, які обліковуються за амортизованою собівартістю | I89: П | J89: 0 | K89: 0 | L89: 0 | M89: 0 | O89: 0 | P89: 0 | Q89: 0 | R89: 0 | S89: 0
A90: 83 | F90: Група 152 - Усього | J90: 126444.59 | K90: 0 | L90: 126444.59 | M90: 126444.59 | O90: 0 | P90: 126444.59 | Q90: 0 | R90: 0 | S90: 0
A91: 84 | D91: Розділ 15 - Усього | J91: 4109829.7 | K91: 47979.715 | L91: 4061850 | M91: 4052725.8 | O91: 47896.045 | P91: 4004829.8 | Q91: 124039.9 | R91: 198.30165 | S91: 123841.6
A92: 85 | C92: 16 | D92: 160 | F92: 1600 | H92: Кореспондентські рахунки інших банків | I92: А | J92: 0 | K92: 0 | L92: 0 | M92: 0 | O92: 0 | P92: 0 | Q92: 0 | R92: 0 | S92: 0
A93: 86 | F93: Група 160 - Усього | J93: 0 | K93: 0 | L93: 0 | M93: 0 | O93: 0 | P93: 0 | Q93: 0 | R93: 0 | S93: 0
A94: 87 | D94: Розділ 16 - Усього | J94: 0 | K94: 0 | L94: 0 | M94: 0 | O94: 0 | P94: 0 | Q94: 0 | R94: 0 | S94: 0
A95: 88 | C95: 18 | D95: 181 | F95: 1811 | H95: Дебіторська заборгованість за операціями з готівкою | I95: А | J95: 7060 | K95: 7060 | L95: 0 | M95: 6914.9 | O95: 6914.9 | P95: 0 | Q95: 145.1 | R95: 145.1 | S95: 0
A96: 89 | F96: 1819 | H96: Інша дебіторська заборгованість за операціями з банками | I96: А | J96: 2469361.8 | K96: 204549.58 | L96: 2264812.2 | M96: 2469361.8 | O96: 204549.58 | P96: 2264812.2 | Q96: 0 | R96: 0 | S96: 0
A97: 90 | F97: Група 181 - Усього | J97: 2476421.8 | K97: 211609.58 | L97: 2264812.2 | M97: 2476276.7 | O97: 211464.48 | P97: 2264812.2 | Q97: 145.1 | R97: 145.1 | S97: 0
A98: 91 | D98: 183 | F98: 1832 | H98: Кошти банків у розрахунках | I98: А | J98: 9888.6812 | K98: 5902.3474 | L98: 3986.3338 | M98: 10342.303 | O98: 2543.4864 | P98: 7798.8168 | Q98: 30377.879 | R98: 18992.458 | S98: 11385.421
A99: 92 | F99: 1839 | H99: Резерви за коштами банків у розрахунках | I99: П | J99: 16.91152 | K99: 0.71377 | L99: 16.19775 | M99: 14.47766 | O99: 13.52986 | P99: 0.9478 | Q99: -121.69416 | R99: -76.15252 | S99: -45.54164
A100: 93 | F100: Група 183 - Усього | J100: 9905.5927 | K100: 5903.0611 | L100: 4002.5316 | M100: 10356.781 | O100: 2557.0162 | P100: 7799.7646 | Q100: 30256.185 | R100: 18916.306 | S100: 11339.88
...
