Workbook

Sheet Index
C2: Оборотно-сальдовий баланс банку* | D2: відповідно до Додатку 1 до постанови Правління Національного банку України
D3: від 15 березня 2018 року № 11 "Про встановлення переліку інформації, що підлягає обов'язковому опублікуванню банками України" (зі змінами)
D4: за даними статистичної звітності з файлів 02X "Дані про обороти та залишки на рахунках".
A5: NKB | B5: Порядковий номер | C5: Назва банку | D5: Категорія банку | E5: МФО | F5: ПРОЦЕНТИ ЗА ДЕПОЗИТНИМИ СЕРТИФІКАТАМИ (ДС), тис. грн | G5: ПРОЦЕНТИ ЗА ОВДП (ОВДП), тис.грн | H5: ПРОЦЕНТИ ЗА КРЕДИТАМИ ЗДУ | I5: ПРОЦЕНТИ ЗА КРЕДИТАМИ БІЗНЕСУ | J5: ПРОЦЕНТИ ЗА КРЕДИТАМИ НАСЕЛЕННЮ | K5: ПРОЦЕНТНІ ДОХОДИ ВСЬОГО (ПД), тис. грн | L5: ДС/ПД, % | M5: ДС до підсумку, % | N5: (ДС+ОВДП)/ПД, % | O5: ОВДП/ПД, % | P5: ОВДП до підсумку | Q5: Обсяг ДС | R5: Кошти в НБУ (кор.рахунок) (кредит) (код 1200) | S5: Кошти в НБУ (УСЬОГО) (кредит) (розділ 12) | T5: Проценти за поточними вкладами ДГ (код 7040) | U5: Проценти за строковими вкладами ДГ (код 7041) | V5: Кредити субʼєктам господарювання (р.20, р.23, 260) | W5: Кредити ЗДУ (р.21) | X5: Кредити фізичним особам (р. 22, 24, 262) | Y5: Кредити небанківським установам (265) | Z5: Прибуток звітного року (5040) | AA5: Збиток звітного року (5041) | AB5: Податок на прибуток (7900) | AC5: Інші податки (741) | AD5: Відрахування в резерви (770) | AE5: Загальні доходи (6) | AF5: Загальні витрати (7)
A6: 2 | B6: 1 | C6: АТ "Укрексімбанк" | D6: Державний | E6: 322313 | F6: =' 2АТ "Укрексімбанк" '!O1130 | G6: =' 2АТ "Укрексімбанк" '!O1129 | H6: =' 2АТ "Укрексімбанк" '!O1140 | I6: =' 2АТ "Укрексімбанк" '!O1138 | J6: =' 2АТ "Укрексімбанк" '!O1139 | K6: =' 2АТ "Укрексімбанк" '!O1134 | L6: =IFERROR(F6/K6*100,0) | M6: =IFERROR(F6/SUM(F6:F11)*100,0) | N6: =IFERROR((F6+G6)/K6*100,0) | O6: =IFERROR(G6/K6*100,0) | P6: =IFERROR(G6/SUM(G6:G11)*100,0) | Q6: =' 2АТ "Укрексімбанк" '!O1131 | R6: =' 2АТ "Укрексімбанк" '!L1132 | S6: =' 2АТ "Укрексімбанк" '!L1133 | T6: =' 2АТ "Укрексімбанк" '!O1141 | U6: =' 2АТ "Укрексімбанк" '!O1142 | V6: =' 2АТ "Укрексімбанк" '!O1144 | W6: =' 2АТ "Укрексімбанк" '!O1145 | X6: =' 2АТ "Укрексімбанк" '!O1146 | Y6: =' 2АТ "Укрексімбанк" '!O1147 | Z6: =' 2АТ "Укрексімбанк" '!O1148 | AA6: =' 2АТ "Укрексімбанк" '!O1149 | AB6: =' 2АТ "Укрексімбанк" '!O1150 | AC6: =' 2АТ "Укрексімбанк" '!O1151 | AD6: =' 2АТ "Укрексімбанк" '!O1152 | AE6: =' 2АТ "Укрексімбанк" '!O1153 | AF6: =' 2АТ "Укрексімбанк" '!O1154
A7: 6 | B7: 2 | C7: АТ "Ощадбанк" | D7: Державний | E7: 300465 | F7: =' 6АТ "Ощадбанк" '!O1130 | G7: =' 6АТ "Ощадбанк" '!O1129 | H7: =' 6АТ "Ощадбанк" '!O1140 | I7: =' 6АТ "Ощадбанк" '!O1138 | J7: =' 6АТ "Ощадбанк" '!O1139 | K7: =' 6АТ "Ощадбанк" '!O1134 | L7: =IFERROR(F7/K7*100,0) | M7: =IFERROR(F7/SUM(F6:F11)*100,0) | N7: =IFERROR((F7+G7)/K7*100,0) | O7: =IFERROR(G7/K7*100,0) | P7: =IFERROR(G7/SUM(G6:G11)*100,0) | Q7: =' 6АТ "Ощадбанк" '!O1131 | R7: =' 6АТ "Ощадбанк" '!L1132 | S7: =' 6АТ "Ощадбанк" '!L1133 | T7: =' 6АТ "Ощадбанк" '!O1141 | U7: =' 6АТ "Ощадбанк" '!O1142 | V7: =' 6АТ "Ощадбанк" '!O1144 | W7: =' 6АТ "Ощадбанк" '!O1145 | X7: =' 6АТ "Ощадбанк" '!O1146 | Y7: =' 6АТ "Ощадбанк" '!O1147 | Z7: =' 6АТ "Ощадбанк" '!O1148 | AA7: =' 6АТ "Ощадбанк" '!O1149 | AB7: =' 6АТ "Ощадбанк" '!O1150 | AC7: =' 6АТ "Ощадбанк" '!O1151 | AD7: =' 6АТ "Ощадбанк" '!O1152 | AE7: =' 6АТ "Ощадбанк" '!O1153 | AF7: =' 6АТ "Ощадбанк" '!O1154
A8: 29 | B8: 3 | C8: АТ "БАНК АЛЬЯНС" | D8: Приватний капітал | E8: 300119 | F8: =' 29АТ "БАНК АЛЬЯНС" '!O1130 | G8: =' 29АТ "БАНК АЛЬЯНС" '!O1129 | H8: =' 29АТ "БАНК АЛЬЯНС" '!O1140 | I8: =' 29АТ "БАНК АЛЬЯНС" '!O1138 | J8: =' 29АТ "БАНК АЛЬЯНС" '!O1139 | K8: =' 29АТ "БАНК АЛЬЯНС" '!O1134 | L8: =IFERROR(F8/K8*100,0) | M8: =IFERROR(F8/SUM(F6:F11)*100,0) | N8: =IFERROR((F8+G8)/K8*100,0) | O8: =IFERROR(G8/K8*100,0) | P8: =IFERROR(G8/SUM(G6:G11)*100,0) | Q8: =' 29АТ "БАНК АЛЬЯНС" '!O1131 | R8: =' 29АТ "БАНК АЛЬЯНС" '!L1132 | S8: =' 29АТ "БАНК АЛЬЯНС" '!L1133 | T8: =' 29АТ "БАНК АЛЬЯНС" '!O1141 | U8: =' 29АТ "БАНК АЛЬЯНС" '!O1142 | V8: =' 29АТ "БАНК АЛЬЯНС" '!O1144 | W8: =' 29АТ "БАНК АЛЬЯНС" '!O1145 | X8: =' 29АТ "БАНК АЛЬЯНС" '!O1146 | Y8: =' 29АТ "БАНК АЛЬЯНС" '!O1147 | Z8: =' 29АТ "БАНК АЛЬЯНС" '!O1148 | AA8: =' 29АТ "БАНК АЛЬЯНС" '!O1149 | AB8: =' 29АТ "БАНК АЛЬЯНС" '!O1150 | AC8: =' 29АТ "БАНК АЛЬЯНС" '!O1151 | AD8: =' 29АТ "БАНК АЛЬЯНС" '!O1152 | AE8: =' 29АТ "БАНК АЛЬЯНС" '!O1153 | AF8: =' 29АТ "БАНК АЛЬЯНС" '!O1154
A9: 36 | B9: 4 | C9: АТ "Райффайзен Банк" | D9: Іноземний капітал | E9: 300335 | F9: =' 36АТ "Райффайзен Банк" '!O1130 | G9: =' 36АТ "Райффайзен Банк" '!O1129 | H9: =' 36АТ "Райффайзен Банк" '!O1140 | I9: =' 36АТ "Райффайзен Банк" '!O1138 | J9: =' 36АТ "Райффайзен Банк" '!O1139 | K9: =' 36АТ "Райффайзен Банк" '!O1134 | L9: =IFERROR(F9/K9*100,0) | M9: =IFERROR(F9/SUM(F6:F11)*100,0) | N9: =IFERROR((F9+G9)/K9*100,0) | O9: =IFERROR(G9/K9*100,0) | P9: =IFERROR(G9/SUM(G6:G11)*100,0) | Q9: =' 36АТ "Райффайзен Банк" '!O1131 | R9: =' 36АТ "Райффайзен Банк" '!L1132 | S9: =' 36АТ "Райффайзен Банк" '!L1133 | T9: =' 36АТ "Райффайзен Банк" '!O1141 | U9: =' 36АТ "Райффайзен Банк" '!O1142 | V9: =' 36АТ "Райффайзен Банк" '!O1144 | W9: =' 36АТ "Райффайзен Банк" '!O1145 | X9: =' 36АТ "Райффайзен Банк" '!O1146 | Y9: =' 36АТ "Райффайзен Банк" '!O1147 | Z9: =' 36АТ "Райффайзен Банк" '!O1148 | AA9: =' 36АТ "Райффайзен Банк" '!O1149 | AB9: =' 36АТ "Райффайзен Банк" '!O1150 | AC9: =' 36АТ "Райффайзен Банк" '!O1151 | AD9: =' 36АТ "Райффайзен Банк" '!O1152 | AE9: =' 36АТ "Райффайзен Банк" '!O1153 | AF9: =' 36АТ "Райффайзен Банк" '!O1154
A10: 43 | B10: 5 | C10: АТ "АЛЬТБАНК" | D10: Приватний капітал | E10: 320940 | F10: =' 43АТ "АЛЬТБАНК" '!O1130 | G10: =' 43АТ "АЛЬТБАНК" '!O1129 | H10: =' 43АТ "АЛЬТБАНК" '!O1140 | I10: =' 43АТ "АЛЬТБАНК" '!O1138 | J10: =' 43АТ "АЛЬТБАНК" '!O1139 | K10: =' 43АТ "АЛЬТБАНК" '!O1134 | L10: =IFERROR(F10/K10*100,0) | M10: =IFERROR(F10/SUM(F6:F11)*100,0) | N10: =IFERROR((F10+G10)/K10*100,0) | O10: =IFERROR(G10/K10*100,0) | P10: =IFERROR(G10/SUM(G6:G11)*100,0) | Q10: =' 43АТ "АЛЬТБАНК" '!O1131 | R10: =' 43АТ "АЛЬТБАНК" '!L1132 | S10: =' 43АТ "АЛЬТБАНК" '!L1133 | T10: =' 43АТ "АЛЬТБАНК" '!O1141 | U10: =' 43АТ "АЛЬТБАНК" '!O1142 | V10: =' 43АТ "АЛЬТБАНК" '!O1144 | W10: =' 43АТ "АЛЬТБАНК" '!O1145 | X10: =' 43АТ "АЛЬТБАНК" '!O1146 | Y10: =' 43АТ "АЛЬТБАНК" '!O1147 | Z10: =' 43АТ "АЛЬТБАНК" '!O1148 | AA10: =' 43АТ "АЛЬТБАНК" '!O1149 | AB10: =' 43АТ "АЛЬТБАНК" '!O1150 | AC10: =' 43АТ "АЛЬТБАНК" '!O1151 | AD10: =' 43АТ "АЛЬТБАНК" '!O1152 | AE10: =' 43АТ "АЛЬТБАНК" '!O1153 | AF10: =' 43АТ "АЛЬТБАНК" '!O1154
A11: 381 | B11: 6 | C11: АТ "МОТОР-БАНК"нпб | D11: Інше | E11: 313009 | F11: ='381АТ "МОТОР-БАНК"нпб'!O1130 | G11: ='381АТ "МОТОР-БАНК"нпб'!O1129 | H11: ='381АТ "МОТОР-БАНК"нпб'!O1140 | I11: ='381АТ "МОТОР-БАНК"нпб'!O1138 | J11: ='381АТ "МОТОР-БАНК"нпб'!O1139 | K11: ='381АТ "МОТОР-БАНК"нпб'!O1134 | L11: =IFERROR(F11/K11*100,0) | M11: =IFERROR(F11/SUM(F6:F11)*100,0) | N11: =IFERROR((F11+G11)/K11*100,0) | O11: =IFERROR(G11/K11*100,0) | P11: =IFERROR(G11/SUM(G6:G11)*100,0) | Q11: ='381АТ "МОТОР-БАНК"нпб'!O1131 | R11: ='381АТ "МОТОР-БАНК"нпб'!L1132 | S11: ='381АТ "МОТОР-БАНК"нпб'!L1133 | T11: ='381АТ "МОТОР-БАНК"нпб'!O1141 | U11: ='381АТ "МОТОР-БАНК"нпб'!O1142 | V11: ='381АТ "МОТОР-БАНК"нпб'!O1144 | W11: ='381АТ "МОТОР-БАНК"нпб'!O1145 | X11: ='381АТ "МОТОР-БАНК"нпб'!O1146 | Y11: ='381АТ "МОТОР-БАНК"нпб'!O1147 | Z11: ='381АТ "МОТОР-БАНК"нпб'!O1148 | AA11: ='381АТ "МОТОР-БАНК"нпб'!O1149 | AB11: ='381АТ "МОТОР-БАНК"нпб'!O1150 | AC11: ='381АТ "МОТОР-БАНК"нпб'!O1151 | AD11: ='381АТ "МОТОР-БАНК"нпб'!O1152 | AE11: ='381АТ "МОТОР-БАНК"нпб'!O1153 | AF11: ='381АТ "МОТОР-БАНК"нпб'!O1154
A12: Всього | F12: =IFERROR(SUM(F6:F11),0) | G12: =IFERROR(SUM(G6:G11),0) | H12: =IFERROR(SUM(H6:H11),0) | I12: =IFERROR(SUM(I6:I11),0) | J12: =IFERROR(SUM(J6:J11),0) | K12: =IFERROR(SUM(K6:K11),0) | L12: =IFERROR(F12/K12*100,0) | M12: =IFERROR(F12/SUM(F6:F11)*100,0) | N12: =IFERROR((F12+G12)/K12*100,0) | O12: =IFERROR(G12/K12*100,0) | P12: =IFERROR(G12/SUM(G6:G11)*100,0) | Q12: =IFERROR(SUM(Q6:Q11),0) | R12: =IFERROR(SUM(R6:R11),0) | S12: =IFERROR(SUM(S6:S11),0) | T12: =IFERROR(SUM(T6:T11),0) | U12: =IFERROR(SUM(U6:U11),0) | V12: =IFERROR(SUM(V6:V11),0) | W12: =IFERROR(SUM(W6:W11),0) | X12: =IFERROR(SUM(X6:X11),0) | ... AF12: =IFERROR(SUM(AF6:AF11),0)
A13: Державні банки | D13: 2 банк(и/ів) | F13: =IFERROR(SUM(F6,F7),0) | G13: =IFERROR(SUM(G6,G7),0) | H13: =IFERROR(SUM(H6,H7),0) | I13: =IFERROR(SUM(I6,I7),0) | J13: =IFERROR(SUM(J6,J7),0) | K13: =IFERROR(SUM(K6,K7),0) | L13: =IFERROR(F13/K13*100,0) | M13: =IFERROR(F13/F12*100,0) | N13: =IFERROR(SUM(N6,N7),0) | O13: =IFERROR(SUM(O6,O7),0) | P13: =IFERROR(G13/G12*100,0) | Q13: =IFERROR(SUM(Q6,Q7),0) | R13: =IFERROR(SUM(R6,R7),0) | S13: =IFERROR(SUM(S6,S7),0) | T13: =IFERROR(SUM(T6,T7),0) | U13: =IFERROR(SUM(U6,U7),0) | V13: =IFERROR(SUM(V6,V7),0) | W13: =IFERROR(SUM(W6,W7),0) | X13: =IFERROR(SUM(X6,X7),0) | ... AF13: =IFERROR(SUM(AF6,AF7),0)
A14: Банки з іноземним капіталом | D14: 1 банк(и/ів) | F14: =IFERROR(SUM(F9),0) | G14: =IFERROR(SUM(G9),0) | H14: =IFERROR(SUM(H9),0) | I14: =IFERROR(SUM(I9),0) | J14: =IFERROR(SUM(J9),0) | K14: =IFERROR(SUM(K9),0) | L14: =IFERROR(F14/K14*100,0) | M14: =IFERROR(F14/F12*100,0) | N14: =IFERROR(SUM(N9),0) | O14: =IFERROR(SUM(O9),0) | P14: =IFERROR(G14/G12*100,0) | Q14: =IFERROR(SUM(Q9),0) | R14: =IFERROR(SUM(R9),0) | S14: =IFERROR(SUM(S9),0) | T14: =IFERROR(SUM(T9),0) | U14: =IFERROR(SUM(U9),0) | V14: =IFERROR(SUM(V9),0) | W14: =IFERROR(SUM(W9),0) | X14: =IFERROR(SUM(X9),0) | ... AF14: =IFERROR(SUM(AF9),0)
A15: Банки з українським приватним капіталом | D15: 2 банк(и/ів) | F15: =IFERROR(SUM(F8,F10),0) | G15: =IFERROR(SUM(G8,G10),0) | H15: =IFERROR(SUM(H8,H10),0) | I15: =IFERROR(SUM(I8,I10),0) | J15: =IFERROR(SUM(J8,J10),0) | K15: =IFERROR(SUM(K8,K10),0) | L15: =IFERROR(F15/K15*100,0) | M15: =IFERROR(F15/F12*100,0) | N15: =IFERROR(SUM(N8,N10),0) | O15: =IFERROR(SUM(O8,O10),0) | P15: =IFERROR(G15/G12*100,0) | Q15: =IFERROR(SUM(Q8,Q10),0) | R15: =IFERROR(SUM(R8,R10),0) | S15: =IFERROR(SUM(S8,S10),0) | T15: =IFERROR(SUM(T8,T10),0) | U15: =IFERROR(SUM(U8,U10),0) | V15: =IFERROR(SUM(V8,V10),0) | W15: =IFERROR(SUM(W8,W10),0) | X15: =IFERROR(SUM(X8,X10),0) | ... AF15: =IFERROR(SUM(AF8,AF10),0)
A16: Інші банки | D16: 1 банк(и/ів) | F16: =IFERROR(SUM(F11),0) | G16: =IFERROR(SUM(G11),0) | H16: =IFERROR(SUM(H11),0) | I16: =IFERROR(SUM(I11),0) | J16: =IFERROR(SUM(J11),0) | K16: =IFERROR(SUM(K11),0) | L16: =IFERROR(F16/K16*100,0) | M16: =IFERROR(F16/F12*100,0) | N16: =IFERROR(SUM(N11),0) | O16: =IFERROR(SUM(O11),0) | P16: =IFERROR(G16/G12*100,0) | Q16: =IFERROR(SUM(Q11),0) | R16: =IFERROR(SUM(R11),0) | S16: =IFERROR(SUM(S11),0) | T16: =IFERROR(SUM(T11),0) | U16: =IFERROR(SUM(U11),0) | V16: =IFERROR(SUM(V11),0) | W16: =IFERROR(SUM(W11),0) | X16: =IFERROR(SUM(X11),0) | ... AF16: =IFERROR(SUM(AF11),0)
B18: Категорія | C18: ДС/ПД, % | H18: Категорія | I18: ДС до підсумку, %
B19: =A13 | C19: =IFERROR(L13,0) | H19: =A13 | I19: =IFERROR(M13,0)
B20: =A14 | C20: =IFERROR(L14,0) | H20: =A14 | I20: =IFERROR(M14,0)
B21: =A15 | C21: =IFERROR(L15,0) | H21: =A15 | I21: =IFERROR(M15,0)
B22: =A16 | C22: =IFERROR(L16,0) | H22: =A16 | I22: =IFERROR(M16,0)

Sheet Indicator_Summary
A1: ПРОЦЕНТНІ ДОХОДИ банків
B2: млрд | C2: %
A3: Депозитні сертифікати | B3: =SUM(Index!F6:F11)/1000000 | C3: =B3/B8 * 100
A4: ОВДП | B4: =SUM(Index!G6:G11)/1000000 | C4: =B4/B8 * 100
A5: Кредити бізнесу | B5: =SUM(Index!I6:I11)/1000000 | C5: =B5/B8 * 100
A6: Кредити населенню | B6: =SUM(Index!J6:J11)/1000000 | C6: =B6/B8 * 100
A7: Інші процентні доходи | B7: =B8 - (B3 +B4 +B5 +B6) | C7: =B7/B8 * 100
A8: ВСЬОГО | B8: =SUM(Index!K6:K11)/1000000 | C8: 100

Sheet Pivot_Data
A1: bank_code | B1: bank_name | C1: bank_class | D1: Kind | E1: indicator | F1: Class | G1: Division | H1: Group | I1: Balance | J1: Name | K1: Kind_Mark | L1: Debit_Total | M1: Debit_NC | N1: Debit_IC | O1: Credit_Total | P1: Credit_NC | Q1: Credit_IC | R1: Balance_Total | S1: Balance_NC | T1: Balance_IC
A2: 2 | B2: АТ "Укрексімбанк" | C2: державний | D2: Активи | E2: (без привʼязки) | F2: 1 | G2: 10 | H2: 100 | I2: 1001 | J2: Банкноти та монети в касі банку | K2: А | L2: 2232019.4 | M2: 1053099.1 | N2: 1178920.3 | O2: 2266548.1 | P2: 1055118 | Q2: 1211430.1 | R2: 803299.8 | S2: 221112.15 | T2: 582187.66
A3: 2 | B3: АТ "Укрексімбанк" | C3: державний | D3: Активи | E3: (без привʼязки) | F3: 1 | G3: 10 | H3: 100 | I3: 1002 | J3: Банкноти та монети в касі відділень банку | K3: А | L3: 92541.798 | M3: 42633.366 | N3: 49908.432 | O3: 91942.424 | P3: 40331.164 | Q3: 51611.26 | R3: 15163.933 | S3: 4553.7256 | T3: 10610.208
A4: 2 | B4: АТ "Укрексімбанк" | C4: державний | D4: Активи | E4: (без привʼязки) | F4: 1 | G4: 10 | H4: 100 | I4: 1004 | J4: Банкноти та монети в банкоматах | K4: А | L4: 1093212.5 | M4: 1093212.5 | N4: 0 | O4: 1127848.9 | P4: 1127848.9 | Q4: 0 | R4: 263889.59 | S4: 263889.59 | T4: 0
A5: 2 | B5: АТ "Укрексімбанк" | C5: державний | D5: Активи | E5: (без привʼязки) | F5: 1 | G5: 10 | H5: 100 | I5: 1005 | J5: Банкноти та монети, інкасовані до перерахування | K5: А | L5: 62532.715 | M5: 62532.715 | N5: 0 | O5: 62532.715 | P5: 62532.715 | Q5: 0 | R5: 0 | S5: 0 | T5: 0
A6: 2 | B6: АТ "Укрексімбанк" | C6: державний | D6: Активи | E6: (без привʼязки) | F6: 1 | G6: 10 | H6: 100 | I6: 1006 | J6: Банкноти та монети на зберіганні в інкасаторській компанії | K6: А | L6: 0 | M6: 0 | N6: 0 | O6: 0 | P6: 0 | Q6: 0 | R6: 0 | S6: 0 | T6: 0
A7: 2 | B7: АТ "Укрексімбанк" | C7: державний | D7: Активи | E7: (без привʼязки) | F7: 1 | G7: 10 | H7: 100 | I7: 1007 | J7: Банкноти та монети в дорозі | K7: А | L7: 572012.05 | M7: 168067.05 | N7: 403945 | O7: 516742.42 | P7: 158139.23 | Q7: 358603.18 | R7: 57529.923 | S7: 9927.8134 | T7: 47602.11
A8: 2 | B8: АТ "Укрексімбанк" | C8: державний | D8: Активи | E8: (без привʼязки) | F8: 1 | G8: 10 | H8: 101 | I8: 1011 | J8: Дорожні чеки в касі банку | K8: А | L8: 0 | M8: 0 | N8: 0 | O8: 0 | P8: 0 | Q8: 0 | R8: 0 | S8: 0 | T8: 0
A9: 2 | B9: АТ "Укрексімбанк" | C9: державний | D9: Активи | E9: (без привʼязки) | F9: 1 | G9: 10 | H9: 101 | I9: 1012 | J9: Дорожні чеки в касі відділень банку | K9: А | L9: 0 | M9: 0 | N9: 0 | O9: 0 | P9: 0 | Q9: 0 | R9: 0 | S9: 0 | T9: 0
A10: 2 | B10: АТ "Укрексімбанк" | C10: державний | D10: Активи | E10: (без привʼязки) | F10: 1 | G10: 10 | H10: 109 | I10: 1090 | J10: Резерви за готівковими коштами, наявність яких є непідтвердженою | K10: П | L10: 580.24613 | M10: 0 | N10: 580.24613 | O10: 862.24315 | P10: 0 | Q10: 862.24315 | R10: -52091.86 | S10: -5377.8999 | T10: -46713.96
A11: 2 | B11: АТ "Укрексімбанк" | C11: державний | D11: Активи | E11: (без привʼязки) | F11: 1 | G11: 11 | H11: 110 | I11: 1101 | J11: Банківські метали в банку | K11: А | L11: 0 | M11: 0 | N11: 0 | O11: 0 | P11: 0 | Q11: 0 | R11: 0 | S11: 0 | T11: 0
A12: 2 | B12: АТ "Укрексімбанк" | C12: державний | D12: Активи | E12: (без привʼязки) | F12: 1 | G12: 11 | H12: 110 | I12: 1102 | J12: Банківські метали у відділенні банку | K12: А | L12: 0 | M12: 0 | N12: 0 | O12: 0 | P12: 0 | Q12: 0 | R12: 0 | S12: 0 | T12: 0
A13: 2 | B13: АТ "Укрексімбанк" | C13: державний | D13: Активи | E13: (без привʼязки) | F13: 1 | G13: 11 | H13: 110 | I13: 1107 | J13: Банківські метали в дорозі | K13: А | L13: 0 | M13: 0 | N13: 0 | O13: 0 | P13: 0 | Q13: 0 | R13: 0 | S13: 0 | T13: 0
... A4699: 43 | B4699: АТ "АЛЬТБАНК" | C4699: приватний | D4699: Пасиви | E4699: (без привʼязки) | F4699: 9 | G4699: 99 | H4699: 992 | I4699: 9920 | J4699: Позабалансова позиція банку за іноземною валютою та банківськими металами | K4699: П | L4699: 0 | M4699: 0 | N4699: 0 | O4699: 0 | P4699: 0 | Q4699: 0 | R4699: 0 | S4699: 0 | T4699: 0

Sheet Зміст
B2: Оборотно-сальдовий баланс банку* | C2: відповідно до підпункту 1 пункту 2 постанови Правління Національного банку України
C3: від 15 березня 2018 року № 11 “Про встановлення переліку інформації, що підлягає обов'язковому опублікуванню банками України” (зі змінами)
C4: за даними статистичної звітності з файлу 02X “Дані про обороти та залишки на рахунках”.
A6: NKB | B6: Назва | C6: МФО
A7: 2 | B7: АТ "Укрексімбанк" | C7: 322313
A8: 6 | B8: АТ "ОЩАДБАНК" | C8: 300465
A9: 29 | B9: АТ "БАНК АЛЬЯНС" | C9: 300119
A10: 36 | B10: АТ "Райффайзен Банк" | C10: 300335
A11: 43 | B11: АТ "АЛЬТБАНК" | C11: 320940
A12: 46 | B12: АТ КБ "ПриватБанк" | C12: 305299
A13: 49 | B13: Полікомбанк | C13: 353100
A14: 62 | B14: АТ "ТАСКОМБАНК" | C14: 339500
A15: 72 | B15: ПрАТ "БАНК ФАМІЛЬНИЙ" | C15: 334840
A16: 88 | B16: АТ "КРЕДОБАНК" | C16: 325365
A17: 91 | B17: АТ АКБ "Львів" | C17: 325268
... A65: 694 | B65: АТ "КРИСТАЛБАНК" | C65: 339050
A66: 695 | B66: ПрАТ "ПЕРЕХІДНИЙ БАНК "ЮТЕ БАНК" | C66: 370140
A68: *Неплатоспроможні банки.

Sheet   2АТ "Укрексімбанк" 
A1: Зміст
B2: Оборотно-сальдовий баланс банку АТ "Укрексімбанк" за станом на 01.03.2026
B3: (тис грн)
A4: Номер з/п | B4: Клас/ розділ/ група/ рахунок | I4: Актив/ пасив | J4: Обороти за місяць | Q4: Сальдо
J5: дебет | M5: кредит | Q5: усього | R5: НВ | S5: ІВ
B6: номер | F6: назва | J6: усього | K6: НВ | L6: ІВ | M6: усього | O6: НВ | P6: ІВ
A7: 1 | B7: 2 | F7: 3 | I7: 4 | J7: 5 | K7: 6 | L7: 7 | M7: 8 | O7: 9 | P7: 10 | Q7: 11 | R7: 12 | S7: 13
A8: 1 | B8: Балансові рахунки
A9: 2 | B9: Активи
A10: 3 | B10: Класи 1 - 4
A11: 4 | B11: Клас 1 | C11: 10 | D11: 100 | F11: 1001 | H11: Банкноти та монети в касі банку | I11: А | J11: 2232019.4 | K11: 1053099.1 | L11: 1178920.3 | M11: 2266548.1 | O11: 1055118 | P11: 1211430.1 | Q11: 803299.8 | R11: 221112.15 | S11: 582187.66
A12: 5 | F12: 1002 | H12: Банкноти та монети в касі відділень банку | I12: А | J12: 92541.798 | K12: 42633.366 | L12: 49908.432 | M12: 91942.424 | O12: 40331.164 | P12: 51611.26 | Q12: 15163.933 | R12: 4553.7256 | S12: 10610.208
A13: 6 | F13: 1004 | H13: Банкноти та монети в банкоматах | I13: А | J13: 1093212.5 | K13: 1093212.5 | L13: 0 | M13: 1127848.9 | O13: 1127848.9 | P13: 0 | Q13: 263889.59 | R13: 263889.59 | S13: 0
A14: 7 | F14: 1005 | H14: Банкноти та монети, інкасовані до перерахування | I14: А | J14: 62532.715 | K14: 62532.715 | L14: 0 | M14: 62532.715 | O14: 62532.715 | P14: 0 | Q14: 0 | R14: 0 | S14: 0
A15: 8 | F15: 1006 | H15: Банкноти та монети на зберіганні в інкасаторській компанії | I15: А | J15: 0 | K15: 0 | L15: 0 | M15: 0 | O15: 0 | P15: 0 | Q15: 0 | R15: 0 | S15: 0
A16: 9 | F16: 1007 | H16: Банкноти та монети в дорозі | I16: А | J16: 572012.05 | K16: 168067.05 | L16: 403945 | M16: 516742.42 | O16: 158139.23 | P16: 358603.18 | Q16: 57529.923 | R16: 9927.8134 | S16: 47602.11
A17: 10 | F17: Група 100 - Усього | J17: 4052318.5 | K17: 2419544.8 | L17: 1632773.7 | M17: 4065614.5 | O17: 2443970 | P17: 1621644.6 | Q17: 1139883.3 | R17: 499483.28 | S17: 640399.97
A18: 11 | D18: 101 | F18: 1011 | H18: Дорожні чеки в касі банку | I18: А | J18: 0 | K18: 0 | L18: 0 | M18: 0 | O18: 0 | P18: 0 | Q18: 0 | R18: 0 | S18: 0
A19: 12 | F19: 1012 | H19: Дорожні чеки в касі відділень банку | I19: А | J19: 0 | K19: 0 | L19: 0 | M19: 0 | O19: 0 | P19: 0 | Q19: 0 | R19: 0 | S19: 0
A20: 13 | F20: Група 101 - Усього | J20: 0 | K20: 0 | L20: 0 | M20: 0 | O20: 0 | P20: 0 | Q20: 0 | R20: 0 | S20: 0
A21: 14 | D21: 109 | F21: 1090 | H21: Резерви за готівковими коштами, наявність яких є непідтвердженою | I21: П | J21: 580.24613 | K21: 0 | L21: 580.24613 | M21: 862.24315 | O21: 0 | P21: 862.24315 | Q21: -52091.86 | R21: -5377.8999 | S21: -46713.96
A22: 15 | F22: Група 109 - Усього | J22: 580.24613 | K22: 0 | L22: 580.24613 | M22: 862.24315 | O22: 0 | P22: 862.24315 | Q22: -52091.86 | R22: -5377.8999 | S22: -46713.96
A23: 16 | D23: Розділ 10 - Усього | J23: 4052898.7 | K23: 2419544.8 | L23: 1633354 | M23: 4066476.8 | O23: 2443970 | P23: 1622506.8 | Q23: 1087791.4 | R23: 494105.38 | S23: 593686.01
A24: 17 | C24: 11 | D24: 110 | F24: 1101 | H24: Банківські метали в банку | I24: А | J24: 0 | K24: 0 | L24: 0 | M24: 0 | O24: 0 | P24: 0 | Q24: 0 | R24: 0 | S24: 0
A25: 18 | F25: 1102 | H25: Банківські метали у відділенні банку | I25: А | J25: 0 | K25: 0 | L25: 0 | M25: 0 | O25: 0 | P25: 0 | Q25: 0 | R25: 0 | S25: 0
A26: 19 | F26: 1107 | H26: Банківські метали в дорозі | I26: А | J26: 0 | K26: 0 | L26: 0 | M26: 0 | O26: 0 | P26: 0 | Q26: 0 | R26: 0 | S26: 0
A27: 20 | F27: Група 110 - Усього | J27: 0 | K27: 0 | L27: 0 | M27: 0 | O27: 0 | P27: 0 | Q27: 0 | R27: 0 | S27: 0
A28: 21 | D28: 119 | F28: 1190 | H28: Резерви за банківськими металами, наявність яких є непідтвердженою | I28: П | J28: 0 | K28: 0 | L28: 0 | M28: 0 | O28: 0 | P28: 0 | Q28: 0 | R28: 0 | S28: 0
A29: 22 | F29: Група 119 - Усього | J29: 0 | K29: 0 | L29: 0 | M29: 0 | O29: 0 | P29: 0 | Q29: 0 | R29: 0 | S29: 0
A30: 23 | D30: Розділ 11 - Усього | J30: 0 | K30: 0 | L30: 0 | M30: 0 | O30: 0 | P30: 0 | Q30: 0 | R30: 0 | S30: 0
A31: 24 | C31: 12 | D31: 120 | F31: 1200 | H31: Кореспондентський рахунок банку в Національному банку України | I31: А | J31: 9.2610004e+08 | K31: 9.2610004e+08 | L31: 0 | M31: 9.4457766e+08 | O31: 9.4457766e+08 | P31: 0 | Q31: 22264737 | R31: 22264737 | S31: 0
A32: 25 | F32: 1202 | H32: Кошти банків за рахунками умовного зберігання (ескроу) у Національному банку України | I32: А | J32: 0 | K32: 0 | L32: 0 | M32: 0 | O32: 0 | P32: 0 | Q32: 0 | R32: 0 | S32: 0
A33: 26 | F33: 1205 | H33: Кошти банків для забезпечення виконання зобов’язань перед Національним банком України за кредитами, наданими банкам, та операціями своп процентної ставки | I33: А | J33: 0 | K33: 0 | L33: 0 | M33: 0 | O33: 0 | P33: 0 | Q33: 0 | R33: 0 | S33: 0
A34: 27 | F34: 1208 | H34: Нараховані доходи за коштами на вимогу в Національному банку України | I34: А | J34: 0 | K34: 0 | L34: 0 | M34: 0 | O34: 0 | P34: 0 | Q34: 0 | R34: 0 | S34: 0
A35: 28 | F35: Група 120 - Усього | J35: 9.2610004e+08 | K35: 9.2610004e+08 | L35: 0 | M35: 9.4457766e+08 | O35: 9.4457766e+08 | P35: 0 | Q35: 22264737 | R35: 22264737 | S35: 0
A36: 29 | D36: Розділ 12 - Усього | J36: 9.2610004e+08 | K36: 9.2610004e+08 | L36: 0 | M36: 9.4457766e+08 | O36: 9.4457766e+08 | P36: 0 | Q36: 22264737 | R36: 22264737 | S36: 0
A37: 30 | C37: 14 | D37: 140 | F37: 1400 | H37: Облігації внутрішньої державної позики, що рефінансуються Національним банком України, які обліковуються за справедливою вартістю через прибутки/збитки | I37: А | J37: 14123037 | K37: 12375430 | L37: 1747606.7 | M37: 15507637 | O37: 13864351 | P37: 1643286.4 | Q37: 7224374.4 | R37: 7001935 | S37: 222439.43
A38: 31 | F38: 1405 | H38: Переоцінка боргових цінних паперів, що рефінансуються Національним банком України, які обліковуються за справедливою вартістю через прибутки/збитки | I38: А | J38: 268455.54 | K38: 267186.83 | L38: 1268.7109 | M38: 184814.09 | O38: 182117.37 | P38: 2696.7177 | Q38: 1171947 | R38: 1171814.2 | S38: 132.77157
A39: 32 | I39: П | J39: 0 | K39: 0 | L39: 0 | M39: 0 | O39: 0 | P39: 0 | Q39: -11150.005 | R39: -10297.678 | S39: -852.3269
A40: 33 | F40: 1406 | H40: Неамортизована премія/дисконт за борговими цінними паперами, що рефінансуються Національним банком України, які обліковуються за справедливою вартістю через прибутки/збитки | I40: А | J40: 157462.82 | K40: 139797.01 | L40: 17665.815 | M40: 177508.8 | O40: 161428.53 | P40: 16080.273 | Q40: 673032.14 | R40: 670533.72 | S40: 2498.4182
A41: 34 | I41: П | J41: 0 | K41: 0 | L41: 0 | M41: 0 | O41: 0 | P41: 0 | Q41: -9230.2153 | R41: -9230.1855 | S41: -0.02981
A42: 35 | F42: 1408 | H42: Нараховані доходи за борговими цінними паперами, що рефінансуються Національним банком України, які обліковуються за справедливою вартістю через прибутки/збитки | I42: А | J42: 779469.83 | K42: 770646.03 | L42: 8823.8022 | M42: 875008.92 | O42: 866759.26 | P42: 8249.6564 | Q42: 259455.05 | R42: 257804.37 | S42: 1650.6804
A43: 36 | F43: Група 140 - Усього | J43: 15328425 | K43: 13553060 | L43: 1775365 | M43: 16744969 | O43: 15074656 | P43: 1670313.1 | Q43: 9308428.4 | R43: 9082559.5 | S43: 225868.95
A44: 37 | D44: 141 | F44: 1410 | H44: Облігації внутрішньої державної позики, що рефінансуються Національним банком України, які обліковуються за справедливою вартістю через інший сукупний дохід | I44: А | J44: 0 | K44: 0 | L44: 0 | M44: 25 | O44: 25 | P44: 0 | Q44: 18642964 | R44: 18642964 | S44: 0
A45: 38 | F45: 1411 | H45: Облігації зовнішньої державної позики, що рефінансуються Національним банком України, які обліковуються за справедливою вартістю через інший сукупний дохід | I45: А | J45: 0 | K45: 0 | L45: 0 | M45: 0 | O45: 0 | P45: 0 | Q45: 0 | R45: 0 | S45: 0
A46: 39 | F46: 1412 | H46: Боргові цінні папери органів державної влади та місцевого самоврядування, що рефінансуються Національним банком України, які обліковуються за справедливою вартістю через інший сукупний дохід | I46: А | J46: 0 | K46: 0 | L46: 0 | M46: 0 | O46: 0 | P46: 0 | Q46: 0 | R46: 0 | S46: 0
A47: 40 | F47: 1415 | H47: Переоцінка боргових цінних паперів, що рефінансуються Національним банком України, які обліковуються за справедливою вартістю через інший сукупний дохід | I47: А | J47: 87825.45 | K47: 87825.45 | L47: 0 | M47: 20834.304 | O47: 20834.304 | P47: 0 | Q47: 596163.53 | R47: 596163.53 | S47: 0
A48: 41 | I48: П | J48: 0 | K48: 0 | L48: 0 | M48: 0 | O48: 0 | P48: 0 | Q48: -353578.8 | R48: -353578.8 | S48: 0
A49: 42 | F49: 1416 | H49: Неамортизована премія/дисконт за борговими цінними паперами, що рефінансуються Національним банком України, які обліковуються за справедливою вартістю через інший сукупний дохід | I49: А | J49: 434.86589 | K49: 434.86589 | L49: 0 | M49: 8394.1923 | O49: 8394.1923 | P49: 0 | Q49: 94421.057 | R49: 94421.057 | S49: 0
A50: 43 | I50: П | J50: 0 | K50: 0 | L50: 0 | M50: 0 | O50: 0 | P50: 0 | Q50: -1083.628 | R50: -1083.628 | S50: 0
A51: 44 | F51: 1418 | H51: Нараховані доходи за борговими цінними паперами, що рефінансуються Національним банком України, які обліковуються за справедливою вартістю через інший сукупний дохід | I51: А | J51: 224357.46 | K51: 224357.46 | L51: 0 | M51: 386693.66 | O51: 386693.66 | P51: 0 | Q51: 432744.89 | R51: 432744.89 | S51: 0
A52: 45 | F52: 1419 | H52: Резерв за борговими цінними паперами,що рефінансуються Національним банком України, які обліковуються за справедливою вартістю через інший сукупний дохід | I52: П | J52: 24650.147 | K52: 24650.147 | L52: 0 | M52: 3130.2114 | O52: 3130.2114 | P52: 0 | Q52: -774586.17 | R52: -774586.17 | S52: 0
A53: 46 | F53: Група 141 - Усього | J53: 337267.92 | K53: 337267.92 | L53: 0 | M53: 419077.37 | O53: 419077.37 | P53: 0 | Q53: 18637045 | R53: 18637045 | S53: 0
A54: 47 | D54: 142 | F54: 1420 | H54: Облігації внутрішньої державної позики, що рефінансуються Національним банком України, які обліковуються за амортизованою собівартістю | I54: А | J54: 771886 | K54: 771886 | L54: 0 | M54: 0 | O54: 0 | P54: 0 | Q54: 35012828 | R54: 35012828 | S54: 0
A55: 48 | F55: 1426 | H55: Неамортизована премія/дисконт за борговими цінними паперами, що рефінансуються Національним банком України, які обліковуються за амортизованою собівартістю | I55: А | J55: 6043.0315 | K55: 6043.0315 | L55: 0 | M55: 11171.942 | O55: 11171.942 | P55: 0 | Q55: 141160.22 | R55: 141160.22 | S55: 0
A56: 49 | I56: П | J56: 0 | K56: 0 | L56: 0 | M56: 0 | O56: 0 | P56: 0 | Q56: -43710.381 | R56: -43710.381 | S56: 0
A57: 50 | F57: 1428 | H57: Нараховані доходи за борговими цінними паперами, що рефінансуються Національним банком України, які обліковуються за амортизованою собівартістю | I57: А | J57: 414908.28 | K57: 414908.28 | L57: 0 | M57: 1218610.2 | O57: 1218610.2 | P57: 0 | Q57: 1113788.5 | R57: 1113788.5 | S57: 0
A58: 51 | F58: 1429 | H58: Резерв за борговими цінними паперами,що рефінансуються Національним банком України, які обліковуються за амортизованою собівартістю | I58: П | J58: 54542.325 | K58: 54542.325 | L58: 0 | M58: 38169.714 | O58: 38169.714 | P58: 0 | Q58: -1588674.1 | R58: -1588674.1 | S58: 0
A59: 52 | F59: Група 142 - Усього | J59: 1247379.6 | K59: 1247379.6 | L59: 0 | M59: 1267951.9 | O59: 1267951.9 | P59: 0 | Q59: 34635392 | R59: 34635392 | S59: 0
A60: 53 | D60: 143 | F60: 1430 | H60: Депозитні сертифікати Національного банку України, розміщені в банках України, що обліковуються за справедливою вартістю через інший сукупний дохід | I60: А | J60: 0 | K60: 0 | L60: 0 | M60: 0 | O60: 0 | P60: 0 | Q60: 0 | R60: 0 | S60: 0
A61: 54 | F61: 1435 | H61: Переоцінка депозитних сертифікатів Національного банку України, розміщених у банках України, що обліковуються за справедливою вартістю через інший сукупний дохід | I61: А | J61: 0 | K61: 0 | L61: 0 | M61: 0 | O61: 0 | P61: 0 | Q61: 0 | R61: 0 | S61: 0
A62: 55 | I62: П | J62: 0 | K62: 0 | L62: 0 | M62: 0 | O62: 0 | P62: 0 | Q62: 0 | R62: 0 | S62: 0
A63: 56 | F63: 1436 | H63: Неамортизована премія/дисконт за депозитними сертифікатами Національного банку України, розміщеними в банках України, що обліковуються за справедливою вартістю через інший сукупний дохід | I63: А | J63: 0 | K63: 0 | L63: 0 | M63: 0 | O63: 0 | P63: 0 | Q63: 0 | R63: 0 | S63: 0
A64: 57 | I64: П | J64: 0 | K64: 0 | L64: 0 | M64: 0 | O64: 0 | P64: 0 | Q64: 0 | R64: 0 | S64: 0
A65: 58 | F65: 1438 | H65: Нараховані доходи за депозитними сертифікатами Національного банку України, розміщеними в банках України, що обліковуються за справедливою вартістю через інший сукупний дохід | I65: А | J65: 0 | K65: 0 | L65: 0 | M65: 0 | O65: 0 | P65: 0 | Q65: 0 | R65: 0 | S65: 0
A66: 59 | F66: Група 143 - Усього | J66: 0 | K66: 0 | L66: 0 | M66: 0 | O66: 0 | P66: 0 | Q66: 0 | R66: 0 | S66: 0
A67: 60 | D67: 144 | F67: 1440 | H67: Депозитні сертифікати Національного банку України, розміщені в банках України, що обліковуються за амортизованою собівартістю | I67: А | J67: 676400000 | K67: 676400000 | L67: 0 | M67: 666400000 | O67: 666400000 | P67: 0 | Q67: 27500000 | R67: 27500000 | S67: 0
A68: 61 | F68: 1446 | H68: Неамортизована премія/дисконт за депозитними сертифікатами Національного банку України, розміщеними в банках України, що обліковуються за амортизованою собівартістю | I68: А | J68: 16.17489 | K68: 16.17489 | L68: 0 | M68: 17.79878 | O68: 17.79878 | P68: 0 | Q68: 0 | R68: 0 | S68: 0
A69: 62 | I69: П | J69: 0 | K69: 0 | L69: 0 | M69: 0 | O69: 0 | P69: 0 | Q69: -4.4657 | R69: -4.4657 | S69: 0
A70: 63 | F70: 1448 | H70: Нараховані доходи за депозитними сертифікатами Національного банку України, розміщеними в банках України, що обліковуються за амортизованою собівартістю | I70: А | J70: 362220.12 | K70: 362220.12 | L70: 0 | M70: 354000.94 | O70: 354000.94 | P70: 0 | Q70: 22602.74 | R70: 22602.74 | S70: 0
A71: 64 | F71: Група 144 - Усього | J71: 6.7676224e+08 | K71: 6.7676224e+08 | L71: 0 | M71: 6.6675402e+08 | O71: 6.6675402e+08 | P71: 0 | Q71: 27522598 | R71: 27522598 | S71: 0
A72: 65 | D72: Розділ 14 - Усього | J72: 6.9367531e+08 | K72: 6.9189994e+08 | L72: 1775365 | M72: 6.8518602e+08 | O72: 6.835157e+08 | P72: 1670313.1 | Q72: 90103464 | R72: 89877595 | S72: 225868.95
A73: 66 | C73: 15 | D73: 150 | F73: 1500 | H73: Кореспондентські рахунки, що відкриті в інших банках | I73: А | J73: 2.7697682e+08 | K73: 0 | L73: 2.7697682e+08 | M73: 2.825942e+08 | O73: 0 | P73: 2.825942e+08 | Q73: 22094922 | R73: 0 | S73: 22094922
A74: 67 | F74: 1508 | H74: Нараховані доходи за коштами на вимогу в інших банках | I74: А | J74: 0 | K74: 0 | L74: 0 | M74: 0 | O74: 0 | P74: 0 | Q74: 0 | R74: 0 | S74: 0
A75: 68 | F75: 1509 | H75: Резерв за коштами на вимогу в інших банках | I75: П | J75: 54178.521 | K75: 0 | L75: 54178.521 | M75: 50760.358 | O75: 0 | P75: 50760.358 | Q75: -50356.268 | R75: 0 | S75: -50356.268
A76: 69 | F76: Група 150 - Усього | J76: 2.77031e+08 | K76: 0 | L76: 2.77031e+08 | M76: 2.8264496e+08 | O76: 0 | P76: 2.8264496e+08 | Q76: 22044566 | R76: 0 | S76: 22044566
A77: 70 | D77: 151 | F77: 1510 | H77: Депозити овернайт, що розміщені в інших банках, які обліковуються за амортизованою собівартістю | I77: А | J77: 92148166 | K77: 0 | L77: 92148166 | M77: 91222690 | O77: 0 | P77: 91222690 | Q77: 5065149.8 | R77: 0 | S77: 5065149.8
A78: 71 | F78: 1513 | H78: Строкові вклади (депозити), що розміщені в інших банках, які обліковуються за амортизованою собівартістю | I78: А | J78: 94980719 | K78: 0 | L78: 94980719 | M78: 89267289 | O78: 0 | P78: 89267289 | Q78: 25250669 | R78: 0 | S78: 25250669
A79: 72 | F79: 1516 | H79: Неамортизована премія/дисконт за строковими вкладами (депозитами), що розміщені в інших банках, які обліковуються за амортизованою собівартістю | I79: А | J79: 4.12165 | K79: 0 | L79: 4.12165 | M79: 4.30492 | O79: 0 | P79: 4.30492 | Q79: 0.06223 | R79: 0 | S79: 0.06223
A80: 73 | I80: П | J80: 0 | K80: 0 | L80: 0 | M80: 0 | O80: 0 | P80: 0 | Q80: -0.98111 | R80: 0 | S80: -0.98111
A81: 74 | F81: 1518 | H81: Нараховані доходи за строковими вкладами (депозитами), що розміщені в інших банках, які обліковуються за амортизованою собівартістю | I81: А | J81: 58887.181 | K81: 0 | L81: 58887.181 | M81: 57126.212 | O81: 0 | P81: 57126.212 | Q81: 8567.7033 | R81: 0 | S81: 8567.7033
A82: 75 | F82: 1519 | H82: Резерв за строковими вкладами (депозитами), що розміщені в інших банках, які обліковуються за амортизованою собівартістю | I82: П | J82: 17403.116 | K82: 0 | L82: 17403.116 | M82: 19989.351 | O82: 0 | P82: 19989.351 | Q82: -19623.768 | R82: 0 | S82: -19623.768
A83: 76 | F83: Група 151 - Усього | J83: 1.8720518e+08 | K83: 0 | L83: 1.8720518e+08 | M83: 1.805671e+08 | O83: 0 | P83: 1.805671e+08 | Q83: 30304762 | R83: 0 | S83: 30304762
A84: 77 | D84: 152 | F84: 1521 | H84: Кредити овернайт, що надані іншим банкам,які обліковуються за амортизованою собівартістю | I84: А | J84: 0 | K84: 0 | L84: 0 | M84: 0 | O84: 0 | P84: 0 | Q84: 0 | R84: 0 | S84: 0
A85: 78 | F85: 1522 | H85: Кредити, що надані іншим банкам за операціями репо, які обліковуються за амортизованою собівартістю | I85: А | J85: 0 | K85: 0 | L85: 0 | M85: 0 | O85: 0 | P85: 0 | Q85: 0 | R85: 0 | S85: 0
A86: 79 | F86: 1524 | H86: Інші кредити, що надані іншим банкам, які обліковуються за амортизованою собівартістю | I86: А | J86: 0 | K86: 0 | L86: 0 | M86: 0 | O86: 0 | P86: 0 | Q86: 0 | R86: 0 | S86: 0
A87: 80 | F87: 1526 | H87: Неамортизована премія/дисконт за кредитами, що надані іншим банкам, які обліковуються за амортизованою собівартістю | I87: А | J87: 0 | K87: 0 | L87: 0 | M87: 0 | O87: 0 | P87: 0 | Q87: 0 | R87: 0 | S87: 0
A88: 81 | I88: П | J88: 0 | K88: 0 | L88: 0 | M88: 0 | O88: 0 | P88: 0 | Q88: 0 | R88: 0 | S88: 0
A89: 82 | F89: 1528 | H89: Нараховані доходи за кредитами, що надані іншим банкам, які обліковуються за амортизованою собівартістю | I89: А | J89: 0 | K89: 0 | L89: 0 | M89: 0 | O89: 0 | P89: 0 | Q89: 0 | R89: 0 | S89: 0
A90: 83 | F90: 1529 | H90: Резерв за кредитами, що надані іншим банкам, які обліковуються за амортизованою собівартістю | I90: П | J90: 0 | K90: 0 | L90: 0 | M90: 0 | O90: 0 | P90: 0 | Q90: 0 | R90: 0 | S90: 0
A91: 84 | F91: Група 152 - Усього | J91: 0 | K91: 0 | L91: 0 | M91: 0 | O91: 0 | P91: 0 | Q91: 0 | R91: 0 | S91: 0
A92: 85 | D92: Розділ 15 - Усього | J92: 4.6423618e+08 | K92: 0 | L92: 4.6423618e+08 | M92: 4.6321206e+08 | O92: 0 | P92: 4.6321206e+08 | Q92: 52349327 | R92: 0 | S92: 52349327
A93: 86 | C93: 16 | D93: 160 | F93: 1600 | H93: Кореспондентські рахунки інших банків | I93: А | J93: 1.6575307e+08 | K93: 1.1139781e+08 | L93: 54355261 | M93: 1.692006e+08 | O93: 1.1334771e+08 | P93: 55852887 | Q93: 0 | R93: 0 | S93: 0
A94: 87 | F94: Група 160 - Усього | J94: 1.6575307e+08 | K94: 1.1139781e+08 | L94: 54355261 | M94: 1.692006e+08 | O94: 1.1334771e+08 | P94: 55852887 | Q94: 0 | R94: 0 | S94: 0
A95: 88 | D95: Розділ 16 - Усього | J95: 1.6575307e+08 | K95: 1.1139781e+08 | L95: 54355261 | M95: 1.692006e+08 | O95: 1.1334771e+08 | P95: 55852887 | Q95: 0 | R95: 0 | S95: 0
A96: 89 | C96: 18 | D96: 181 | F96: 1811 | H96: Дебіторська заборгованість за операціями з готівкою | I96: А | J96: 2131859.2 | K96: 1473588.1 | L96: 658271.18 | M96: 2132309.2 | O96: 1474038.1 | P96: 658271.18 | Q96: 4000 | R96: 4000 | S96: 0
A97: 90 | F97: 1819 | H97: Інша дебіторська заборгованість за операціями з банками | I97: А | J97: 660260.53 | K97: 600086.62 | L97: 60173.91 | M97: 644937.78 | O97: 586076.5 | P97: 58861.282 | Q97: 62703.13 | R97: 14018.156 | S97: 48684.974
A98: 91 | F98: Група 181 - Усього | J98: 2792119.8 | K98: 2073674.7 | L98: 718445.09 | M98: 2777247 | O98: 2060114.5 | P98: 717132.46 | Q98: 66703.13 | R98: 18018.156 | S98: 48684.974
A99: 92 | D99: 183 | F99: 1832 | H99: Кошти банків у розрахунках | I99: А | J99: 215480.39 | K99: 0 | L99: 215480.39 | M99: 132022.2 | O99: 0 | P99: 132022.2 | Q99: 984649.7 | R99: 20 | S99: 984629.7
A100: 93 | F100: 1839 | H100: Резерви за коштами банків у розрахунках | I100: П | J100: 1042.8366 | K100: 0 | L100: 1042.8366 | M100: 1096.9657 | O100: 0 | P100: 1096.9657 | Q100: -1077.5612 | R100: 0 | S100: -1077.5612
...

Sheet   6АТ "Ощадбанк" 
A1: Зміст
B2: Оборотно-сальдовий баланс банку АТ "Ощадбанк" за станом на 01.03.2026
B3: (тис грн)
A4: Номер з/п | B4: Клас/ розділ/ група/ рахунок | I4: Актив/ пасив | J4: Обороти за місяць | Q4: Сальдо
J5: дебет | M5: кредит | Q5: усього | R5: НВ | S5: ІВ
B6: номер | F6: назва | J6: усього | K6: НВ | L6: ІВ | M6: усього | O6: НВ | P6: ІВ
A7: 1 | B7: 2 | F7: 3 | I7: 4 | J7: 5 | K7: 6 | L7: 7 | M7: 8 | O7: 9 | P7: 10 | Q7: 11 | R7: 12 | S7: 13
A8: 1 | B8: Балансові рахунки
A9: 2 | B9: Активи
A10: 3 | B10: Класи 1 - 4
A11: 4 | B11: Клас 1 | C11: 10 | D11: 100 | F11: 1001 | H11: Банкноти та монети в касі банку | I11: А | J11: 3.2940591e+08 | K11: 2.4121788e+08 | L11: 88188034 | M11: 3.2858763e+08 | O11: 2.4112026e+08 | P11: 87467365 | Q11: 13348535 | R11: 4567955.7 | S11: 8780579.2
A12: 5 | F12: 1002 | H12: Банкноти та монети в касі відділень банку | I12: А | J12: 28078075 | K12: 19342710 | L12: 8735365.4 | M12: 28234772 | O12: 19484727 | P12: 8750044.1 | Q12: 1501348.2 | R12: 936716.74 | S12: 564631.42
A13: 6 | F13: 1004 | H13: Банкноти та монети в банкоматах | I13: А | J13: 25813113 | K13: 25813113 | L13: 0 | M13: 26185548 | O13: 26185548 | P13: 0 | Q13: 3350937 | R13: 3350937 | S13: 0
A14: 7 | F14: 1005 | H14: Банкноти та монети, інкасовані до перерахування | I14: А | J14: 40976222 | K14: 40976222 | L14: 0 | M14: 40976222 | O14: 40976222 | P14: 0 | Q14: 0 | R14: 0 | S14: 0
A15: 8 | F15: 1006 | H15: Банкноти та монети на зберіганні в інкасаторській компанії | I15: А | J15: 0 | K15: 0 | L15: 0 | M15: 0 | O15: 0 | P15: 0 | Q15: 0 | R15: 0 | S15: 0
A16: 9 | F16: 1007 | H16: Банкноти та монети в дорозі | I16: А | J16: 1.312748e+08 | K16: 94542321 | L16: 36732483 | M16: 1.3130096e+08 | O16: 94553465 | P16: 36747492 | Q16: 124612.51 | R16: 87996.62 | S16: 36615.886
A17: 10 | F17: Група 100 - Усього | J17: 5.5554813e+08 | K17: 4.2189224e+08 | L17: 1.3365588e+08 | M17: 5.5528512e+08 | O17: 4.2232022e+08 | P17: 1.329649e+08 | Q17: 18325433 | R17: 8943606 | S17: 9381826.5
A18: 11 | D18: 101 | F18: 1011 | H18: Дорожні чеки в касі банку | I18: А | J18: 0 | K18: 0 | L18: 0 | M18: 0 | O18: 0 | P18: 0 | Q18: 0 | R18: 0 | S18: 0
A19: 12 | F19: 1012 | H19: Дорожні чеки в касі відділень банку | I19: А | J19: 0 | K19: 0 | L19: 0 | M19: 0 | O19: 0 | P19: 0 | Q19: 0 | R19: 0 | S19: 0
A20: 13 | F20: Група 101 - Усього | J20: 0 | K20: 0 | L20: 0 | M20: 0 | O20: 0 | P20: 0 | Q20: 0 | R20: 0 | S20: 0
A21: 14 | D21: 109 | F21: 1090 | H21: Резерви за готівковими коштами, наявність яких є непідтвердженою | I21: П | J21: 248.44174 | K21: 0 | L21: 248.44174 | M21: 399.74697 | O21: 0 | P21: 399.74697 | Q21: -95568.364 | R21: -73346.687 | S21: -22221.676
A22: 15 | F22: Група 109 - Усього | J22: 248.44174 | K22: 0 | L22: 248.44174 | M22: 399.74697 | O22: 0 | P22: 399.74697 | Q22: -95568.364 | R22: -73346.687 | S22: -22221.676
A23: 16 | D23: Розділ 10 - Усього | J23: 5.5554837e+08 | K23: 4.2189224e+08 | L23: 1.3365613e+08 | M23: 5.5528552e+08 | O23: 4.2232022e+08 | P23: 1.329653e+08 | Q23: 18229864 | R23: 8870259.3 | S23: 9359604.8
A24: 17 | C24: 11 | D24: 110 | F24: 1101 | H24: Банківські метали в банку | I24: А | J24: 1344160.1 | K24: 0 | L24: 1344160.1 | M24: 1367621.5 | O24: 0 | P24: 1367621.5 | Q24: 72233.49 | R24: 0 | S24: 72233.49
A25: 18 | F25: 1102 | H25: Банківські метали у відділенні банку | I25: А | J25: 14442.208 | K25: 0 | L25: 14442.208 | M25: 18122.768 | O25: 0 | P25: 18122.768 | Q25: 25530.823 | R25: 0 | S25: 25530.823
A26: 19 | F26: 1107 | H26: Банківські метали в дорозі | I26: А | J26: 20398.936 | K26: 0 | L26: 20398.936 | M26: 20403.005 | O26: 0 | P26: 20403.005 | Q26: 0 | R26: 0 | S26: 0
A27: 20 | F27: Група 110 - Усього | J27: 1379001.3 | K27: 0 | L27: 1379001.3 | M27: 1406147.3 | O27: 0 | P27: 1406147.3 | Q27: 97764.313 | R27: 0 | S27: 97764.313
A28: 21 | D28: 119 | F28: 1190 | H28: Резерви за банківськими металами, наявність яких є непідтвердженою | I28: П | J28: 764.16045 | K28: 0 | L28: 764.16045 | M28: 459.96969 | O28: 0 | P28: 459.96969 | Q28: -2081.7807 | R28: 0 | S28: -2081.7807
A29: 22 | F29: Група 119 - Усього | J29: 764.16045 | K29: 0 | L29: 764.16045 | M29: 459.96969 | O29: 0 | P29: 459.96969 | Q29: -2081.7807 | R29: 0 | S29: -2081.7807
A30: 23 | D30: Розділ 11 - Усього | J30: 1379765.4 | K30: 0 | L30: 1379765.4 | M30: 1406607.2 | O30: 0 | P30: 1406607.2 | Q30: 95682.533 | R30: 0 | S30: 95682.533
A31: 24 | C31: 12 | D31: 120 | F31: 1200 | H31: Кореспондентський рахунок банку в Національному банку України | I31: А | J31: 1.4126544e+09 | K31: 1.4126544e+09 | L31: 0 | M31: 1.4078833e+09 | O31: 1.4078833e+09 | P31: 0 | Q31: 35005070 | R31: 35005070 | S31: 0
A32: 25 | F32: 1202 | H32: Кошти банків за рахунками умовного зберігання (ескроу) у Національному банку України | I32: А | J32: 5604.5031 | K32: 0 | L32: 5604.5031 | M32: 3004.9153 | O32: 0 | P32: 3004.9153 | Q32: 320829.45 | R32: 8647 | S32: 312182.45
A33: 26 | F33: 1205 | H33: Кошти банків для забезпечення виконання зобов’язань перед Національним банком України за кредитами, наданими банкам, та операціями своп процентної ставки | I33: А | J33: 0 | K33: 0 | L33: 0 | M33: 0 | O33: 0 | P33: 0 | Q33: 0 | R33: 0 | S33: 0
A34: 27 | F34: 1208 | H34: Нараховані доходи за коштами на вимогу в Національному банку України | I34: А | J34: 668.44388 | K34: 0 | L34: 668.44388 | M34: 668.44388 | O34: 0 | P34: 668.44388 | Q34: 0 | R34: 0 | S34: 0
A35: 28 | F35: Група 120 - Усього | J35: 1.4126607e+09 | K35: 1.4126544e+09 | L35: 6272.947 | M35: 1.407887e+09 | O35: 1.4078833e+09 | P35: 3673.3592 | Q35: 35325899 | R35: 35013717 | S35: 312182.45
A36: 29 | D36: Розділ 12 - Усього | J36: 1.4126607e+09 | K36: 1.4126544e+09 | L36: 6272.947 | M36: 1.407887e+09 | O36: 1.4078833e+09 | P36: 3673.3592 | Q36: 35325899 | R36: 35013717 | S36: 312182.45
A37: 30 | C37: 14 | D37: 140 | F37: 1400 | H37: Облігації внутрішньої державної позики, що рефінансуються Національним банком України, які обліковуються за справедливою вартістю через прибутки/збитки | I37: А | J37: 136125.11 | K37: 115432 | L37: 20693.113 | M37: 160322.98 | O37: 151441 | P37: 8881.9818 | Q37: 9483961.9 | R37: 9305662 | S37: 178299.93
A38: 31 | F38: 1405 | H38: Переоцінка боргових цінних паперів, що рефінансуються Національним банком України, які обліковуються за справедливою вартістю через прибутки/збитки | I38: А | J38: 19838922 | K38: 19817776 | L38: 21145.536 | M38: 19633143 | O38: 19612606 | P38: 20536.424 | Q38: 6574794.9 | R38: 6573515.7 | S38: 1279.2501
A39: 32 | I39: П | J39: 0 | K39: 0 | L39: 0 | M39: 0 | O39: 0 | P39: 0 | Q39: -863801.83 | R39: -863801.83 | S39: 0
A40: 33 | F40: 1406 | H40: Неамортизована премія/дисконт за борговими цінними паперами, що рефінансуються Національним банком України, які обліковуються за справедливою вартістю через прибутки/збитки | I40: А | J40: 21421.294 | K40: 21377.283 | L40: 44.01095 | M40: 195.46714 | O40: 184.94964 | P40: 10.5175 | Q40: 323.43646 | R40: 290.8407 | S40: 32.59576
A41: 34 | I41: П | J41: 0 | K41: 0 | L41: 0 | M41: 0 | O41: 0 | P41: 0 | Q41: -1112977.9 | R41: -1112965.8 | S41: -12.17985
A42: 35 | F42: 1408 | H42: Нараховані доходи за борговими цінними паперами, що рефінансуються Національним банком України, які обліковуються за справедливою вартістю через прибутки/збитки | I42: А | J42: 50099.418 | K42: 49539.195 | L42: 560.22344 | M42: 149100.38 | O42: 147509.58 | P42: 1590.8073 | Q42: 39304.361 | R42: 38560.277 | S42: 744.08398
A43: 36 | F43: Група 140 - Усього | J43: 20046568 | K43: 20004125 | L43: 42442.883 | M43: 19942761 | O43: 19911742 | P43: 31019.73 | Q43: 14121605 | R43: 13941261 | S43: 180343.68
A44: 37 | D44: 141 | F44: 1410 | H44: Облігації внутрішньої державної позики, що рефінансуються Національним банком України, які обліковуються за справедливою вартістю через інший сукупний дохід | I44: А | J44: 0 | K44: 0 | L44: 0 | M44: 0 | O44: 0 | P44: 0 | Q44: 0 | R44: 0 | S44: 0
A45: 38 | F45: 1411 | H45: Облігації зовнішньої державної позики, що рефінансуються Національним банком України, які обліковуються за справедливою вартістю через інший сукупний дохід | I45: А | J45: 0 | K45: 0 | L45: 0 | M45: 0 | O45: 0 | P45: 0 | Q45: 0 | R45: 0 | S45: 0
A46: 39 | F46: 1412 | H46: Боргові цінні папери органів державної влади та місцевого самоврядування, що рефінансуються Національним банком України, які обліковуються за справедливою вартістю через інший сукупний дохід | I46: А | J46: 0 | K46: 0 | L46: 0 | M46: 0 | O46: 0 | P46: 0 | Q46: 0 | R46: 0 | S46: 0
A47: 40 | F47: 1415 | H47: Переоцінка боргових цінних паперів, що рефінансуються Національним банком України, які обліковуються за справедливою вартістю через інший сукупний дохід | I47: А | J47: 0 | K47: 0 | L47: 0 | M47: 0 | O47: 0 | P47: 0 | Q47: 0 | R47: 0 | S47: 0
A48: 41 | I48: П | J48: 0 | K48: 0 | L48: 0 | M48: 0 | O48: 0 | P48: 0 | Q48: 0 | R48: 0 | S48: 0
A49: 42 | F49: 1416 | H49: Неамортизована премія/дисконт за борговими цінними паперами, що рефінансуються Національним банком України, які обліковуються за справедливою вартістю через інший сукупний дохід | I49: А | J49: 0 | K49: 0 | L49: 0 | M49: 0 | O49: 0 | P49: 0 | Q49: 0 | R49: 0 | S49: 0
A50: 43 | I50: П | J50: 0 | K50: 0 | L50: 0 | M50: 0 | O50: 0 | P50: 0 | Q50: 0 | R50: 0 | S50: 0
A51: 44 | F51: 1418 | H51: Нараховані доходи за борговими цінними паперами, що рефінансуються Національним банком України, які обліковуються за справедливою вартістю через інший сукупний дохід | I51: А | J51: 0 | K51: 0 | L51: 0 | M51: 0 | O51: 0 | P51: 0 | Q51: 0 | R51: 0 | S51: 0
A52: 45 | F52: 1419 | H52: Резерв за борговими цінними паперами,що рефінансуються Національним банком України, які обліковуються за справедливою вартістю через інший сукупний дохід | I52: П | J52: 0 | K52: 0 | L52: 0 | M52: 0 | O52: 0 | P52: 0 | Q52: 0 | R52: 0 | S52: 0
A53: 46 | F53: Група 141 - Усього | J53: 0 | K53: 0 | L53: 0 | M53: 0 | O53: 0 | P53: 0 | Q53: 0 | R53: 0 | S53: 0
A54: 47 | D54: 142 | F54: 1420 | H54: Облігації внутрішньої державної позики, що рефінансуються Національним банком України, які обліковуються за амортизованою собівартістю | I54: А | J54: 8928857.9 | K54: 8427066 | L54: 501791.92 | M54: 13178668 | O54: 11977597 | P54: 1201071.5 | Q54: 1.7359255e+08 | R54: 160799529 | S54: 12793020
A55: 48 | F55: 1426 | H55: Неамортизована премія/дисконт за борговими цінними паперами, що рефінансуються Національним банком України, які обліковуються за амортизованою собівартістю | I55: А | J55: 140846.26 | K55: 135739.91 | L55: 5106.3488 | M55: 15271.564 | O55: 14909.964 | P55: 361.6002 | Q55: 242081.13 | R55: 241951.56 | S55: 129.5677
A56: 49 | I56: П | J56: 0 | K56: 0 | L56: 0 | M56: 0 | O56: 0 | P56: 0 | Q56: -270529.66 | R56: -257909.54 | S56: -12620.119
A57: 50 | F57: 1428 | H57: Нараховані доходи за борговими цінними паперами, що рефінансуються Національним банком України, які обліковуються за амортизованою собівартістю | I57: А | J57: 2672334.4 | K57: 2630122.7 | L57: 42211.62 | M57: 3091410.6 | O57: 3013839.5 | P57: 77571.101 | Q57: 7224989 | R57: 7123088.9 | S57: 101900.1
A58: 51 | F58: 1429 | H58: Резерв за борговими цінними паперами,що рефінансуються Національним банком України, які обліковуються за амортизованою собівартістю | I58: П | J58: 734918.24 | K58: 656496.52 | L58: 78421.72 | M58: 799911.09 | O58: 716748.73 | P58: 83162.366 | Q58: -2345814.4 | R58: -2017693.8 | S58: -328120.56
A59: 52 | F59: Група 142 - Усього | J59: 12476957 | K59: 11849425 | L59: 627531.61 | M59: 17085262 | O59: 15723095 | P59: 1362166.5 | Q59: 1.7844327e+08 | R59: 1.6588897e+08 | S59: 12554309
A60: 53 | D60: 143 | F60: 1430 | H60: Депозитні сертифікати Національного банку України, розміщені в банках України, що обліковуються за справедливою вартістю через інший сукупний дохід | I60: А | J60: 0 | K60: 0 | L60: 0 | M60: 0 | O60: 0 | P60: 0 | Q60: 0 | R60: 0 | S60: 0
A61: 54 | F61: 1435 | H61: Переоцінка депозитних сертифікатів Національного банку України, розміщених у банках України, що обліковуються за справедливою вартістю через інший сукупний дохід | I61: А | J61: 0 | K61: 0 | L61: 0 | M61: 0 | O61: 0 | P61: 0 | Q61: 0 | R61: 0 | S61: 0
A62: 55 | I62: П | J62: 0 | K62: 0 | L62: 0 | M62: 0 | O62: 0 | P62: 0 | Q62: 0 | R62: 0 | S62: 0
A63: 56 | F63: 1436 | H63: Неамортизована премія/дисконт за депозитними сертифікатами Національного банку України, розміщеними в банках України, що обліковуються за справедливою вартістю через інший сукупний дохід | I63: А | J63: 0 | K63: 0 | L63: 0 | M63: 0 | O63: 0 | P63: 0 | Q63: 0 | R63: 0 | S63: 0
A64: 57 | I64: П | J64: 0 | K64: 0 | L64: 0 | M64: 0 | O64: 0 | P64: 0 | Q64: 0 | R64: 0 | S64: 0
A65: 58 | F65: 1438 | H65: Нараховані доходи за депозитними сертифікатами Національного банку України, розміщеними в банках України, що обліковуються за справедливою вартістю через інший сукупний дохід | I65: А | J65: 0 | K65: 0 | L65: 0 | M65: 0 | O65: 0 | P65: 0 | Q65: 0 | R65: 0 | S65: 0
A66: 59 | F66: Група 143 - Усього | J66: 0 | K66: 0 | L66: 0 | M66: 0 | O66: 0 | P66: 0 | Q66: 0 | R66: 0 | S66: 0
A67: 60 | D67: 144 | F67: 1440 | H67: Депозитні сертифікати Національного банку України, розміщені в банках України, що обліковуються за амортизованою собівартістю | I67: А | J67: 884700000 | K67: 884700000 | L67: 0 | M67: 874800000 | O67: 874800000 | P67: 0 | Q67: 61700000 | R67: 61700000 | S67: 0
A68: 61 | F68: 1446 | H68: Неамортизована премія/дисконт за депозитними сертифікатами Національного банку України, розміщеними в банках України, що обліковуються за амортизованою собівартістю | I68: А | J68: 0 | K68: 0 | L68: 0 | M68: 0 | O68: 0 | P68: 0 | Q68: 0 | R68: 0 | S68: 0
A69: 62 | I69: П | J69: 0 | K69: 0 | L69: 0 | M69: 0 | O69: 0 | P69: 0 | Q69: 0 | R69: 0 | S69: 0
A70: 63 | F70: 1448 | H70: Нараховані доходи за депозитними сертифікатами Національного банку України, розміщеними в банках України, що обліковуються за амортизованою собівартістю | I70: А | J70: 844945.13 | K70: 844945.13 | L70: 0 | M70: 627080.79 | O70: 627080.79 | P70: 0 | Q70: 559710.93 | R70: 559710.93 | S70: 0
A71: 64 | F71: Група 144 - Усього | J71: 8.8554495e+08 | K71: 8.8554495e+08 | L71: 0 | M71: 8.7542708e+08 | O71: 8.7542708e+08 | P71: 0 | Q71: 62259711 | R71: 62259711 | S71: 0
A72: 65 | D72: Розділ 14 - Усього | J72: 9.1806847e+08 | K72: 9.173985e+08 | L72: 669974.49 | M72: 9.124551e+08 | O72: 9.1106192e+08 | P72: 1393186.3 | Q72: 2.5482459e+08 | R72: 2.4208994e+08 | S72: 12734652
A73: 66 | C73: 15 | D73: 150 | F73: 1500 | H73: Кореспондентські рахунки, що відкриті в інших банках | I73: А | J73: 3.9388891e+08 | K73: 11447286 | L73: 3.8244162e+08 | M73: 4.1100047e+08 | O73: 11447297 | P73: 3.9955318e+08 | Q73: 17214557 | R73: 400055.67 | S73: 16814501
A74: 67 | F74: 1508 | H74: Нараховані доходи за коштами на вимогу в інших банках | I74: А | J74: 40943.542 | K74: 0 | L74: 40943.542 | M74: 49486.806 | O74: 0 | P74: 49486.806 | Q74: 3765.327 | R74: 0 | S74: 3765.327
A75: 68 | F75: 1509 | H75: Резерв за коштами на вимогу в інших банках | I75: П | J75: 32.07449 | K75: 0.002 | L75: 32.07249 | M75: 4.06751 | O75: 0 | P75: 4.06751 | Q75: -155.33783 | R75: -74.83264 | S75: -80.50519
A76: 69 | F76: Група 150 - Усього | J76: 3.9392989e+08 | K76: 11447286 | L76: 3.824826e+08 | M76: 4.1104996e+08 | O76: 11447297 | P76: 3.9960267e+08 | Q76: 17218167 | R76: 399980.84 | S76: 16818186
A77: 70 | D77: 151 | F77: 1510 | H77: Депозити овернайт, що розміщені в інших банках, які обліковуються за амортизованою собівартістю | I77: А | J77: 0 | K77: 0 | L77: 0 | M77: 0 | O77: 0 | P77: 0 | Q77: 0 | R77: 0 | S77: 0
A78: 71 | F78: 1513 | H78: Строкові вклади (депозити), що розміщені в інших банках, які обліковуються за амортизованою собівартістю | I78: А | J78: 0 | K78: 0 | L78: 0 | M78: 0 | O78: 0 | P78: 0 | Q78: 0 | R78: 0 | S78: 0
A79: 72 | F79: 1516 | H79: Неамортизована премія/дисконт за строковими вкладами (депозитами), що розміщені в інших банках, які обліковуються за амортизованою собівартістю | I79: А | J79: 0 | K79: 0 | L79: 0 | M79: 0 | O79: 0 | P79: 0 | Q79: 0 | R79: 0 | S79: 0
A80: 73 | I80: П | J80: 0 | K80: 0 | L80: 0 | M80: 0 | O80: 0 | P80: 0 | Q80: 0 | R80: 0 | S80: 0
A81: 74 | F81: 1518 | H81: Нараховані доходи за строковими вкладами (депозитами), що розміщені в інших банках, які обліковуються за амортизованою собівартістю | I81: А | J81: 0 | K81: 0 | L81: 0 | M81: 0 | O81: 0 | P81: 0 | Q81: 0 | R81: 0 | S81: 0
A82: 75 | F82: 1519 | H82: Резерв за строковими вкладами (депозитами), що розміщені в інших банках, які обліковуються за амортизованою собівартістю | I82: П | J82: 0 | K82: 0 | L82: 0 | M82: 0 | O82: 0 | P82: 0 | Q82: 0 | R82: 0 | S82: 0
A83: 76 | F83: Група 151 - Усього | J83: 0 | K83: 0 | L83: 0 | M83: 0 | O83: 0 | P83: 0 | Q83: 0 | R83: 0 | S83: 0
A84: 77 | D84: 152 | F84: 1521 | H84: Кредити овернайт, що надані іншим банкам,які обліковуються за амортизованою собівартістю | I84: А | J84: 2.5682168e+08 | K84: 0 | L84: 2.5682168e+08 | M84: 2.4384108e+08 | O84: 0 | P84: 2.4384108e+08 | Q84: 12980607 | R84: 0 | S84: 12980607
A85: 78 | F85: 1522 | H85: Кредити, що надані іншим банкам за операціями репо, які обліковуються за амортизованою собівартістю | I85: А | J85: 0 | K85: 0 | L85: 0 | M85: 0 | O85: 0 | P85: 0 | Q85: 0 | R85: 0 | S85: 0
A86: 79 | F86: 1524 | H86: Інші кредити, що надані іншим банкам, які обліковуються за амортизованою собівартістю | I86: А | J86: 0 | K86: 0 | L86: 0 | M86: 0 | O86: 0 | P86: 0 | Q86: 0 | R86: 0 | S86: 0
A87: 80 | F87: 1526 | H87: Неамортизована премія/дисконт за кредитами, що надані іншим банкам, які обліковуються за амортизованою собівартістю | I87: А | J87: 0 | K87: 0 | L87: 0 | M87: 0 | O87: 0 | P87: 0 | Q87: 0 | R87: 0 | S87: 0
A88: 81 | I88: П | J88: 0 | K88: 0 | L88: 0 | M88: 0 | O88: 0 | P88: 0 | Q88: 0 | R88: 0 | S88: 0
A89: 82 | F89: 1528 | H89: Нараховані доходи за кредитами, що надані іншим банкам, які обліковуються за амортизованою собівартістю | I89: А | J89: 17655.952 | K89: 0 | L89: 17655.952 | M89: 16345.872 | O89: 0 | P89: 16345.872 | Q89: 1310.08 | R89: 0 | S89: 1310.08
A90: 83 | F90: 1529 | H90: Резерв за кредитами, що надані іншим банкам, які обліковуються за амортизованою собівартістю | I90: П | J90: 0 | K90: 0 | L90: 0 | M90: 0 | O90: 0 | P90: 0 | Q90: 0 | R90: 0 | S90: 0
A91: 84 | F91: Група 152 - Усього | J91: 2.5683934e+08 | K91: 0 | L91: 2.5683934e+08 | M91: 2.4385742e+08 | O91: 0 | P91: 2.4385742e+08 | Q91: 12981917 | R91: 0 | S91: 12981917
A92: 85 | D92: Розділ 15 - Усього | J92: 6.5076923e+08 | K92: 11447286 | L92: 6.3932194e+08 | M92: 6.5490739e+08 | O92: 11447297 | P92: 6.4346009e+08 | Q92: 30200084 | R92: 399980.84 | S92: 29800103
A93: 86 | C93: 16 | D93: 160 | F93: 1600 | H93: Кореспондентські рахунки інших банків | I93: А | J93: 1908072.3 | K93: 67.31791 | L93: 1908005 | M93: 1670924.8 | O93: 62.92194 | P93: 1670861.9 | Q93: 0 | R93: 0 | S93: 0
A94: 87 | F94: Група 160 - Усього | J94: 1908072.3 | K94: 67.31791 | L94: 1908005 | M94: 1670924.8 | O94: 62.92194 | P94: 1670861.9 | Q94: 0 | R94: 0 | S94: 0
A95: 88 | D95: Розділ 16 - Усього | J95: 1908072.3 | K95: 67.31791 | L95: 1908005 | M95: 1670924.8 | O95: 62.92194 | P95: 1670861.9 | Q95: 0 | R95: 0 | S95: 0
A96: 89 | C96: 18 | D96: 181 | F96: 1811 | H96: Дебіторська заборгованість за операціями з готівкою | I96: А | J96: 71328075 | K96: 50800980 | L96: 20527095 | M96: 71328075 | O96: 50800980 | P96: 20527095 | Q96: 0 | R96: 0 | S96: 0
A97: 90 | F97: 1819 | H97: Інша дебіторська заборгованість за операціями з банками | I97: А | J97: 1.1612533e+08 | K97: 10285201 | L97: 1.0584012e+08 | M97: 1.1612533e+08 | O97: 10285201 | P97: 1.0584012e+08 | Q97: 0 | R97: 0 | S97: 0
A98: 91 | F98: Група 181 - Усього | J98: 1.874534e+08 | K98: 61086181 | L98: 1.2636722e+08 | M98: 1.874534e+08 | O98: 61086181 | P98: 1.2636722e+08 | Q98: 0 | R98: 0 | S98: 0
A99: 92 | D99: 183 | F99: 1832 | H99: Кошти банків у розрахунках | I99: А | J99: 0 | K99: 0 | L99: 0 | M99: 0 | O99: 0 | P99: 0 | Q99: 100 | R99: 100 | S99: 0
A100: 93 | F100: 1839 | H100: Резерви за коштами банків у розрахунках | I100: П | J100: 0 | K100: 0 | L100: 0 | M100: 0 | O100: 0 | P100: 0 | Q100: 0 | R100: 0 | S100: 0
...

Sheet 381АТ "МОТОР-БАНК"нпб
A1: Зміст
B2: Оборотно-сальдовий баланс банку АТ "МОТОР-БАНК" за станом на 01.03.2026
B3: (тис грн)
A4: Номер з/п | B4: Клас/ розділ/ група/ рахунок | I4: Актив/ пасив | J4: Обороти за місяць | Q4: Сальдо
J5: дебет | M5: кредит | Q5: усього | R5: НВ | S5: ІВ
B6: номер | F6: назва | J6: усього | K6: НВ | L6: ІВ | M6: усього | O6: НВ | P6: ІВ
A7: 1 | B7: 2 | F7: 3 | I7: 4 | J7: 5 | K7: 6 | L7: 7 | M7: 8 | O7: 9 | P7: 10 | Q7: 11 | R7: 12 | S7: 13
A8: 1 | B8: Балансові рахунки
A9: 2 | B9: Активи
A10: 3 | B10: Класи 1 - 4
A11: 4 | B11: Клас 1 | C11: 10 | D11: 100 | F11: 1001 | H11: Банкноти та монети в касі банку | I11: А | J11: 0 | K11: 0 | L11: 0 | M11: 0 | O11: 0 | P11: 0 | Q11: 0 | R11: 0 | S11: 0
A12: 5 | F12: 1002 | H12: Банкноти та монети в касі відділень банку | I12: А | J12: 125455.89 | K12: 81460.106 | L12: 43995.781 | M12: 144808.97 | O12: 100864.57 | P12: 43944.402 | Q12: 13148.155 | R12: 4251.542 | S12: 8896.613
A13: 6 | F13: 1004 | H13: Банкноти та монети в банкоматах | I13: А | J13: 5940 | K13: 5940 | L13: 0 | M13: 10685 | O13: 10685 | P13: 0 | Q13: 0 | R13: 0 | S13: 0
A14: 7 | F14: 1005 | H14: Банкноти та монети, інкасовані до перерахування | I14: А | J14: 0 | K14: 0 | L14: 0 | M14: 0 | O14: 0 | P14: 0 | Q14: 0 | R14: 0 | S14: 0
A15: 8 | F15: 1006 | H15: Банкноти та монети на зберіганні в інкасаторській компанії | I15: А | J15: 0 | K15: 0 | L15: 0 | M15: 0 | O15: 0 | P15: 0 | Q15: 0 | R15: 0 | S15: 0
A16: 9 | F16: 1007 | H16: Банкноти та монети в дорозі | I16: А | J16: 17380 | K16: 17380 | L16: 0 | M16: 17380 | O16: 17380 | P16: 0 | Q16: 0 | R16: 0 | S16: 0
A17: 10 | F17: Група 100 - Усього | J17: 148775.89 | K17: 104780.11 | L17: 43995.781 | M17: 172873.97 | O17: 128929.57 | P17: 43944.402 | Q17: 13148.155 | R17: 4251.542 | S17: 8896.613
A18: 11 | D18: 101 | F18: 1011 | H18: Дорожні чеки в касі банку | I18: А | J18: 0 | K18: 0 | L18: 0 | M18: 0 | O18: 0 | P18: 0 | Q18: 0 | R18: 0 | S18: 0
A19: 12 | F19: 1012 | H19: Дорожні чеки в касі відділень банку | I19: А | J19: 0 | K19: 0 | L19: 0 | M19: 0 | O19: 0 | P19: 0 | Q19: 0 | R19: 0 | S19: 0
A20: 13 | F20: Група 101 - Усього | J20: 0 | K20: 0 | L20: 0 | M20: 0 | O20: 0 | P20: 0 | Q20: 0 | R20: 0 | S20: 0
A21: 14 | D21: 109 | F21: 1090 | H21: Резерви за готівковими коштами, наявність яких є непідтвердженою | I21: П | J21: 0 | K21: 0 | L21: 0 | M21: 0 | O21: 0 | P21: 0 | Q21: 0 | R21: 0 | S21: 0
A22: 15 | F22: Група 109 - Усього | J22: 0 | K22: 0 | L22: 0 | M22: 0 | O22: 0 | P22: 0 | Q22: 0 | R22: 0 | S22: 0
A23: 16 | D23: Розділ 10 - Усього | J23: 148775.89 | K23: 104780.11 | L23: 43995.781 | M23: 172873.97 | O23: 128929.57 | P23: 43944.402 | Q23: 13148.155 | R23: 4251.542 | S23: 8896.613
A24: 17 | C24: 11 | D24: 110 | F24: 1101 | H24: Банківські метали в банку | I24: А | J24: 0 | K24: 0 | L24: 0 | M24: 0 | O24: 0 | P24: 0 | Q24: 0 | R24: 0 | S24: 0
A25: 18 | F25: 1102 | H25: Банківські метали у відділенні банку | I25: А | J25: 57.73313 | K25: 0 | L25: 57.73313 | M25: 80.07966 | O25: 0 | P25: 80.07966 | Q25: 376.10419 | R25: 0 | S25: 376.10419
A26: 19 | F26: 1107 | H26: Банківські метали в дорозі | I26: А | J26: 0 | K26: 0 | L26: 0 | M26: 0 | O26: 0 | P26: 0 | Q26: 0 | R26: 0 | S26: 0
A27: 20 | F27: Група 110 - Усього | J27: 57.73313 | K27: 0 | L27: 57.73313 | M27: 80.07966 | O27: 0 | P27: 80.07966 | Q27: 376.10419 | R27: 0 | S27: 376.10419
A28: 21 | D28: 119 | F28: 1190 | H28: Резерви за банківськими металами, наявність яких є непідтвердженою | I28: П | J28: 0 | K28: 0 | L28: 0 | M28: 0 | O28: 0 | P28: 0 | Q28: 0 | R28: 0 | S28: 0
A29: 22 | F29: Група 119 - Усього | J29: 0 | K29: 0 | L29: 0 | M29: 0 | O29: 0 | P29: 0 | Q29: 0 | R29: 0 | S29: 0
A30: 23 | D30: Розділ 11 - Усього | J30: 57.73313 | K30: 0 | L30: 57.73313 | M30: 80.07966 | O30: 0 | P30: 80.07966 | Q30: 376.10419 | R30: 0 | S30: 376.10419
A31: 24 | C31: 12 | D31: 120 | F31: 1200 | H31: Кореспондентський рахунок банку в Національному банку України | I31: А | J31: 3270062 | K31: 3270062 | L31: 0 | M31: 3061660 | O31: 3061660 | P31: 0 | Q31: 227747.51 | R31: 227747.51 | S31: 0
A32: 25 | F32: 1202 | H32: Кошти банків за рахунками умовного зберігання (ескроу) у Національному банку України | I32: А | J32: 0 | K32: 0 | L32: 0 | M32: 0 | O32: 0 | P32: 0 | Q32: 0 | R32: 0 | S32: 0
A33: 26 | F33: 1205 | H33: Кошти банків для забезпечення виконання зобов’язань перед Національним банком України за кредитами, наданими банкам, та операціями своп процентної ставки | I33: А | J33: 0 | K33: 0 | L33: 0 | M33: 0 | O33: 0 | P33: 0 | Q33: 0 | R33: 0 | S33: 0
A34: 27 | F34: 1208 | H34: Нараховані доходи за коштами на вимогу в Національному банку України | I34: А | J34: 0 | K34: 0 | L34: 0 | M34: 0 | O34: 0 | P34: 0 | Q34: 0 | R34: 0 | S34: 0
A35: 28 | F35: Група 120 - Усього | J35: 3270062 | K35: 3270062 | L35: 0 | M35: 3061660 | O35: 3061660 | P35: 0 | Q35: 227747.51 | R35: 227747.51 | S35: 0
A36: 29 | D36: Розділ 12 - Усього | J36: 3270062 | K36: 3270062 | L36: 0 | M36: 3061660 | O36: 3061660 | P36: 0 | Q36: 227747.51 | R36: 227747.51 | S36: 0
A37: 30 | C37: 14 | D37: 140 | F37: 1400 | H37: Облігації внутрішньої державної позики, що рефінансуються Національним банком України, які обліковуються за справедливою вартістю через прибутки/збитки | I37: А | J37: 0 | K37: 0 | L37: 0 | M37: 0 | O37: 0 | P37: 0 | Q37: 0 | R37: 0 | S37: 0
A38: 31 | F38: 1405 | H38: Переоцінка боргових цінних паперів, що рефінансуються Національним банком України, які обліковуються за справедливою вартістю через прибутки/збитки | I38: А | J38: 0 | K38: 0 | L38: 0 | M38: 0 | O38: 0 | P38: 0 | Q38: 0 | R38: 0 | S38: 0
A39: 32 | I39: П | J39: 0 | K39: 0 | L39: 0 | M39: 0 | O39: 0 | P39: 0 | Q39: 0 | R39: 0 | S39: 0
A40: 33 | F40: 1406 | H40: Неамортизована премія/дисконт за борговими цінними паперами, що рефінансуються Національним банком України, які обліковуються за справедливою вартістю через прибутки/збитки | I40: А | J40: 0 | K40: 0 | L40: 0 | M40: 0 | O40: 0 | P40: 0 | Q40: 0 | R40: 0 | S40: 0
A41: 34 | I41: П | J41: 0 | K41: 0 | L41: 0 | M41: 0 | O41: 0 | P41: 0 | Q41: 0 | R41: 0 | S41: 0
A42: 35 | F42: 1408 | H42: Нараховані доходи за борговими цінними паперами, що рефінансуються Національним банком України, які обліковуються за справедливою вартістю через прибутки/збитки | I42: А | J42: 0 | K42: 0 | L42: 0 | M42: 0 | O42: 0 | P42: 0 | Q42: 0 | R42: 0 | S42: 0
A43: 36 | F43: Група 140 - Усього | J43: 0 | K43: 0 | L43: 0 | M43: 0 | O43: 0 | P43: 0 | Q43: 0 | R43: 0 | S43: 0
A44: 37 | D44: 141 | F44: 1410 | H44: Облігації внутрішньої державної позики, що рефінансуються Національним банком України, які обліковуються за справедливою вартістю через інший сукупний дохід | I44: А | J44: 0 | K44: 0 | L44: 0 | M44: 0 | O44: 0 | P44: 0 | Q44: 0 | R44: 0 | S44: 0
A45: 38 | F45: 1411 | H45: Облігації зовнішньої державної позики, що рефінансуються Національним банком України, які обліковуються за справедливою вартістю через інший сукупний дохід | I45: А | J45: 0 | K45: 0 | L45: 0 | M45: 0 | O45: 0 | P45: 0 | Q45: 0 | R45: 0 | S45: 0
A46: 39 | F46: 1412 | H46: Боргові цінні папери органів державної влади та місцевого самоврядування, що рефінансуються Національним банком України, які обліковуються за справедливою вартістю через інший сукупний дохід | I46: А | J46: 0 | K46: 0 | L46: 0 | M46: 0 | O46: 0 | P46: 0 | Q46: 0 | R46: 0 | S46: 0
A47: 40 | F47: 1415 | H47: Переоцінка боргових цінних паперів, що рефінансуються Національним банком України, які обліковуються за справедливою вартістю через інший сукупний дохід | I47: А | J47: 0 | K47: 0 | L47: 0 | M47: 0 | O47: 0 | P47: 0 | Q47: 0 | R47: 0 | S47: 0
A48: 41 | I48: П | J48: 0 | K48: 0 | L48: 0 | M48: 0 | O48: 0 | P48: 0 | Q48: 0 | R48: 0 | S48: 0
A49: 42 | F49: 1416 | H49: Неамортизована премія/дисконт за борговими цінними паперами, що рефінансуються Національним банком України, які обліковуються за справедливою вартістю через інший сукупний дохід | I49: А | J49: 0 | K49: 0 | L49: 0 | M49: 0 | O49: 0 | P49: 0 | Q49: 0 | R49: 0 | S49: 0
A50: 43 | I50: П | J50: 0 | K50: 0 | L50: 0 | M50: 0 | O50: 0 | P50: 0 | Q50: 0 | R50: 0 | S50: 0
A51: 44 | F51: 1418 | H51: Нараховані доходи за борговими цінними паперами, що рефінансуються Національним банком України, які обліковуються за справедливою вартістю через інший сукупний дохід | I51: А | J51: 0 | K51: 0 | L51: 0 | M51: 0 | O51: 0 | P51: 0 | Q51: 0 | R51: 0 | S51: 0
A52: 45 | F52: 1419 | H52: Резерв за борговими цінними паперами,що рефінансуються Національним банком України, які обліковуються за справедливою вартістю через інший сукупний дохід | I52: П | J52: 0 | K52: 0 | L52: 0 | M52: 0 | O52: 0 | P52: 0 | Q52: 0 | R52: 0 | S52: 0
A53: 46 | F53: Група 141 - Усього | J53: 0 | K53: 0 | L53: 0 | M53: 0 | O53: 0 | P53: 0 | Q53: 0 | R53: 0 | S53: 0
A54: 47 | D54: 142 | F54: 1420 | H54: Облігації внутрішньої державної позики, що рефінансуються Національним банком України, які обліковуються за амортизованою собівартістю | I54: А | J54: 0 | K54: 0 | L54: 0 | M54: 0 | O54: 0 | P54: 0 | Q54: 0 | R54: 0 | S54: 0
A55: 48 | F55: 1426 | H55: Неамортизована премія/дисконт за борговими цінними паперами, що рефінансуються Національним банком України, які обліковуються за амортизованою собівартістю | I55: А | J55: 0 | K55: 0 | L55: 0 | M55: 0 | O55: 0 | P55: 0 | Q55: 0 | R55: 0 | S55: 0
A56: 49 | I56: П | J56: 0 | K56: 0 | L56: 0 | M56: 0 | O56: 0 | P56: 0 | Q56: 0 | R56: 0 | S56: 0
A57: 50 | F57: 1428 | H57: Нараховані доходи за борговими цінними паперами, що рефінансуються Національним банком України, які обліковуються за амортизованою собівартістю | I57: А | J57: 0 | K57: 0 | L57: 0 | M57: 0 | O57: 0 | P57: 0 | Q57: 0 | R57: 0 | S57: 0
A58: 51 | F58: 1429 | H58: Резерв за борговими цінними паперами,що рефінансуються Національним банком України, які обліковуються за амортизованою собівартістю | I58: П | J58: 0 | K58: 0 | L58: 0 | M58: 0 | O58: 0 | P58: 0 | Q58: 0 | R58: 0 | S58: 0
A59: 52 | F59: Група 142 - Усього | J59: 0 | K59: 0 | L59: 0 | M59: 0 | O59: 0 | P59: 0 | Q59: 0 | R59: 0 | S59: 0
A60: 53 | D60: 143 | F60: 1430 | H60: Депозитні сертифікати Національного банку України, розміщені в банках України, що обліковуються за справедливою вартістю через інший сукупний дохід | I60: А | J60: 0 | K60: 0 | L60: 0 | M60: 0 | O60: 0 | P60: 0 | Q60: 0 | R60: 0 | S60: 0
A61: 54 | F61: 1435 | H61: Переоцінка депозитних сертифікатів Національного банку України, розміщених у банках України, що обліковуються за справедливою вартістю через інший сукупний дохід | I61: А | J61: 0 | K61: 0 | L61: 0 | M61: 0 | O61: 0 | P61: 0 | Q61: 0 | R61: 0 | S61: 0
A62: 55 | I62: П | J62: 0 | K62: 0 | L62: 0 | M62: 0 | O62: 0 | P62: 0 | Q62: 0 | R62: 0 | S62: 0
A63: 56 | F63: 1436 | H63: Неамортизована премія/дисконт за депозитними сертифікатами Національного банку України, розміщеними в банках України, що обліковуються за справедливою вартістю через інший сукупний дохід | I63: А | J63: 0 | K63: 0 | L63: 0 | M63: 0 | O63: 0 | P63: 0 | Q63: 0 | R63: 0 | S63: 0
A64: 57 | I64: П | J64: 0 | K64: 0 | L64: 0 | M64: 0 | O64: 0 | P64: 0 | Q64: 0 | R64: 0 | S64: 0
A65: 58 | F65: 1438 | H65: Нараховані доходи за депозитними сертифікатами Національного банку України, розміщеними в банках України, що обліковуються за справедливою вартістю через інший сукупний дохід | I65: А | J65: 0 | K65: 0 | L65: 0 | M65: 0 | O65: 0 | P65: 0 | Q65: 0 | R65: 0 | S65: 0
A66: 59 | F66: Група 143 - Усього | J66: 0 | K66: 0 | L66: 0 | M66: 0 | O66: 0 | P66: 0 | Q66: 0 | R66: 0 | S66: 0
A67: 60 | D67: 144 | F67: 1440 | H67: Депозитні сертифікати Національного банку України, розміщені в банках України, що обліковуються за амортизованою собівартістю | I67: А | J67: 2560000 | K67: 2560000 | L67: 0 | M67: 2760000 | O67: 2760000 | P67: 0 | Q67: 0 | R67: 0 | S67: 0
A68: 61 | F68: 1446 | H68: Неамортизована премія/дисконт за депозитними сертифікатами Національного банку України, розміщеними в банках України, що обліковуються за амортизованою собівартістю | I68: А | J68: 0 | K68: 0 | L68: 0 | M68: 0 | O68: 0 | P68: 0 | Q68: 0 | R68: 0 | S68: 0
A69: 62 | I69: П | J69: 0 | K69: 0 | L69: 0 | M69: 0 | O69: 0 | P69: 0 | Q69: 0 | R69: 0 | S69: 0
A70: 63 | F70: 1448 | H70: Нараховані доходи за депозитними сертифікатами Національного банку України, розміщеними в банках України, що обліковуються за амортизованою собівартістю | I70: А | J70: 1471.2368 | K70: 1471.2368 | L70: 0 | M70: 1635.6208 | O70: 1635.6208 | P70: 0 | Q70: 0 | R70: 0 | S70: 0
A71: 64 | F71: Група 144 - Усього | J71: 2561471.2 | K71: 2561471.2 | L71: 0 | M71: 2761635.6 | O71: 2761635.6 | P71: 0 | Q71: 0 | R71: 0 | S71: 0
A72: 65 | D72: Розділ 14 - Усього | J72: 2561471.2 | K72: 2561471.2 | L72: 0 | M72: 2761635.6 | O72: 2761635.6 | P72: 0 | Q72: 0 | R72: 0 | S72: 0
A73: 66 | C73: 15 | D73: 150 | F73: 1500 | H73: Кореспондентські рахунки, що відкриті в інших банках | I73: А | J73: 47063.637 | K73: 28.32373 | L73: 47035.313 | M73: 64243.086 | O73: 662.97248 | P73: 63580.113 | Q73: 13109.051 | R73: 67.94231 | S73: 13041.109
A74: 67 | F74: 1508 | H74: Нараховані доходи за коштами на вимогу в інших банках | I74: А | J74: 0 | K74: 0 | L74: 0 | M74: 0 | O74: 0 | P74: 0 | Q74: 0 | R74: 0 | S74: 0
A75: 68 | F75: 1509 | H75: Резерв за коштами на вимогу в інших банках | I75: П | J75: 207.19276 | K75: 5.21636 | L75: 201.9764 | M75: 30.69999 | O75: 0 | P75: 30.69999 | Q75: -10529.833 | R75: -1.24242 | S75: -10528.59
A76: 69 | F76: Група 150 - Усього | J76: 47270.83 | K76: 33.54009 | L76: 47237.29 | M76: 64273.786 | O76: 662.97248 | P76: 63610.813 | Q76: 2579.2184 | R76: 66.69989 | S76: 2512.5185
A77: 70 | D77: 151 | F77: 1510 | H77: Депозити овернайт, що розміщені в інших банках, які обліковуються за амортизованою собівартістю | I77: А | J77: 0 | K77: 0 | L77: 0 | M77: 0 | O77: 0 | P77: 0 | Q77: 0 | R77: 0 | S77: 0
A78: 71 | F78: 1513 | H78: Строкові вклади (депозити), що розміщені в інших банках, які обліковуються за амортизованою собівартістю | I78: А | J78: 0 | K78: 0 | L78: 0 | M78: 0 | O78: 0 | P78: 0 | Q78: 0 | R78: 0 | S78: 0
A79: 72 | F79: 1516 | H79: Неамортизована премія/дисконт за строковими вкладами (депозитами), що розміщені в інших банках, які обліковуються за амортизованою собівартістю | I79: А | J79: 0 | K79: 0 | L79: 0 | M79: 0 | O79: 0 | P79: 0 | Q79: 0 | R79: 0 | S79: 0
A80: 73 | I80: П | J80: 0 | K80: 0 | L80: 0 | M80: 0 | O80: 0 | P80: 0 | Q80: 0 | R80: 0 | S80: 0
A81: 74 | F81: 1518 | H81: Нараховані доходи за строковими вкладами (депозитами), що розміщені в інших банках, які обліковуються за амортизованою собівартістю | I81: А | J81: 0 | K81: 0 | L81: 0 | M81: 0 | O81: 0 | P81: 0 | Q81: 0 | R81: 0 | S81: 0
A82: 75 | F82: 1519 | H82: Резерв за строковими вкладами (депозитами), що розміщені в інших банках, які обліковуються за амортизованою собівартістю | I82: П | J82: 0 | K82: 0 | L82: 0 | M82: 0 | O82: 0 | P82: 0 | Q82: 0 | R82: 0 | S82: 0
A83: 76 | F83: Група 151 - Усього | J83: 0 | K83: 0 | L83: 0 | M83: 0 | O83: 0 | P83: 0 | Q83: 0 | R83: 0 | S83: 0
A84: 77 | D84: 152 | F84: 1521 | H84: Кредити овернайт, що надані іншим банкам,які обліковуються за амортизованою собівартістю | I84: А | J84: 0 | K84: 0 | L84: 0 | M84: 0 | O84: 0 | P84: 0 | Q84: 0 | R84: 0 | S84: 0
A85: 78 | F85: 1522 | H85: Кредити, що надані іншим банкам за операціями репо, які обліковуються за амортизованою собівартістю | I85: А | J85: 0 | K85: 0 | L85: 0 | M85: 0 | O85: 0 | P85: 0 | Q85: 0 | R85: 0 | S85: 0
A86: 79 | F86: 1524 | H86: Інші кредити, що надані іншим банкам, які обліковуються за амортизованою собівартістю | I86: А | J86: 0 | K86: 0 | L86: 0 | M86: 0 | O86: 0 | P86: 0 | Q86: 0 | R86: 0 | S86: 0
A87: 80 | F87: 1526 | H87: Неамортизована премія/дисконт за кредитами, що надані іншим банкам, які обліковуються за амортизованою собівартістю | I87: А | J87: 0 | K87: 0 | L87: 0 | M87: 0 | O87: 0 | P87: 0 | Q87: 0 | R87: 0 | S87: 0
A88: 81 | I88: П | J88: 0 | K88: 0 | L88: 0 | M88: 0 | O88: 0 | P88: 0 | Q88: 0 | R88: 0 | S88: 0
A89: 82 | F89: 1528 | H89: Нараховані доходи за кредитами, що надані іншим банкам, які обліковуються за амортизованою собівартістю | I89: А | J89: 0 | K89: 0 | L89: 0 | M89: 0 | O89: 0 | P89: 0 | Q89: 0 | R89: 0 | S89: 0
A90: 83 | F90: 1529 | H90: Резерв за кредитами, що надані іншим банкам, які обліковуються за амортизованою собівартістю | I90: П | J90: 0 | K90: 0 | L90: 0 | M90: 0 | O90: 0 | P90: 0 | Q90: 0 | R90: 0 | S90: 0
A91: 84 | F91: Група 152 - Усього | J91: 0 | K91: 0 | L91: 0 | M91: 0 | O91: 0 | P91: 0 | Q91: 0 | R91: 0 | S91: 0
A92: 85 | D92: Розділ 15 - Усього | J92: 47270.83 | K92: 33.54009 | L92: 47237.29 | M92: 64273.786 | O92: 662.97248 | P92: 63610.813 | Q92: 2579.2184 | R92: 66.69989 | S92: 2512.5185
A93: 86 | C93: 16 | D93: 160 | F93: 1600 | H93: Кореспондентські рахунки інших банків | I93: А | J93: 0 | K93: 0 | L93: 0 | M93: 0 | O93: 0 | P93: 0 | Q93: 0 | R93: 0 | S93: 0
A94: 87 | F94: Група 160 - Усього | J94: 0 | K94: 0 | L94: 0 | M94: 0 | O94: 0 | P94: 0 | Q94: 0 | R94: 0 | S94: 0
A95: 88 | D95: Розділ 16 - Усього | J95: 0 | K95: 0 | L95: 0 | M95: 0 | O95: 0 | P95: 0 | Q95: 0 | R95: 0 | S95: 0
A96: 89 | C96: 18 | D96: 181 | F96: 1811 | H96: Дебіторська заборгованість за операціями з готівкою | I96: А | J96: 115092.84 | K96: 71621.613 | L96: 43471.227 | M96: 115092.84 | O96: 71621.613 | P96: 43471.227 | Q96: 0 | R96: 0 | S96: 0
A97: 90 | F97: 1819 | H97: Інша дебіторська заборгованість за операціями з банками | I97: А | J97: 45069.422 | K97: 0 | L97: 45069.422 | M97: 45069.601 | O97: 0 | P97: 45069.601 | Q97: 41.84358 | R97: 0 | S97: 41.84358
A98: 91 | F98: Група 181 - Усього | J98: 160162.26 | K98: 71621.613 | L98: 88540.649 | M98: 160162.44 | O98: 71621.613 | P98: 88540.828 | Q98: 41.84358 | R98: 0 | S98: 41.84358
A99: 92 | D99: 183 | F99: 1832 | H99: Кошти банків у розрахунках | I99: А | J99: 4719.1983 | K99: 4623.6159 | L99: 95.5824 | M99: 5359.334 | O99: 5130.9894 | P99: 228.34465 | Q99: 6641.1114 | R99: 6470.1491 | S99: 170.96235
A100: 93 | F100: 1839 | H100: Резерви за коштами банків у розрахунках | I100: П | J100: 90.58053 | K100: 79.70074 | L100: 10.87979 | M100: 0.6488 | O100: 0 | P100: 0.6488 | Q100: -404.10074 | R100: -393.66685 | S100: -10.43389
...

Sheet  29АТ "БАНК АЛЬЯНС" 
A1: Зміст
B2: Оборотно-сальдовий баланс банку АТ "БАНК АЛЬЯНС" за станом на 01.03.2026
B3: (тис грн)
A4: Номер з/п | B4: Клас/ розділ/ група/ рахунок | I4: Актив/ пасив | J4: Обороти за місяць | Q4: Сальдо
J5: дебет | M5: кредит | Q5: усього | R5: НВ | S5: ІВ
B6: номер | F6: назва | J6: усього | K6: НВ | L6: ІВ | M6: усього | O6: НВ | P6: ІВ
A7: 1 | B7: 2 | F7: 3 | I7: 4 | J7: 5 | K7: 6 | L7: 7 | M7: 8 | O7: 9 | P7: 10 | Q7: 11 | R7: 12 | S7: 13
A8: 1 | B8: Балансові рахунки
A9: 2 | B9: Активи
A10: 3 | B10: Класи 1 - 4
A11: 4 | B11: Клас 1 | C11: 10 | D11: 100 | F11: 1001 | H11: Банкноти та монети в касі банку | I11: А | J11: 0 | K11: 0 | L11: 0 | M11: 0 | O11: 0 | P11: 0 | Q11: 0 | R11: 0 | S11: 0
A12: 5 | F12: 1002 | H12: Банкноти та монети в касі відділень банку | I12: А | J12: 5914005.9 | K12: 3084127.6 | L12: 2829878.3 | M12: 5943978.8 | O12: 3071289.4 | P12: 2872689.4 | Q12: 251905.6 | R12: 114771.12 | S12: 137134.49
A13: 6 | F13: 1004 | H13: Банкноти та монети в банкоматах | I13: А | J13: 4182370.7 | K13: 2136668.1 | L13: 2045702.6 | M13: 4168093.5 | O13: 2127828.4 | P13: 2040265.2 | Q13: 143784.34 | R13: 108761.99 | S13: 35022.355
A14: 7 | F14: 1005 | H14: Банкноти та монети, інкасовані до перерахування | I14: А | J14: 9057.9186 | K14: 9057.9186 | L14: 0 | M14: 9057.9186 | O14: 9057.9186 | P14: 0 | Q14: 0 | R14: 0 | S14: 0
A15: 8 | F15: 1006 | H15: Банкноти та монети на зберіганні в інкасаторській компанії | I15: А | J15: 0 | K15: 0 | L15: 0 | M15: 0 | O15: 0 | P15: 0 | Q15: 0 | R15: 0 | S15: 0
A16: 9 | F16: 1007 | H16: Банкноти та монети в дорозі | I16: А | J16: 6356298.7 | K16: 3256552.9 | L16: 3099745.8 | M16: 6356298.7 | O16: 3256552.9 | P16: 3099745.8 | Q16: 0 | R16: 0 | S16: 0
A17: 10 | F17: Група 100 - Усього | J17: 16461733 | K17: 8486406.6 | L17: 7975326.7 | M17: 16477429 | O17: 8464728.6 | P17: 8012700.3 | Q17: 395689.95 | R17: 223533.11 | S17: 172156.84
A18: 11 | D18: 101 | F18: 1011 | H18: Дорожні чеки в касі банку | I18: А | J18: 0 | K18: 0 | L18: 0 | M18: 0 | O18: 0 | P18: 0 | Q18: 0 | R18: 0 | S18: 0
A19: 12 | F19: 1012 | H19: Дорожні чеки в касі відділень банку | I19: А | J19: 0 | K19: 0 | L19: 0 | M19: 0 | O19: 0 | P19: 0 | Q19: 0 | R19: 0 | S19: 0
A20: 13 | F20: Група 101 - Усього | J20: 0 | K20: 0 | L20: 0 | M20: 0 | O20: 0 | P20: 0 | Q20: 0 | R20: 0 | S20: 0
A21: 14 | D21: 109 | F21: 1090 | H21: Резерви за готівковими коштами, наявність яких є непідтвердженою | I21: П | J21: 0 | K21: 0 | L21: 0 | M21: 0 | O21: 0 | P21: 0 | Q21: 0 | R21: 0 | S21: 0
A22: 15 | F22: Група 109 - Усього | J22: 0 | K22: 0 | L22: 0 | M22: 0 | O22: 0 | P22: 0 | Q22: 0 | R22: 0 | S22: 0
A23: 16 | D23: Розділ 10 - Усього | J23: 16461733 | K23: 8486406.6 | L23: 7975326.7 | M23: 16477429 | O23: 8464728.6 | P23: 8012700.3 | Q23: 395689.95 | R23: 223533.11 | S23: 172156.84
A24: 17 | C24: 11 | D24: 110 | F24: 1101 | H24: Банківські метали в банку | I24: А | J24: 0 | K24: 0 | L24: 0 | M24: 0 | O24: 0 | P24: 0 | Q24: 0 | R24: 0 | S24: 0
A25: 18 | F25: 1102 | H25: Банківські метали у відділенні банку | I25: А | J25: 407.81537 | K25: 0 | L25: 407.81537 | M25: 1703.0032 | O25: 0 | P25: 1703.0032 | Q25: 2518.5548 | R25: 0 | S25: 2518.5548
A26: 19 | F26: 1107 | H26: Банківські метали в дорозі | I26: А | J26: 0 | K26: 0 | L26: 0 | M26: 0 | O26: 0 | P26: 0 | Q26: 0 | R26: 0 | S26: 0
A27: 20 | F27: Група 110 - Усього | J27: 407.81537 | K27: 0 | L27: 407.81537 | M27: 1703.0032 | O27: 0 | P27: 1703.0032 | Q27: 2518.5548 | R27: 0 | S27: 2518.5548
A28: 21 | D28: 119 | F28: 1190 | H28: Резерви за банківськими металами, наявність яких є непідтвердженою | I28: П | J28: 0 | K28: 0 | L28: 0 | M28: 0 | O28: 0 | P28: 0 | Q28: 0 | R28: 0 | S28: 0
A29: 22 | F29: Група 119 - Усього | J29: 0 | K29: 0 | L29: 0 | M29: 0 | O29: 0 | P29: 0 | Q29: 0 | R29: 0 | S29: 0
A30: 23 | D30: Розділ 11 - Усього | J30: 407.81537 | K30: 0 | L30: 407.81537 | M30: 1703.0032 | O30: 0 | P30: 1703.0032 | Q30: 2518.5548 | R30: 0 | S30: 2518.5548
A31: 24 | C31: 12 | D31: 120 | F31: 1200 | H31: Кореспондентський рахунок банку в Національному банку України | I31: А | J31: 31603437 | K31: 31603437 | L31: 0 | M31: 31126964 | O31: 31126964 | P31: 0 | Q31: 920992.33 | R31: 920992.33 | S31: 0
A32: 25 | F32: 1202 | H32: Кошти банків за рахунками умовного зберігання (ескроу) у Національному банку України | I32: А | J32: 0 | K32: 0 | L32: 0 | M32: 0 | O32: 0 | P32: 0 | Q32: 0 | R32: 0 | S32: 0
A33: 26 | F33: 1205 | H33: Кошти банків для забезпечення виконання зобов’язань перед Національним банком України за кредитами, наданими банкам, та операціями своп процентної ставки | I33: А | J33: 0 | K33: 0 | L33: 0 | M33: 0 | O33: 0 | P33: 0 | Q33: 0 | R33: 0 | S33: 0
A34: 27 | F34: 1208 | H34: Нараховані доходи за коштами на вимогу в Національному банку України | I34: А | J34: 0 | K34: 0 | L34: 0 | M34: 0 | O34: 0 | P34: 0 | Q34: 0 | R34: 0 | S34: 0
A35: 28 | F35: Група 120 - Усього | J35: 31603437 | K35: 31603437 | L35: 0 | M35: 31126964 | O35: 31126964 | P35: 0 | Q35: 920992.33 | R35: 920992.33 | S35: 0
A36: 29 | D36: Розділ 12 - Усього | J36: 31603437 | K36: 31603437 | L36: 0 | M36: 31126964 | O36: 31126964 | P36: 0 | Q36: 920992.33 | R36: 920992.33 | S36: 0
A37: 30 | C37: 14 | D37: 140 | F37: 1400 | H37: Облігації внутрішньої державної позики, що рефінансуються Національним банком України, які обліковуються за справедливою вартістю через прибутки/збитки | I37: А | J37: 0 | K37: 0 | L37: 0 | M37: 0 | O37: 0 | P37: 0 | Q37: 0 | R37: 0 | S37: 0
A38: 31 | F38: 1405 | H38: Переоцінка боргових цінних паперів, що рефінансуються Національним банком України, які обліковуються за справедливою вартістю через прибутки/збитки | I38: А | J38: 0 | K38: 0 | L38: 0 | M38: 0 | O38: 0 | P38: 0 | Q38: 0 | R38: 0 | S38: 0
A39: 32 | I39: П | J39: 0 | K39: 0 | L39: 0 | M39: 0 | O39: 0 | P39: 0 | Q39: 0 | R39: 0 | S39: 0
A40: 33 | F40: 1406 | H40: Неамортизована премія/дисконт за борговими цінними паперами, що рефінансуються Національним банком України, які обліковуються за справедливою вартістю через прибутки/збитки | I40: А | J40: 0 | K40: 0 | L40: 0 | M40: 0 | O40: 0 | P40: 0 | Q40: 0 | R40: 0 | S40: 0
A41: 34 | I41: П | J41: 0 | K41: 0 | L41: 0 | M41: 0 | O41: 0 | P41: 0 | Q41: 0 | R41: 0 | S41: 0
A42: 35 | F42: 1408 | H42: Нараховані доходи за борговими цінними паперами, що рефінансуються Національним банком України, які обліковуються за справедливою вартістю через прибутки/збитки | I42: А | J42: 0 | K42: 0 | L42: 0 | M42: 0 | O42: 0 | P42: 0 | Q42: 0 | R42: 0 | S42: 0
A43: 36 | F43: Група 140 - Усього | J43: 0 | K43: 0 | L43: 0 | M43: 0 | O43: 0 | P43: 0 | Q43: 0 | R43: 0 | S43: 0
A44: 37 | D44: 141 | F44: 1410 | H44: Облігації внутрішньої державної позики, що рефінансуються Національним банком України, які обліковуються за справедливою вартістю через інший сукупний дохід | I44: А | J44: 0 | K44: 0 | L44: 0 | M44: 0 | O44: 0 | P44: 0 | Q44: 0 | R44: 0 | S44: 0
A45: 38 | F45: 1411 | H45: Облігації зовнішньої державної позики, що рефінансуються Національним банком України, які обліковуються за справедливою вартістю через інший сукупний дохід | I45: А | J45: 0 | K45: 0 | L45: 0 | M45: 0 | O45: 0 | P45: 0 | Q45: 0 | R45: 0 | S45: 0
A46: 39 | F46: 1412 | H46: Боргові цінні папери органів державної влади та місцевого самоврядування, що рефінансуються Національним банком України, які обліковуються за справедливою вартістю через інший сукупний дохід | I46: А | J46: 0 | K46: 0 | L46: 0 | M46: 0 | O46: 0 | P46: 0 | Q46: 0 | R46: 0 | S46: 0
A47: 40 | F47: 1415 | H47: Переоцінка боргових цінних паперів, що рефінансуються Національним банком України, які обліковуються за справедливою вартістю через інший сукупний дохід | I47: А | J47: 0 | K47: 0 | L47: 0 | M47: 0 | O47: 0 | P47: 0 | Q47: 0 | R47: 0 | S47: 0
A48: 41 | I48: П | J48: 0 | K48: 0 | L48: 0 | M48: 0 | O48: 0 | P48: 0 | Q48: 0 | R48: 0 | S48: 0
A49: 42 | F49: 1416 | H49: Неамортизована премія/дисконт за борговими цінними паперами, що рефінансуються Національним банком України, які обліковуються за справедливою вартістю через інший сукупний дохід | I49: А | J49: 0 | K49: 0 | L49: 0 | M49: 0 | O49: 0 | P49: 0 | Q49: 0 | R49: 0 | S49: 0
A50: 43 | I50: П | J50: 0 | K50: 0 | L50: 0 | M50: 0 | O50: 0 | P50: 0 | Q50: 0 | R50: 0 | S50: 0
A51: 44 | F51: 1418 | H51: Нараховані доходи за борговими цінними паперами, що рефінансуються Національним банком України, які обліковуються за справедливою вартістю через інший сукупний дохід | I51: А | J51: 0 | K51: 0 | L51: 0 | M51: 0 | O51: 0 | P51: 0 | Q51: 0 | R51: 0 | S51: 0
A52: 45 | F52: 1419 | H52: Резерв за борговими цінними паперами,що рефінансуються Національним банком України, які обліковуються за справедливою вартістю через інший сукупний дохід | I52: П | J52: 0 | K52: 0 | L52: 0 | M52: 0 | O52: 0 | P52: 0 | Q52: 0 | R52: 0 | S52: 0
A53: 46 | F53: Група 141 - Усього | J53: 0 | K53: 0 | L53: 0 | M53: 0 | O53: 0 | P53: 0 | Q53: 0 | R53: 0 | S53: 0
A54: 47 | D54: 142 | F54: 1420 | H54: Облігації внутрішньої державної позики, що рефінансуються Національним банком України, які обліковуються за амортизованою собівартістю | I54: А | J54: 0 | K54: 0 | L54: 0 | M54: 0 | O54: 0 | P54: 0 | Q54: 5000000 | R54: 5000000 | S54: 0
A55: 48 | F55: 1426 | H55: Неамортизована премія/дисконт за борговими цінними паперами, що рефінансуються Національним банком України, які обліковуються за амортизованою собівартістю | I55: А | J55: 3273.5908 | K55: 3273.5908 | L55: 0 | M55: 6804.8255 | O55: 6804.8255 | P55: 0 | Q55: 31794.336 | R55: 31794.336 | S55: 0
A56: 49 | I56: П | J56: 0 | K56: 0 | L56: 0 | M56: 0 | O56: 0 | P56: 0 | Q56: -53663.784 | R56: -53663.784 | S56: 0
A57: 50 | F57: 1428 | H57: Нараховані доходи за борговими цінними паперами, що рефінансуються Національним банком України, які обліковуються за амортизованою собівартістю | I57: А | J57: 66431.445 | K57: 66431.445 | L57: 0 | M57: 60399 | O57: 60399 | P57: 0 | Q57: 200791.95 | R57: 200791.95 | S57: 0
A58: 51 | F58: 1429 | H58: Резерв за борговими цінними паперами,що рефінансуються Національним банком України, які обліковуються за амортизованою собівартістю | I58: П | J58: 0 | K58: 0 | L58: 0 | M58: 0 | O58: 0 | P58: 0 | Q58: 0 | R58: 0 | S58: 0
A59: 52 | F59: Група 142 - Усього | J59: 69705.036 | K59: 69705.036 | L59: 0 | M59: 67203.825 | O59: 67203.825 | P59: 0 | Q59: 5178922.5 | R59: 5178922.5 | S59: 0
A60: 53 | D60: 143 | F60: 1430 | H60: Депозитні сертифікати Національного банку України, розміщені в банках України, що обліковуються за справедливою вартістю через інший сукупний дохід | I60: А | J60: 0 | K60: 0 | L60: 0 | M60: 0 | O60: 0 | P60: 0 | Q60: 0 | R60: 0 | S60: 0
A61: 54 | F61: 1435 | H61: Переоцінка депозитних сертифікатів Національного банку України, розміщених у банках України, що обліковуються за справедливою вартістю через інший сукупний дохід | I61: А | J61: 0 | K61: 0 | L61: 0 | M61: 0 | O61: 0 | P61: 0 | Q61: 0 | R61: 0 | S61: 0
A62: 55 | I62: П | J62: 0 | K62: 0 | L62: 0 | M62: 0 | O62: 0 | P62: 0 | Q62: 0 | R62: 0 | S62: 0
A63: 56 | F63: 1436 | H63: Неамортизована премія/дисконт за депозитними сертифікатами Національного банку України, розміщеними в банках України, що обліковуються за справедливою вартістю через інший сукупний дохід | I63: А | J63: 0 | K63: 0 | L63: 0 | M63: 0 | O63: 0 | P63: 0 | Q63: 0 | R63: 0 | S63: 0
A64: 57 | I64: П | J64: 0 | K64: 0 | L64: 0 | M64: 0 | O64: 0 | P64: 0 | Q64: 0 | R64: 0 | S64: 0
A65: 58 | F65: 1438 | H65: Нараховані доходи за депозитними сертифікатами Національного банку України, розміщеними в банках України, що обліковуються за справедливою вартістю через інший сукупний дохід | I65: А | J65: 0 | K65: 0 | L65: 0 | M65: 0 | O65: 0 | P65: 0 | Q65: 0 | R65: 0 | S65: 0
A66: 59 | F66: Група 143 - Усього | J66: 0 | K66: 0 | L66: 0 | M66: 0 | O66: 0 | P66: 0 | Q66: 0 | R66: 0 | S66: 0
A67: 60 | D67: 144 | F67: 1440 | H67: Депозитні сертифікати Національного банку України, розміщені в банках України, що обліковуються за амортизованою собівартістю | I67: А | J67: 1150000 | K67: 1150000 | L67: 0 | M67: 1400000 | O67: 1400000 | P67: 0 | Q67: 1050000 | R67: 1050000 | S67: 0
A68: 61 | F68: 1446 | H68: Неамортизована премія/дисконт за депозитними сертифікатами Національного банку України, розміщеними в банках України, що обліковуються за амортизованою собівартістю | I68: А | J68: 0 | K68: 0 | L68: 0 | M68: 0 | O68: 0 | P68: 0 | Q68: 0 | R68: 0 | S68: 0
A69: 62 | I69: П | J69: 0 | K69: 0 | L69: 0 | M69: 0 | O69: 0 | P69: 0 | Q69: 0 | R69: 0 | S69: 0
A70: 63 | F70: 1448 | H70: Нараховані доходи за депозитними сертифікатами Національного банку України, розміщеними в банках України, що обліковуються за амортизованою собівартістю | I70: А | J70: 9456.164 | K70: 9456.164 | L70: 0 | M70: 29326.028 | O70: 29326.028 | P70: 0 | Q70: 1294.524 | R70: 1294.524 | S70: 0
A71: 64 | F71: Група 144 - Усього | J71: 1159456.2 | K71: 1159456.2 | L71: 0 | M71: 1429326 | O71: 1429326 | P71: 0 | Q71: 1051294.5 | R71: 1051294.5 | S71: 0
A72: 65 | D72: Розділ 14 - Усього | J72: 1229161.2 | K72: 1229161.2 | L72: 0 | M72: 1496529.9 | O72: 1496529.9 | P72: 0 | Q72: 6230217 | R72: 6230217 | S72: 0
A73: 66 | C73: 15 | D73: 150 | F73: 1500 | H73: Кореспондентські рахунки, що відкриті в інших банках | I73: А | J73: 32601730 | K73: 1182110.4 | L73: 31419619 | M73: 33843598 | O73: 1151015.9 | P73: 32692582 | Q73: 1447726.3 | R73: 37359.845 | S73: 1410366.5
A74: 67 | F74: 1508 | H74: Нараховані доходи за коштами на вимогу в інших банках | I74: А | J74: 0 | K74: 0 | L74: 0 | M74: 0 | O74: 0 | P74: 0 | Q74: 0 | R74: 0 | S74: 0
A75: 68 | F75: 1509 | H75: Резерв за коштами на вимогу в інших банках | I75: П | J75: 70493.687 | K75: 333.40617 | L75: 70160.281 | M75: 67718.172 | O75: 1652.7504 | P75: 66065.422 | Q75: -66586.294 | R75: -1652.7504 | S75: -64933.544
A76: 69 | F76: Група 150 - Усього | J76: 32672223 | K76: 1182443.8 | L76: 31489779 | M76: 33911316 | O76: 1152668.6 | P76: 32758647 | Q76: 1381140.1 | R76: 35707.095 | S76: 1345433
A77: 70 | D77: 151 | F77: 1510 | H77: Депозити овернайт, що розміщені в інших банках, які обліковуються за амортизованою собівартістю | I77: А | J77: 0 | K77: 0 | L77: 0 | M77: 0 | O77: 0 | P77: 0 | Q77: 0 | R77: 0 | S77: 0
A78: 71 | F78: 1513 | H78: Строкові вклади (депозити), що розміщені в інших банках, які обліковуються за амортизованою собівартістю | I78: А | J78: 0 | K78: 0 | L78: 0 | M78: 0 | O78: 0 | P78: 0 | Q78: 0 | R78: 0 | S78: 0
A79: 72 | F79: 1516 | H79: Неамортизована премія/дисконт за строковими вкладами (депозитами), що розміщені в інших банках, які обліковуються за амортизованою собівартістю | I79: А | J79: 0 | K79: 0 | L79: 0 | M79: 0 | O79: 0 | P79: 0 | Q79: 0 | R79: 0 | S79: 0
A80: 73 | I80: П | J80: 0 | K80: 0 | L80: 0 | M80: 0 | O80: 0 | P80: 0 | Q80: 0 | R80: 0 | S80: 0
A81: 74 | F81: 1518 | H81: Нараховані доходи за строковими вкладами (депозитами), що розміщені в інших банках, які обліковуються за амортизованою собівартістю | I81: А | J81: 0 | K81: 0 | L81: 0 | M81: 0 | O81: 0 | P81: 0 | Q81: 0 | R81: 0 | S81: 0
A82: 75 | F82: 1519 | H82: Резерв за строковими вкладами (депозитами), що розміщені в інших банках, які обліковуються за амортизованою собівартістю | I82: П | J82: 0 | K82: 0 | L82: 0 | M82: 0 | O82: 0 | P82: 0 | Q82: 0 | R82: 0 | S82: 0
A83: 76 | F83: Група 151 - Усього | J83: 0 | K83: 0 | L83: 0 | M83: 0 | O83: 0 | P83: 0 | Q83: 0 | R83: 0 | S83: 0
A84: 77 | D84: 152 | F84: 1521 | H84: Кредити овернайт, що надані іншим банкам,які обліковуються за амортизованою собівартістю | I84: А | J84: 0 | K84: 0 | L84: 0 | M84: 0 | O84: 0 | P84: 0 | Q84: 0 | R84: 0 | S84: 0
A85: 78 | F85: 1522 | H85: Кредити, що надані іншим банкам за операціями репо, які обліковуються за амортизованою собівартістю | I85: А | J85: 0 | K85: 0 | L85: 0 | M85: 0 | O85: 0 | P85: 0 | Q85: 0 | R85: 0 | S85: 0
A86: 79 | F86: 1524 | H86: Інші кредити, що надані іншим банкам, які обліковуються за амортизованою собівартістю | I86: А | J86: 0 | K86: 0 | L86: 0 | M86: 0 | O86: 0 | P86: 0 | Q86: 0 | R86: 0 | S86: 0
A87: 80 | F87: 1526 | H87: Неамортизована премія/дисконт за кредитами, що надані іншим банкам, які обліковуються за амортизованою собівартістю | I87: А | J87: 0 | K87: 0 | L87: 0 | M87: 0 | O87: 0 | P87: 0 | Q87: 0 | R87: 0 | S87: 0
A88: 81 | I88: П | J88: 0 | K88: 0 | L88: 0 | M88: 0 | O88: 0 | P88: 0 | Q88: 0 | R88: 0 | S88: 0
A89: 82 | F89: 1528 | H89: Нараховані доходи за кредитами, що надані іншим банкам, які обліковуються за амортизованою собівартістю | I89: А | J89: 0 | K89: 0 | L89: 0 | M89: 0 | O89: 0 | P89: 0 | Q89: 0 | R89: 0 | S89: 0
A90: 83 | F90: 1529 | H90: Резерв за кредитами, що надані іншим банкам, які обліковуються за амортизованою собівартістю | I90: П | J90: 0 | K90: 0 | L90: 0 | M90: 0 | O90: 0 | P90: 0 | Q90: 0 | R90: 0 | S90: 0
A91: 84 | F91: Група 152 - Усього | J91: 0 | K91: 0 | L91: 0 | M91: 0 | O91: 0 | P91: 0 | Q91: 0 | R91: 0 | S91: 0
A92: 85 | D92: Розділ 15 - Усього | J92: 32672223 | K92: 1182443.8 | L92: 31489779 | M92: 33911316 | O92: 1152668.6 | P92: 32758647 | Q92: 1381140.1 | R92: 35707.095 | S92: 1345433
A93: 86 | C93: 16 | D93: 160 | F93: 1600 | H93: Кореспондентські рахунки інших банків | I93: А | J93: 0 | K93: 0 | L93: 0 | M93: 0 | O93: 0 | P93: 0 | Q93: 0 | R93: 0 | S93: 0
A94: 87 | F94: Група 160 - Усього | J94: 0 | K94: 0 | L94: 0 | M94: 0 | O94: 0 | P94: 0 | Q94: 0 | R94: 0 | S94: 0
A95: 88 | D95: Розділ 16 - Усього | J95: 0 | K95: 0 | L95: 0 | M95: 0 | O95: 0 | P95: 0 | Q95: 0 | R95: 0 | S95: 0
A96: 89 | C96: 18 | D96: 181 | F96: 1811 | H96: Дебіторська заборгованість за операціями з готівкою | I96: А | J96: 2969998.1 | K96: 1250070 | L96: 1719928.1 | M96: 2969998.1 | O96: 1250070 | P96: 1719928.1 | Q96: 0 | R96: 0 | S96: 0
A97: 90 | F97: 1819 | H97: Інша дебіторська заборгованість за операціями з банками | I97: А | J97: 500 | K97: 500 | L97: 0 | M97: 500 | O97: 500 | P97: 0 | Q97: 0 | R97: 0 | S97: 0
A98: 91 | F98: Група 181 - Усього | J98: 2970498.1 | K98: 1250570 | L98: 1719928.1 | M98: 2970498.1 | O98: 1250570 | P98: 1719928.1 | Q98: 0 | R98: 0 | S98: 0
A99: 92 | D99: 183 | F99: 1832 | H99: Кошти банків у розрахунках | I99: А | J99: 1531456.1 | K99: 0 | L99: 1531456.1 | M99: 1483010.2 | O99: 0 | P99: 1483010.2 | Q99: 57192.893 | R99: 8747 | S99: 48445.893
A100: 93 | F100: 1839 | H100: Резерви за коштами банків у розрахунках | I100: П | J100: 0 | K100: 0 | L100: 0 | M100: 43.6013 | O100: 0 | P100: 43.6013 | Q100: -43.6013 | R100: 0 | S100: -43.6013
...

Sheet  36АТ "Райффайзен Банк" 
A1: Зміст
B2: Оборотно-сальдовий баланс банку АТ "Райффайзен Банк" за станом на 01.03.2026
B3: (тис грн)
A4: Номер з/п | B4: Клас/ розділ/ група/ рахунок | I4: Актив/ пасив | J4: Обороти за місяць | Q4: Сальдо
J5: дебет | M5: кредит | Q5: усього | R5: НВ | S5: ІВ
B6: номер | F6: назва | J6: усього | K6: НВ | L6: ІВ | M6: усього | O6: НВ | P6: ІВ
A7: 1 | B7: 2 | F7: 3 | I7: 4 | J7: 5 | K7: 6 | L7: 7 | M7: 8 | O7: 9 | P7: 10 | Q7: 11 | R7: 12 | S7: 13
A8: 1 | B8: Балансові рахунки
A9: 2 | B9: Активи
A10: 3 | B10: Класи 1 - 4
A11: 4 | B11: Клас 1 | C11: 10 | D11: 100 | F11: 1001 | H11: Банкноти та монети в касі банку | I11: А | J11: 27799241 | K11: 16977007 | L11: 10822234 | M11: 27866755 | O11: 16869992 | P11: 10996763 | Q11: 4153591.9 | R11: 1261063.6 | S11: 2892528.3
A12: 5 | F12: 1002 | H12: Банкноти та монети в касі відділень банку | I12: А | J12: 47793586 | K12: 22796032 | L12: 24997554 | M12: 47679391 | O12: 23370904 | P12: 24308487 | Q12: 5039857.2 | R12: 1754011.7 | S12: 3285845.5
A13: 6 | F13: 1004 | H13: Банкноти та монети в банкоматах | I13: А | J13: 17073488 | K13: 16958904 | L13: 114583.72 | M13: 17199240 | O13: 17086163 | P13: 113076.88 | Q13: 2617846.6 | R13: 2577793.1 | S13: 40053.48
A14: 7 | F14: 1005 | H14: Банкноти та монети, інкасовані до перерахування | I14: А | J14: 1227183.3 | K14: 1227183.3 | L14: 0 | M14: 1227183.3 | O14: 1227183.3 | P14: 0 | Q14: 0 | R14: 0 | S14: 0
A15: 8 | F15: 1006 | H15: Банкноти та монети на зберіганні в інкасаторській компанії | I15: А | J15: 0 | K15: 0 | L15: 0 | M15: 0 | O15: 0 | P15: 0 | Q15: 0 | R15: 0 | S15: 0
A16: 9 | F16: 1007 | H16: Банкноти та монети в дорозі | I16: А | J16: 65050454 | K16: 36481549 | L16: 28568906 | M16: 65069025 | O16: 36654667 | P16: 28414358 | Q16: 2547928.4 | R16: 470061.02 | S16: 2077867.4
A17: 10 | F17: Група 100 - Усього | J17: 1.5894395e+08 | K17: 94440675 | L17: 64503277 | M17: 1.590416e+08 | O17: 95208910 | P17: 63832685 | Q17: 14359224 | R17: 6062929.5 | S17: 8296294.6
A18: 11 | D18: 101 | F18: 1011 | H18: Дорожні чеки в касі банку | I18: А | J18: 0 | K18: 0 | L18: 0 | M18: 0 | O18: 0 | P18: 0 | Q18: 0 | R18: 0 | S18: 0
A19: 12 | F19: 1012 | H19: Дорожні чеки в касі відділень банку | I19: А | J19: 0 | K19: 0 | L19: 0 | M19: 0 | O19: 0 | P19: 0 | Q19: 0 | R19: 0 | S19: 0
A20: 13 | F20: Група 101 - Усього | J20: 0 | K20: 0 | L20: 0 | M20: 0 | O20: 0 | P20: 0 | Q20: 0 | R20: 0 | S20: 0
A21: 14 | D21: 109 | F21: 1090 | H21: Резерви за готівковими коштами, наявність яких є непідтвердженою | I21: П | J21: 9618.22 | K21: 9618.22 | L21: 0 | M21: 9618.22 | O21: 9618.22 | P21: 0 | Q21: -9618.22 | R21: -9618.22 | S21: 0
A22: 15 | F22: Група 109 - Усього | J22: 9618.22 | K22: 9618.22 | L22: 0 | M22: 9618.22 | O22: 9618.22 | P22: 0 | Q22: -9618.22 | R22: -9618.22 | S22: 0
A23: 16 | D23: Розділ 10 - Усього | J23: 1.5895357e+08 | K23: 94450293 | L23: 64503277 | M23: 1.5905121e+08 | O23: 95218528 | P23: 63832685 | Q23: 14349606 | R23: 6053311.3 | S23: 8296294.6
A24: 17 | C24: 11 | D24: 110 | F24: 1101 | H24: Банківські метали в банку | I24: А | J24: 0 | K24: 0 | L24: 0 | M24: 0 | O24: 0 | P24: 0 | Q24: 0 | R24: 0 | S24: 0
A25: 18 | F25: 1102 | H25: Банківські метали у відділенні банку | I25: А | J25: 0 | K25: 0 | L25: 0 | M25: 0 | O25: 0 | P25: 0 | Q25: 0 | R25: 0 | S25: 0
A26: 19 | F26: 1107 | H26: Банківські метали в дорозі | I26: А | J26: 0 | K26: 0 | L26: 0 | M26: 0 | O26: 0 | P26: 0 | Q26: 0 | R26: 0 | S26: 0
A27: 20 | F27: Група 110 - Усього | J27: 0 | K27: 0 | L27: 0 | M27: 0 | O27: 0 | P27: 0 | Q27: 0 | R27: 0 | S27: 0
A28: 21 | D28: 119 | F28: 1190 | H28: Резерви за банківськими металами, наявність яких є непідтвердженою | I28: П | J28: 0 | K28: 0 | L28: 0 | M28: 0 | O28: 0 | P28: 0 | Q28: 0 | R28: 0 | S28: 0
A29: 22 | F29: Група 119 - Усього | J29: 0 | K29: 0 | L29: 0 | M29: 0 | O29: 0 | P29: 0 | Q29: 0 | R29: 0 | S29: 0
A30: 23 | D30: Розділ 11 - Усього | J30: 0 | K30: 0 | L30: 0 | M30: 0 | O30: 0 | P30: 0 | Q30: 0 | R30: 0 | S30: 0
A31: 24 | C31: 12 | D31: 120 | F31: 1200 | H31: Кореспондентський рахунок банку в Національному банку України | I31: А | J31: 7.9929295e+08 | K31: 7.9929295e+08 | L31: 0 | M31: 8.0261565e+08 | O31: 8.0261565e+08 | P31: 0 | Q31: 16759705 | R31: 16759705 | S31: 0
A32: 25 | F32: 1202 | H32: Кошти банків за рахунками умовного зберігання (ескроу) у Національному банку України | I32: А | J32: 0 | K32: 0 | L32: 0 | M32: 0 | O32: 0 | P32: 0 | Q32: 0 | R32: 0 | S32: 0
A33: 26 | F33: 1205 | H33: Кошти банків для забезпечення виконання зобов’язань перед Національним банком України за кредитами, наданими банкам, та операціями своп процентної ставки | I33: А | J33: 0 | K33: 0 | L33: 0 | M33: 0 | O33: 0 | P33: 0 | Q33: 0 | R33: 0 | S33: 0
A34: 27 | F34: 1208 | H34: Нараховані доходи за коштами на вимогу в Національному банку України | I34: А | J34: 0 | K34: 0 | L34: 0 | M34: 0 | O34: 0 | P34: 0 | Q34: 0 | R34: 0 | S34: 0
A35: 28 | F35: Група 120 - Усього | J35: 7.9929295e+08 | K35: 7.9929295e+08 | L35: 0 | M35: 8.0261565e+08 | O35: 8.0261565e+08 | P35: 0 | Q35: 16759705 | R35: 16759705 | S35: 0
A36: 29 | D36: Розділ 12 - Усього | J36: 7.9929295e+08 | K36: 7.9929295e+08 | L36: 0 | M36: 8.0261565e+08 | O36: 8.0261565e+08 | P36: 0 | Q36: 16759705 | R36: 16759705 | S36: 0
A37: 30 | C37: 14 | D37: 140 | F37: 1400 | H37: Облігації внутрішньої державної позики, що рефінансуються Національним банком України, які обліковуються за справедливою вартістю через прибутки/збитки | I37: А | J37: 3851399.2 | K37: 3742391 | L37: 109008.22 | M37: 3935099.8 | O37: 3834430 | P37: 100669.79 | Q37: 5623716.1 | R37: 5554324 | S37: 69392.113
A38: 31 | F38: 1405 | H38: Переоцінка боргових цінних паперів, що рефінансуються Національним банком України, які обліковуються за справедливою вартістю через прибутки/збитки | I38: А | J38: 603378.37 | K38: 593690.91 | L38: 9687.4606 | M38: 527740.04 | O38: 517433.34 | P38: 10306.707 | Q38: 118388.58 | R38: 118137.17 | S38: 251.40946
A39: 32 | I39: П | J39: 0 | K39: 0 | L39: 0 | M39: 0 | O39: 0 | P39: 0 | Q39: -33161.668 | R39: -32982.402 | S39: -179.26523
A40: 33 | F40: 1406 | H40: Неамортизована премія/дисконт за борговими цінними паперами, що рефінансуються Національним банком України, які обліковуються за справедливою вартістю через прибутки/збитки | I40: А | J40: 147671.44 | K40: 146510.71 | L40: 1160.7273 | M40: 147473.05 | O40: 146731.15 | P40: 741.8955 | Q40: 96912.095 | R40: 96384.044 | S40: 528.05135
A41: 34 | I41: П | J41: 0 | K41: 0 | L41: 0 | M41: 0 | O41: 0 | P41: 0 | Q41: -8362.0675 | R41: -8362.0675 | S41: 0
A42: 35 | F42: 1408 | H42: Нараховані доходи за борговими цінними паперами, що рефінансуються Національним банком України, які обліковуються за справедливою вартістю через прибутки/збитки | I42: А | J42: 147246.59 | K42: 145124.3 | L42: 2122.2942 | M42: 111925.07 | O42: 109927.82 | P42: 1997.2478 | Q42: 251885.22 | R42: 250962.06 | S42: 923.15831
A43: 36 | F43: Група 140 - Усього | J43: 4749695.6 | K43: 4627716.9 | L43: 121978.7 | M43: 4722237.9 | O43: 4608522.3 | P43: 113715.64 | Q43: 6049378.3 | R43: 5978462.8 | S43: 70915.467
A44: 37 | D44: 141 | F44: 1410 | H44: Облігації внутрішньої державної позики, що рефінансуються Національним банком України, які обліковуються за справедливою вартістю через інший сукупний дохід | I44: А | J44: 1756908 | K44: 1756908 | L44: 0 | M44: 550000 | O44: 550000 | P44: 0 | Q44: 28592135 | R44: 28592135 | S44: 0
A45: 38 | F45: 1411 | H45: Облігації зовнішньої державної позики, що рефінансуються Національним банком України, які обліковуються за справедливою вартістю через інший сукупний дохід | I45: А | J45: 0 | K45: 0 | L45: 0 | M45: 0 | O45: 0 | P45: 0 | Q45: 0 | R45: 0 | S45: 0
A46: 39 | F46: 1412 | H46: Боргові цінні папери органів державної влади та місцевого самоврядування, що рефінансуються Національним банком України, які обліковуються за справедливою вартістю через інший сукупний дохід | I46: А | J46: 0 | K46: 0 | L46: 0 | M46: 0 | O46: 0 | P46: 0 | Q46: 0 | R46: 0 | S46: 0
A47: 40 | F47: 1415 | H47: Переоцінка боргових цінних паперів, що рефінансуються Національним банком України, які обліковуються за справедливою вартістю через інший сукупний дохід | I47: А | J47: 7072050.1 | K47: 7072050.1 | L47: 0 | M47: 6550158.5 | O47: 6550158.5 | P47: 0 | Q47: 3557336.2 | R47: 3557336.2 | S47: 0
A48: 41 | I48: П | J48: 0 | K48: 0 | L48: 0 | M48: 0 | O48: 0 | P48: 0 | Q48: 0 | R48: 0 | S48: 0
A49: 42 | F49: 1416 | H49: Неамортизована премія/дисконт за борговими цінними паперами, що рефінансуються Національним банком України, які обліковуються за справедливою вартістю через інший сукупний дохід | I49: А | J49: 89271.535 | K49: 89271.535 | L49: 0 | M49: 22421.772 | O49: 22421.772 | P49: 0 | Q49: 439037.51 | R49: 439037.51 | S49: 0
A50: 43 | I50: П | J50: 0 | K50: 0 | L50: 0 | M50: 0 | O50: 0 | P50: 0 | Q50: -58169.247 | R50: -58169.247 | S50: 0
A51: 44 | F51: 1418 | H51: Нараховані доходи за борговими цінними паперами, що рефінансуються Національним банком України, які обліковуються за справедливою вартістю через інший сукупний дохід | I51: А | J51: 359171.02 | K51: 359171.02 | L51: 0 | M51: 585435.88 | O51: 585435.88 | P51: 0 | Q51: 1004702.8 | R51: 1004702.8 | S51: 0
A52: 45 | F52: 1419 | H52: Резерв за борговими цінними паперами,що рефінансуються Національним банком України, які обліковуються за справедливою вартістю через інший сукупний дохід | I52: П | J52: 3168840.6 | K52: 3168840.6 | L52: 0 | M52: 3326530 | O52: 3326530 | P52: 0 | Q52: -3326530 | R52: -3326530 | S52: 0
A53: 46 | F53: Група 141 - Усього | J53: 12446241 | K53: 12446241 | L53: 0 | M53: 11034546 | O53: 11034546 | P53: 0 | Q53: 30208512 | R53: 30208512 | S53: 0
A54: 47 | D54: 142 | F54: 1420 | H54: Облігації внутрішньої державної позики, що рефінансуються Національним банком України, які обліковуються за амортизованою собівартістю | I54: А | J54: 0 | K54: 0 | L54: 0 | M54: 1 | O54: 1 | P54: 0 | Q54: 6036907 | R54: 6036907 | S54: 0
A55: 48 | F55: 1426 | H55: Неамортизована премія/дисконт за борговими цінними паперами, що рефінансуються Національним банком України, які обліковуються за амортизованою собівартістю | I55: А | J55: 3398.1914 | K55: 3398.1914 | L55: 0 | M55: 371.6 | O55: 371.6 | P55: 0 | Q55: 37847.808 | R55: 37847.808 | S55: 0
A56: 49 | I56: П | J56: 0 | K56: 0 | L56: 0 | M56: 0 | O56: 0 | P56: 0 | Q56: -39704.164 | R56: -39704.164 | S56: 0
A57: 50 | F57: 1428 | H57: Нараховані доходи за борговими цінними паперами, що рефінансуються Національним банком України, які обліковуються за амортизованою собівартістю | I57: А | J57: 79309.356 | K57: 79309.356 | L57: 0 | M57: 148129.6 | O57: 148129.6 | P57: 0 | Q57: 249605.94 | R57: 249605.94 | S57: 0
A58: 51 | F58: 1429 | H58: Резерв за борговими цінними паперами,що рефінансуються Національним банком України, які обліковуються за амортизованою собівартістю | I58: П | J58: 646694.94 | K58: 646694.94 | L58: 0 | M58: 613854.58 | O58: 613854.58 | P58: 0 | Q58: -613854.58 | R58: -613854.58 | S58: 0
A59: 52 | F59: Група 142 - Усього | J59: 729402.49 | K59: 729402.49 | L59: 0 | M59: 762356.78 | O59: 762356.78 | P59: 0 | Q59: 5670802 | R59: 5670802 | S59: 0
A60: 53 | D60: 143 | F60: 1430 | H60: Депозитні сертифікати Національного банку України, розміщені в банках України, що обліковуються за справедливою вартістю через інший сукупний дохід | I60: А | J60: 0 | K60: 0 | L60: 0 | M60: 0 | O60: 0 | P60: 0 | Q60: 0 | R60: 0 | S60: 0
A61: 54 | F61: 1435 | H61: Переоцінка депозитних сертифікатів Національного банку України, розміщених у банках України, що обліковуються за справедливою вартістю через інший сукупний дохід | I61: А | J61: 0 | K61: 0 | L61: 0 | M61: 0 | O61: 0 | P61: 0 | Q61: 0 | R61: 0 | S61: 0
A62: 55 | I62: П | J62: 0 | K62: 0 | L62: 0 | M62: 0 | O62: 0 | P62: 0 | Q62: 0 | R62: 0 | S62: 0
A63: 56 | F63: 1436 | H63: Неамортизована премія/дисконт за депозитними сертифікатами Національного банку України, розміщеними в банках України, що обліковуються за справедливою вартістю через інший сукупний дохід | I63: А | J63: 0 | K63: 0 | L63: 0 | M63: 0 | O63: 0 | P63: 0 | Q63: 0 | R63: 0 | S63: 0
A64: 57 | I64: П | J64: 0 | K64: 0 | L64: 0 | M64: 0 | O64: 0 | P64: 0 | Q64: 0 | R64: 0 | S64: 0
A65: 58 | F65: 1438 | H65: Нараховані доходи за депозитними сертифікатами Національного банку України, розміщеними в банках України, що обліковуються за справедливою вартістю через інший сукупний дохід | I65: А | J65: 0 | K65: 0 | L65: 0 | M65: 0 | O65: 0 | P65: 0 | Q65: 0 | R65: 0 | S65: 0
A66: 59 | F66: Група 143 - Усього | J66: 0 | K66: 0 | L66: 0 | M66: 0 | O66: 0 | P66: 0 | Q66: 0 | R66: 0 | S66: 0
A67: 60 | D67: 144 | F67: 1440 | H67: Депозитні сертифікати Національного банку України, розміщені в банках України, що обліковуються за амортизованою собівартістю | I67: А | J67: 529603000 | K67: 529603000 | L67: 0 | M67: 528822000 | O67: 528822000 | P67: 0 | Q67: 16599000 | R67: 16599000 | S67: 0
A68: 61 | F68: 1446 | H68: Неамортизована премія/дисконт за депозитними сертифікатами Національного банку України, розміщеними в банках України, що обліковуються за амортизованою собівартістю | I68: А | J68: 0 | K68: 0 | L68: 0 | M68: 0 | O68: 0 | P68: 0 | Q68: 0 | R68: 0 | S68: 0
A69: 62 | I69: П | J69: 0 | K69: 0 | L69: 0 | M69: 0 | O69: 0 | P69: 0 | Q69: 0 | R69: 0 | S69: 0
A70: 63 | F70: 1448 | H70: Нараховані доходи за депозитними сертифікатами Національного банку України, розміщеними в банках України, що обліковуються за амортизованою собівартістю | I70: А | J70: 383509.36 | K70: 383509.36 | L70: 0 | M70: 407826.47 | O70: 407826.47 | P70: 0 | Q70: 106554.09 | R70: 106554.09 | S70: 0
A71: 64 | F71: Група 144 - Усього | J71: 5.2998651e+08 | K71: 5.2998651e+08 | L71: 0 | M71: 5.2922983e+08 | O71: 5.2922983e+08 | P71: 0 | Q71: 16705554 | R71: 16705554 | S71: 0
A72: 65 | D72: Розділ 14 - Усього | J72: 5.4791185e+08 | K72: 5.4778987e+08 | L72: 121978.7 | M72: 5.4574897e+08 | O72: 5.4563525e+08 | P72: 113715.64 | Q72: 58634247 | R72: 58563331 | S72: 70915.467
A73: 66 | C73: 15 | D73: 150 | F73: 1500 | H73: Кореспондентські рахунки, що відкриті в інших банках | I73: А | J73: 2.9655548e+08 | K73: 14112734 | L73: 2.8244274e+08 | M73: 2.9341389e+08 | O73: 13875005 | P73: 2.7953889e+08 | Q73: 36456363 | R73: 815178.32 | S73: 35641184
A74: 67 | F74: 1508 | H74: Нараховані доходи за коштами на вимогу в інших банках | I74: А | J74: 43123.736 | K74: 0 | L74: 43123.736 | M74: 43475.458 | O74: 0 | P74: 43475.458 | Q74: 13998.114 | R74: 0 | S74: 13998.114
A75: 68 | F75: 1509 | H75: Резерв за коштами на вимогу в інших банках | I75: П | J75: 46.52895 | K75: 32.98644 | L75: 13.54251 | M75: 61.95719 | O75: 46.56656 | P75: 15.39063 | Q75: -61.73694 | R75: -46.56656 | S75: -15.17038
A76: 69 | F76: Група 150 - Усього | J76: 2.9659865e+08 | K76: 14112767 | L76: 2.8248588e+08 | M76: 2.9345743e+08 | O76: 13875051 | P76: 2.7958238e+08 | Q76: 36470299 | R76: 815131.76 | S76: 35655167
A77: 70 | D77: 151 | F77: 1510 | H77: Депозити овернайт, що розміщені в інших банках, які обліковуються за амортизованою собівартістю | I77: А | J77: 9663663.6 | K77: 0 | L77: 9663663.6 | M77: 9535651.8 | O77: 0 | P77: 9535651.8 | Q77: 425323.25 | R77: 0 | S77: 425323.25
A78: 71 | F78: 1513 | H78: Строкові вклади (депозити), що розміщені в інших банках, які обліковуються за амортизованою собівартістю | I78: А | J78: 0 | K78: 0 | L78: 0 | M78: 0 | O78: 0 | P78: 0 | Q78: 0 | R78: 0 | S78: 0
A79: 72 | F79: 1516 | H79: Неамортизована премія/дисконт за строковими вкладами (депозитами), що розміщені в інших банках, які обліковуються за амортизованою собівартістю | I79: А | J79: 0 | K79: 0 | L79: 0 | M79: 0 | O79: 0 | P79: 0 | Q79: 0 | R79: 0 | S79: 0
A80: 73 | I80: П | J80: 0 | K80: 0 | L80: 0 | M80: 0 | O80: 0 | P80: 0 | Q80: 0 | R80: 0 | S80: 0
A81: 74 | F81: 1518 | H81: Нараховані доходи за строковими вкладами (депозитами), що розміщені в інших банках, які обліковуються за амортизованою собівартістю | I81: А | J81: 141.9277 | K81: 0 | L81: 141.9277 | M81: 140.96597 | O81: 0 | P81: 140.96597 | Q81: 141.52943 | R81: 0 | S81: 141.52943
A82: 75 | F82: 1519 | H82: Резерв за строковими вкладами (депозитами), що розміщені в інших банках, які обліковуються за амортизованою собівартістю | I82: П | J82: 0.02792 | K82: 0 | L82: 0.02792 | M82: 0.03981 | O82: 0 | P82: 0.03981 | Q82: -0.03932 | R82: 0 | S82: -0.03932
A83: 76 | F83: Група 151 - Усього | J83: 9663805.5 | K83: 0 | L83: 9663805.5 | M83: 9535792.8 | O83: 0 | P83: 9535792.8 | Q83: 425464.74 | R83: 0 | S83: 425464.74
A84: 77 | D84: 152 | F84: 1521 | H84: Кредити овернайт, що надані іншим банкам,які обліковуються за амортизованою собівартістю | I84: А | J84: 35920068 | K84: 0 | L84: 35920068 | M84: 35920068 | O84: 0 | P84: 35920068 | Q84: 0 | R84: 0 | S84: 0
A85: 78 | F85: 1522 | H85: Кредити, що надані іншим банкам за операціями репо, які обліковуються за амортизованою собівартістю | I85: А | J85: 0 | K85: 0 | L85: 0 | M85: 0 | O85: 0 | P85: 0 | Q85: 0 | R85: 0 | S85: 0
A86: 79 | F86: 1524 | H86: Інші кредити, що надані іншим банкам, які обліковуються за амортизованою собівартістю | I86: А | J86: 6287858.8 | K86: 0 | L86: 6287858.8 | M86: 3573439.4 | O86: 79683 | P86: 3493756.4 | Q86: 8508398.1 | R86: 2286431.7 | S86: 6221966.4
A87: 80 | F87: 1526 | H87: Неамортизована премія/дисконт за кредитами, що надані іншим банкам, які обліковуються за амортизованою собівартістю | I87: А | J87: 0 | K87: 0 | L87: 0 | M87: 0 | O87: 0 | P87: 0 | Q87: 0 | R87: 0 | S87: 0
A88: 81 | I88: П | J88: 0 | K88: 0 | L88: 0 | M88: 0 | O88: 0 | P88: 0 | Q88: 0 | R88: 0 | S88: 0
A89: 82 | F89: 1528 | H89: Нараховані доходи за кредитами, що надані іншим банкам, які обліковуються за амортизованою собівартістю | I89: А | J89: 26506.098 | K89: 12675.542 | L89: 13830.556 | M89: 18249.765 | O89: 5221.9654 | P89: 13027.8 | Q89: 32082.708 | R89: 25171.213 | S89: 6911.4955
A90: 83 | F90: 1529 | H90: Резерв за кредитами, що надані іншим банкам, які обліковуються за амортизованою собівартістю | I90: П | J90: 48.43553 | K90: 44.17571 | L90: 4.25982 | M90: 69.80887 | O90: 43.23189 | P90: 26.57698 | Q90: -69.73919 | R90: -43.23189 | S90: -26.5073
A91: 84 | F91: Група 152 - Усього | J91: 42234482 | K91: 12719.718 | L91: 42221762 | M91: 39511827 | O91: 84948.197 | P91: 39426879 | Q91: 8540411.1 | R91: 2311559.7 | S91: 6228851.4
A92: 85 | D92: Розділ 15 - Усього | J92: 3.4849693e+08 | K92: 14125487 | L92: 3.3437145e+08 | M92: 3.4250505e+08 | O92: 13959999 | P92: 3.2854505e+08 | Q92: 45436175 | R92: 3126691.4 | S92: 42309484
A93: 86 | C93: 16 | D93: 160 | F93: 1600 | H93: Кореспондентські рахунки інших банків | I93: А | J93: 684404.31 | K93: 456077.81 | L93: 228326.5 | M93: 573514.65 | O93: 345982.78 | P93: 227531.88 | Q93: 0 | R93: 0 | S93: 0
A94: 87 | F94: Група 160 - Усього | J94: 684404.31 | K94: 456077.81 | L94: 228326.5 | M94: 573514.65 | O94: 345982.78 | P94: 227531.88 | Q94: 0 | R94: 0 | S94: 0
A95: 88 | D95: Розділ 16 - Усього | J95: 684404.31 | K95: 456077.81 | L95: 228326.5 | M95: 573514.65 | O95: 345982.78 | P95: 227531.88 | Q95: 0 | R95: 0 | S95: 0
A96: 89 | C96: 18 | D96: 181 | F96: 1811 | H96: Дебіторська заборгованість за операціями з готівкою | I96: А | J96: 29526423 | K96: 13607364 | L96: 15919059 | M96: 29811047 | O96: 13607364 | P96: 16203683 | Q96: 1214187.8 | R96: 0 | S96: 1214187.8
A97: 90 | F97: 1819 | H97: Інша дебіторська заборгованість за операціями з банками | I97: А | J97: 1766631.5 | K97: 1766631.5 | L97: 0 | M97: 1780753.9 | O97: 1780753.9 | P97: 0 | Q97: 10877.563 | R97: 10877.563 | S97: 0
A98: 91 | F98: Група 181 - Усього | J98: 31293055 | K98: 15373996 | L98: 15919059 | M98: 31591801 | O98: 15388118 | P98: 16203683 | Q98: 1225065.4 | R98: 10877.563 | S98: 1214187.8
A99: 92 | D99: 183 | F99: 1832 | H99: Кошти банків у розрахунках | I99: А | J99: 93543.743 | K99: 0 | L99: 93543.743 | M99: 71036.225 | O99: 0 | P99: 71036.225 | Q99: 1713027.2 | R99: 100 | S99: 1712927.2
A100: 93 | F100: 1839 | H100: Резерви за коштами банків у розрахунках | I100: П | J100: 0.67315 | K100: 0 | L100: 0.67315 | M100: 0.68032 | O100: 0 | P100: 0.68032 | Q100: -0.66784 | R100: 0 | S100: -0.66784
...

Sheet  43АТ "АЛЬТБАНК" 
A1: Зміст
B2: Оборотно-сальдовий баланс банку АТ "АЛЬТБАНК" за станом на 01.03.2026
B3: (тис грн)
A4: Номер з/п | B4: Клас/ розділ/ група/ рахунок | I4: Актив/ пасив | J4: Обороти за місяць | Q4: Сальдо
J5: дебет | M5: кредит | Q5: усього | R5: НВ | S5: ІВ
B6: номер | F6: назва | J6: усього | K6: НВ | L6: ІВ | M6: усього | O6: НВ | P6: ІВ
A7: 1 | B7: 2 | F7: 3 | I7: 4 | J7: 5 | K7: 6 | L7: 7 | M7: 8 | O7: 9 | P7: 10 | Q7: 11 | R7: 12 | S7: 13
A8: 1 | B8: Балансові рахунки
A9: 2 | B9: Активи
A10: 3 | B10: Класи 1 - 4
A11: 4 | B11: Клас 1 | C11: 10 | D11: 100 | F11: 1001 | H11: Банкноти та монети в касі банку | I11: А | J11: 15780.663 | K11: 10074.813 | L11: 5705.8503 | M11: 16786.722 | O11: 10262.014 | P11: 6524.7089 | Q11: 9787.4509 | R11: 1731.1779 | S11: 8056.273
A12: 5 | F12: 1002 | H12: Банкноти та монети в касі відділень банку | I12: А | J12: 42294.112 | K12: 28145.647 | L12: 14148.465 | M12: 38117.69 | O12: 26934.88 | P12: 11182.811 | Q12: 22716.854 | R12: 8197.072 | S12: 14519.782
A13: 6 | F13: 1004 | H13: Банкноти та монети в банкоматах | I13: А | J13: 14808.29 | K13: 14808.29 | L13: 0 | M13: 13817.26 | O13: 13817.26 | P13: 0 | Q13: 6979.94 | R13: 6979.94 | S13: 0
A14: 7 | F14: 1005 | H14: Банкноти та монети, інкасовані до перерахування | I14: А | J14: 0 | K14: 0 | L14: 0 | M14: 0 | O14: 0 | P14: 0 | Q14: 0 | R14: 0 | S14: 0
A15: 8 | F15: 1006 | H15: Банкноти та монети на зберіганні в інкасаторській компанії | I15: А | J15: 0 | K15: 0 | L15: 0 | M15: 0 | O15: 0 | P15: 0 | Q15: 0 | R15: 0 | S15: 0
A16: 9 | F16: 1007 | H16: Банкноти та монети в дорозі | I16: А | J16: 12267.49 | K16: 10755.56 | L16: 1511.9305 | M16: 12267.49 | O16: 10755.56 | P16: 1511.9305 | Q16: 0 | R16: 0 | S16: 0
A17: 10 | F17: Група 100 - Усього | J17: 85150.555 | K17: 63784.31 | L17: 21366.246 | M17: 80989.163 | O17: 61769.713 | P17: 19219.45 | Q17: 39484.245 | R17: 16908.19 | S17: 22576.055
A18: 11 | D18: 101 | F18: 1011 | H18: Дорожні чеки в касі банку | I18: А | J18: 0 | K18: 0 | L18: 0 | M18: 0 | O18: 0 | P18: 0 | Q18: 0 | R18: 0 | S18: 0
A19: 12 | F19: 1012 | H19: Дорожні чеки в касі відділень банку | I19: А | J19: 0 | K19: 0 | L19: 0 | M19: 0 | O19: 0 | P19: 0 | Q19: 0 | R19: 0 | S19: 0
A20: 13 | F20: Група 101 - Усього | J20: 0 | K20: 0 | L20: 0 | M20: 0 | O20: 0 | P20: 0 | Q20: 0 | R20: 0 | S20: 0
A21: 14 | D21: 109 | F21: 1090 | H21: Резерви за готівковими коштами, наявність яких є непідтвердженою | I21: П | J21: 0 | K21: 0 | L21: 0 | M21: 0 | O21: 0 | P21: 0 | Q21: 0 | R21: 0 | S21: 0
A22: 15 | F22: Група 109 - Усього | J22: 0 | K22: 0 | L22: 0 | M22: 0 | O22: 0 | P22: 0 | Q22: 0 | R22: 0 | S22: 0
A23: 16 | D23: Розділ 10 - Усього | J23: 85150.555 | K23: 63784.31 | L23: 21366.246 | M23: 80989.163 | O23: 61769.713 | P23: 19219.45 | Q23: 39484.245 | R23: 16908.19 | S23: 22576.055
A24: 17 | C24: 11 | D24: 110 | F24: 1101 | H24: Банківські метали в банку | I24: А | J24: 0 | K24: 0 | L24: 0 | M24: 0 | O24: 0 | P24: 0 | Q24: 0 | R24: 0 | S24: 0
A25: 18 | F25: 1102 | H25: Банківські метали у відділенні банку | I25: А | J25: 0 | K25: 0 | L25: 0 | M25: 0 | O25: 0 | P25: 0 | Q25: 0 | R25: 0 | S25: 0
A26: 19 | F26: 1107 | H26: Банківські метали в дорозі | I26: А | J26: 0 | K26: 0 | L26: 0 | M26: 0 | O26: 0 | P26: 0 | Q26: 0 | R26: 0 | S26: 0
A27: 20 | F27: Група 110 - Усього | J27: 0 | K27: 0 | L27: 0 | M27: 0 | O27: 0 | P27: 0 | Q27: 0 | R27: 0 | S27: 0
A28: 21 | D28: 119 | F28: 1190 | H28: Резерви за банківськими металами, наявність яких є непідтвердженою | I28: П | J28: 0 | K28: 0 | L28: 0 | M28: 0 | O28: 0 | P28: 0 | Q28: 0 | R28: 0 | S28: 0
A29: 22 | F29: Група 119 - Усього | J29: 0 | K29: 0 | L29: 0 | M29: 0 | O29: 0 | P29: 0 | Q29: 0 | R29: 0 | S29: 0
A30: 23 | D30: Розділ 11 - Усього | J30: 0 | K30: 0 | L30: 0 | M30: 0 | O30: 0 | P30: 0 | Q30: 0 | R30: 0 | S30: 0
A31: 24 | C31: 12 | D31: 120 | F31: 1200 | H31: Кореспондентський рахунок банку в Національному банку України | I31: А | J31: 6675209.8 | K31: 6675209.8 | L31: 0 | M31: 6788586 | O31: 6788586 | P31: 0 | Q31: 124950.28 | R31: 124950.28 | S31: 0
A32: 25 | F32: 1202 | H32: Кошти банків за рахунками умовного зберігання (ескроу) у Національному банку України | I32: А | J32: 0 | K32: 0 | L32: 0 | M32: 0 | O32: 0 | P32: 0 | Q32: 0 | R32: 0 | S32: 0
A33: 26 | F33: 1205 | H33: Кошти банків для забезпечення виконання зобов’язань перед Національним банком України за кредитами, наданими банкам, та операціями своп процентної ставки | I33: А | J33: 0 | K33: 0 | L33: 0 | M33: 0 | O33: 0 | P33: 0 | Q33: 0 | R33: 0 | S33: 0
A34: 27 | F34: 1208 | H34: Нараховані доходи за коштами на вимогу в Національному банку України | I34: А | J34: 0 | K34: 0 | L34: 0 | M34: 0 | O34: 0 | P34: 0 | Q34: 0 | R34: 0 | S34: 0
A35: 28 | F35: Група 120 - Усього | J35: 6675209.8 | K35: 6675209.8 | L35: 0 | M35: 6788586 | O35: 6788586 | P35: 0 | Q35: 124950.28 | R35: 124950.28 | S35: 0
A36: 29 | D36: Розділ 12 - Усього | J36: 6675209.8 | K36: 6675209.8 | L36: 0 | M36: 6788586 | O36: 6788586 | P36: 0 | Q36: 124950.28 | R36: 124950.28 | S36: 0
A37: 30 | C37: 14 | D37: 140 | F37: 1400 | H37: Облігації внутрішньої державної позики, що рефінансуються Національним банком України, які обліковуються за справедливою вартістю через прибутки/збитки | I37: А | J37: 0 | K37: 0 | L37: 0 | M37: 0 | O37: 0 | P37: 0 | Q37: 0 | R37: 0 | S37: 0
A38: 31 | F38: 1405 | H38: Переоцінка боргових цінних паперів, що рефінансуються Національним банком України, які обліковуються за справедливою вартістю через прибутки/збитки | I38: А | J38: 0 | K38: 0 | L38: 0 | M38: 0 | O38: 0 | P38: 0 | Q38: 0 | R38: 0 | S38: 0
A39: 32 | I39: П | J39: 0 | K39: 0 | L39: 0 | M39: 0 | O39: 0 | P39: 0 | Q39: 0 | R39: 0 | S39: 0
A40: 33 | F40: 1406 | H40: Неамортизована премія/дисконт за борговими цінними паперами, що рефінансуються Національним банком України, які обліковуються за справедливою вартістю через прибутки/збитки | I40: А | J40: 0 | K40: 0 | L40: 0 | M40: 0 | O40: 0 | P40: 0 | Q40: 0 | R40: 0 | S40: 0
A41: 34 | I41: П | J41: 0 | K41: 0 | L41: 0 | M41: 0 | O41: 0 | P41: 0 | Q41: 0 | R41: 0 | S41: 0
A42: 35 | F42: 1408 | H42: Нараховані доходи за борговими цінними паперами, що рефінансуються Національним банком України, які обліковуються за справедливою вартістю через прибутки/збитки | I42: А | J42: 0 | K42: 0 | L42: 0 | M42: 0 | O42: 0 | P42: 0 | Q42: 0 | R42: 0 | S42: 0
A43: 36 | F43: Група 140 - Усього | J43: 0 | K43: 0 | L43: 0 | M43: 0 | O43: 0 | P43: 0 | Q43: 0 | R43: 0 | S43: 0
A44: 37 | D44: 141 | F44: 1410 | H44: Облігації внутрішньої державної позики, що рефінансуються Національним банком України, які обліковуються за справедливою вартістю через інший сукупний дохід | I44: А | J44: 596149.4 | K44: 355395 | L44: 240754.4 | M44: 926752.75 | O44: 683971 | P44: 242781.75 | Q44: 578874.57 | R44: 545204 | S44: 33670.568
A45: 38 | F45: 1411 | H45: Облігації зовнішньої державної позики, що рефінансуються Національним банком України, які обліковуються за справедливою вартістю через інший сукупний дохід | I45: А | J45: 0 | K45: 0 | L45: 0 | M45: 0 | O45: 0 | P45: 0 | Q45: 0 | R45: 0 | S45: 0
A46: 39 | F46: 1412 | H46: Боргові цінні папери органів державної влади та місцевого самоврядування, що рефінансуються Національним банком України, які обліковуються за справедливою вартістю через інший сукупний дохід | I46: А | J46: 0 | K46: 0 | L46: 0 | M46: 0 | O46: 0 | P46: 0 | Q46: 0 | R46: 0 | S46: 0
A47: 40 | F47: 1415 | H47: Переоцінка боргових цінних паперів, що рефінансуються Національним банком України, які обліковуються за справедливою вартістю через інший сукупний дохід | I47: А | J47: 160450.94 | K47: 158645.68 | L47: 1805.2637 | M47: 172455.78 | O47: 170558.14 | P47: 1897.6393 | Q47: 16683.265 | R47: 16472.784 | S47: 210.48101
A48: 41 | I48: П | J48: 0 | K48: 0 | L48: 0 | M48: 0 | O48: 0 | P48: 0 | Q48: -5349.9405 | R48: -5349.9405 | S48: 0
A49: 42 | F49: 1416 | H49: Неамортизована премія/дисконт за борговими цінними паперами, що рефінансуються Національним банком України, які обліковуються за справедливою вартістю через інший сукупний дохід | I49: А | J49: 12008.696 | K49: 11232.921 | L49: 775.77509 | M49: 9988.845 | O49: 9253.3006 | P49: 735.54437 | Q49: 8369.0508 | R49: 8313.1503 | S49: 55.90048
A50: 43 | I50: П | J50: 0 | K50: 0 | L50: 0 | M50: 0 | O50: 0 | P50: 0 | Q50: -223.37102 | R50: -223.32969 | S50: -0.04133
A51: 44 | F51: 1418 | H51: Нараховані доходи за борговими цінними паперами, що рефінансуються Національним банком України, які обліковуються за справедливою вартістю через інший сукупний дохід | I51: А | J51: 29830.943 | K51: 28735.653 | L51: 1095.2898 | M51: 54722.499 | O51: 53507.842 | P51: 1214.6571 | Q51: 22258.528 | R51: 22010.488 | S51: 248.03979
A52: 45 | F52: 1419 | H52: Резерв за борговими цінними паперами,що рефінансуються Національним банком України, які обліковуються за справедливою вартістю через інший сукупний дохід | I52: П | J52: 0 | K52: 0 | L52: 0 | M52: 0 | O52: 0 | P52: 0 | Q52: 0 | R52: 0 | S52: 0
A53: 46 | F53: Група 141 - Усього | J53: 798439.98 | K53: 554009.25 | L53: 244430.73 | M53: 1163919.9 | O53: 917290.28 | P53: 246629.59 | Q53: 620612.1 | R53: 586427.15 | S53: 34184.948
A54: 47 | D54: 142 | F54: 1420 | H54: Облігації внутрішньої державної позики, що рефінансуються Національним банком України, які обліковуються за амортизованою собівартістю | I54: А | J54: 0 | K54: 0 | L54: 0 | M54: 0 | O54: 0 | P54: 0 | Q54: 0 | R54: 0 | S54: 0
A55: 48 | F55: 1426 | H55: Неамортизована премія/дисконт за борговими цінними паперами, що рефінансуються Національним банком України, які обліковуються за амортизованою собівартістю | I55: А | J55: 0 | K55: 0 | L55: 0 | M55: 0 | O55: 0 | P55: 0 | Q55: 0 | R55: 0 | S55: 0
A56: 49 | I56: П | J56: 0 | K56: 0 | L56: 0 | M56: 0 | O56: 0 | P56: 0 | Q56: 0 | R56: 0 | S56: 0
A57: 50 | F57: 1428 | H57: Нараховані доходи за борговими цінними паперами, що рефінансуються Національним банком України, які обліковуються за амортизованою собівартістю | I57: А | J57: 0 | K57: 0 | L57: 0 | M57: 0 | O57: 0 | P57: 0 | Q57: 0 | R57: 0 | S57: 0
A58: 51 | F58: 1429 | H58: Резерв за борговими цінними паперами,що рефінансуються Національним банком України, які обліковуються за амортизованою собівартістю | I58: П | J58: 0 | K58: 0 | L58: 0 | M58: 0 | O58: 0 | P58: 0 | Q58: 0 | R58: 0 | S58: 0
A59: 52 | F59: Група 142 - Усього | J59: 0 | K59: 0 | L59: 0 | M59: 0 | O59: 0 | P59: 0 | Q59: 0 | R59: 0 | S59: 0
A60: 53 | D60: 143 | F60: 1430 | H60: Депозитні сертифікати Національного банку України, розміщені в банках України, що обліковуються за справедливою вартістю через інший сукупний дохід | I60: А | J60: 23000 | K60: 23000 | L60: 0 | M60: 0 | O60: 0 | P60: 0 | Q60: 98000 | R60: 98000 | S60: 0
A61: 54 | F61: 1435 | H61: Переоцінка депозитних сертифікатів Національного банку України, розміщених у банках України, що обліковуються за справедливою вартістю через інший сукупний дохід | I61: А | J61: 350.88782 | K61: 350.88782 | L61: 0 | M61: 605.1738 | O61: 605.1738 | P61: 0 | Q61: 350.88782 | R61: 350.88782 | S61: 0
A62: 55 | I62: П | J62: 0 | K62: 0 | L62: 0 | M62: 0 | O62: 0 | P62: 0 | Q62: -25.00244 | R62: -25.00244 | S62: 0
A63: 56 | F63: 1436 | H63: Неамортизована премія/дисконт за депозитними сертифікатами Національного банку України, розміщеними в банках України, що обліковуються за справедливою вартістю через інший сукупний дохід | I63: А | J63: 0 | K63: 0 | L63: 0 | M63: 0 | O63: 0 | P63: 0 | Q63: 0 | R63: 0 | S63: 0
A64: 57 | I64: П | J64: 0 | K64: 0 | L64: 0 | M64: 0 | O64: 0 | P64: 0 | Q64: 0 | R64: 0 | S64: 0
A65: 58 | F65: 1438 | H65: Нараховані доходи за депозитними сертифікатами Національного банку України, розміщеними в банках України, що обліковуються за справедливою вартістю через інший сукупний дохід | I65: А | J65: 1198.0686 | K65: 1198.0686 | L65: 0 | M65: 0 | O65: 0 | P65: 0 | Q65: 1549.4385 | R65: 1549.4385 | S65: 0
A66: 59 | F66: Група 143 - Усього | J66: 24548.956 | K66: 24548.956 | L66: 0 | M66: 605.1738 | O66: 605.1738 | P66: 0 | Q66: 99875.324 | R66: 99875.324 | S66: 0
A67: 60 | D67: 144 | F67: 1440 | H67: Депозитні сертифікати Національного банку України, розміщені в банках України, що обліковуються за амортизованою собівартістю | I67: А | J67: 1719000 | K67: 1719000 | L67: 0 | M67: 1862000 | O67: 1862000 | P67: 0 | Q67: 259000 | R67: 259000 | S67: 0
A68: 61 | F68: 1446 | H68: Неамортизована премія/дисконт за депозитними сертифікатами Національного банку України, розміщеними в банках України, що обліковуються за амортизованою собівартістю | I68: А | J68: 0 | K68: 0 | L68: 0 | M68: 0 | O68: 0 | P68: 0 | Q68: 0 | R68: 0 | S68: 0
A69: 62 | I69: П | J69: 0 | K69: 0 | L69: 0 | M69: 0 | O69: 0 | P69: 0 | Q69: 0 | R69: 0 | S69: 0
A70: 63 | F70: 1448 | H70: Нараховані доходи за депозитними сертифікатами Національного банку України, розміщеними в банках України, що обліковуються за амортизованою собівартістю | I70: А | J70: 6553.7144 | K70: 6553.7144 | L70: 0 | M70: 12870.084 | O70: 12870.084 | P70: 0 | Q70: 5769.7128 | R70: 5769.7128 | S70: 0
A71: 64 | F71: Група 144 - Усього | J71: 1725553.7 | K71: 1725553.7 | L71: 0 | M71: 1874870.1 | O71: 1874870.1 | P71: 0 | Q71: 264769.71 | R71: 264769.71 | S71: 0
A72: 65 | D72: Розділ 14 - Усього | J72: 2548542.7 | K72: 2304111.9 | L72: 244430.73 | M72: 3039395.1 | O72: 2792765.5 | P72: 246629.59 | Q72: 985257.14 | R72: 951072.19 | S72: 34184.948
A73: 66 | C73: 15 | D73: 150 | F73: 1500 | H73: Кореспондентські рахунки, що відкриті в інших банках | I73: А | J73: 3447255.5 | K73: 143755.3 | L73: 3303500.2 | M73: 3212067.5 | O73: 143821.28 | P73: 3068246.3 | Q73: 335218.05 | R73: 134.97247 | S73: 335083.08
A74: 67 | F74: 1508 | H74: Нараховані доходи за коштами на вимогу в інших банках | I74: А | J74: 0 | K74: 0 | L74: 0 | M74: 0 | O74: 0 | P74: 0 | Q74: 0 | R74: 0 | S74: 0
A75: 68 | F75: 1509 | H75: Резерв за коштами на вимогу в інших банках | I75: П | J75: 1.79982 | K75: 0.02822 | L75: 1.7716 | M75: 36.45217 | O75: 0 | P75: 36.45217 | Q75: -1399.3889 | R75: -0.04052 | S75: -1399.3484
A76: 69 | F76: Група 150 - Усього | J76: 3447257.3 | K76: 143755.33 | L76: 3303502 | M76: 3212104 | O76: 143821.28 | P76: 3068282.7 | Q76: 333818.66 | R76: 134.93195 | S76: 333683.73
A77: 70 | D77: 151 | F77: 1510 | H77: Депозити овернайт, що розміщені в інших банках, які обліковуються за амортизованою собівартістю | I77: А | J77: 0 | K77: 0 | L77: 0 | M77: 0 | O77: 0 | P77: 0 | Q77: 0 | R77: 0 | S77: 0
A78: 71 | F78: 1513 | H78: Строкові вклади (депозити), що розміщені в інших банках, які обліковуються за амортизованою собівартістю | I78: А | J78: 0 | K78: 0 | L78: 0 | M78: 0 | O78: 0 | P78: 0 | Q78: 0 | R78: 0 | S78: 0
A79: 72 | F79: 1516 | H79: Неамортизована премія/дисконт за строковими вкладами (депозитами), що розміщені в інших банках, які обліковуються за амортизованою собівартістю | I79: А | J79: 0 | K79: 0 | L79: 0 | M79: 0 | O79: 0 | P79: 0 | Q79: 0 | R79: 0 | S79: 0
A80: 73 | I80: П | J80: 0 | K80: 0 | L80: 0 | M80: 0 | O80: 0 | P80: 0 | Q80: 0 | R80: 0 | S80: 0
A81: 74 | F81: 1518 | H81: Нараховані доходи за строковими вкладами (депозитами), що розміщені в інших банках, які обліковуються за амортизованою собівартістю | I81: А | J81: 0 | K81: 0 | L81: 0 | M81: 0 | O81: 0 | P81: 0 | Q81: 0 | R81: 0 | S81: 0
A82: 75 | F82: 1519 | H82: Резерв за строковими вкладами (депозитами), що розміщені в інших банках, які обліковуються за амортизованою собівартістю | I82: П | J82: 0 | K82: 0 | L82: 0 | M82: 0 | O82: 0 | P82: 0 | Q82: 0 | R82: 0 | S82: 0
A83: 76 | F83: Група 151 - Усього | J83: 0 | K83: 0 | L83: 0 | M83: 0 | O83: 0 | P83: 0 | Q83: 0 | R83: 0 | S83: 0
A84: 77 | D84: 152 | F84: 1521 | H84: Кредити овернайт, що надані іншим банкам,які обліковуються за амортизованою собівартістю | I84: А | J84: 496605.4 | K84: 0 | L84: 496605.4 | M84: 496605.4 | O84: 0 | P84: 496605.4 | Q84: 0 | R84: 0 | S84: 0
A85: 78 | F85: 1522 | H85: Кредити, що надані іншим банкам за операціями репо, які обліковуються за амортизованою собівартістю | I85: А | J85: 99860.212 | K85: 99860.212 | L85: 0 | M85: 0 | O85: 0 | P85: 0 | Q85: 99860.212 | R85: 99860.212 | S85: 0
A86: 79 | F86: 1524 | H86: Інші кредити, що надані іншим банкам, які обліковуються за амортизованою собівартістю | I86: А | J86: 460066.46 | K86: 0 | L86: 460066.46 | M86: 460066.46 | O86: 0 | P86: 460066.46 | Q86: 0 | R86: 0 | S86: 0
A87: 80 | F87: 1526 | H87: Неамортизована премія/дисконт за кредитами, що надані іншим банкам, які обліковуються за амортизованою собівартістю | I87: А | J87: 0 | K87: 0 | L87: 0 | M87: 0 | O87: 0 | P87: 0 | Q87: 0 | R87: 0 | S87: 0
A88: 81 | I88: П | J88: 0 | K88: 0 | L88: 0 | M88: 0 | O88: 0 | P88: 0 | Q88: 0 | R88: 0 | S88: 0
A89: 82 | F89: 1528 | H89: Нараховані доходи за кредитами, що надані іншим банкам, які обліковуються за амортизованою собівартістю | I89: А | J89: 370.12686 | K89: 174.59262 | L89: 195.53424 | M89: 195.53424 | O89: 0 | P89: 195.53424 | Q89: 174.59262 | R89: 174.59262 | S89: 0
A90: 83 | F90: 1529 | H90: Резерв за кредитами, що надані іншим банкам, які обліковуються за амортизованою собівартістю | I90: П | J90: 0 | K90: 0 | L90: 0 | M90: 0 | O90: 0 | P90: 0 | Q90: 0 | R90: 0 | S90: 0
A91: 84 | F91: Група 152 - Усього | J91: 1056902.2 | K91: 100034.8 | L91: 956867.39 | M91: 956867.39 | O91: 0 | P91: 956867.39 | Q91: 100034.8 | R91: 100034.8 | S91: 0
A92: 85 | D92: Розділ 15 - Усього | J92: 4504159.5 | K92: 243790.13 | L92: 4260369.4 | M92: 4168971.4 | O92: 143821.28 | P92: 4025150.1 | Q92: 433853.46 | R92: 100169.74 | S92: 333683.73
A93: 86 | C93: 16 | D93: 160 | F93: 1600 | H93: Кореспондентські рахунки інших банків | I93: А | J93: 0 | K93: 0 | L93: 0 | M93: 0 | O93: 0 | P93: 0 | Q93: 0 | R93: 0 | S93: 0
A94: 87 | F94: Група 160 - Усього | J94: 0 | K94: 0 | L94: 0 | M94: 0 | O94: 0 | P94: 0 | Q94: 0 | R94: 0 | S94: 0
A95: 88 | D95: Розділ 16 - Усього | J95: 0 | K95: 0 | L95: 0 | M95: 0 | O95: 0 | P95: 0 | Q95: 0 | R95: 0 | S95: 0
A96: 89 | C96: 18 | D96: 181 | F96: 1811 | H96: Дебіторська заборгованість за операціями з готівкою | I96: А | J96: 15080.89 | K96: 12929.3 | L96: 2151.59 | M96: 15080.89 | O96: 12929.3 | P96: 2151.59 | Q96: 0 | R96: 0 | S96: 0
A97: 90 | F97: 1819 | H97: Інша дебіторська заборгованість за операціями з банками | I97: А | J97: 1427662.9 | K97: 223230.39 | L97: 1204432.5 | M97: 1427662.9 | O97: 223230.39 | P97: 1204432.5 | Q97: 0 | R97: 0 | S97: 0
A98: 91 | F98: Група 181 - Усього | J98: 1442743.7 | K98: 236159.69 | L98: 1206584.1 | M98: 1442743.7 | O98: 236159.69 | P98: 1206584.1 | Q98: 0 | R98: 0 | S98: 0
A99: 92 | D99: 183 | F99: 1832 | H99: Кошти банків у розрахунках | I99: А | J99: 4935.4948 | K99: 2022.0865 | L99: 2913.4083 | M99: 6751.7447 | O99: 5071.8127 | P99: 1679.9319 | Q99: 33419.232 | R99: 17306.994 | S99: 16112.238
A100: 93 | F100: 1839 | H100: Резерви за коштами банків у розрахунках | I100: П | J100: 13.79284 | K100: 13.22612 | L100: 0.56672 | M100: 5.50049 | O100: 0 | P100: 5.50049 | Q100: -134.72153 | R100: -70.27276 | S100: -64.44877
...
