Workbook

Sheet Index
C2: Оборотно-сальдовий баланс банку* | D2: відповідно до Додатку 1 до постанови Правління Національного банку України
D3: від 15 березня 2018 року № 11 "Про встановлення переліку інформації, що підлягає обов'язковому опублікуванню банками України" (зі змінами)
D4: за даними статистичної звітності з файлів 02X "Дані про обороти та залишки на рахунках".
A5: NKB | B5: Порядковий номер | C5: Назва банку | D5: МФО | E5: ПРОЦЕНТИ ЗА ДЕПОЗИТНИМИ СЕРТИФІКАТАМИ (ДС), тис. грн | F5: ПРОЦЕНТИ ЗА ОВДП (ОВДП), тис.грн | G5: ПРОЦЕНТИ ЗА КРЕДИТАМИ ЗДУ | H5: ПРОЦЕНТИ ЗА КРЕДИТАМИ БІЗНЕСУ | I5: ПРОЦЕНТИ ЗА КРЕДИТАМИ НАСЕЛЕННЮ | J5: ПРОЦЕНТНІ ДОХОДИ ВСЬОГО (ПД), тис. грн | K5: ДС/ПД, % | L5: ДС до підсумку, % | M5: (ДС+ОВДП)/ПД, % | N5: ОВДП/ПД, % | O5: ОВДП до підсумку | P5: Обсяг ДС дебит (середні, поділено на кількість банк.днів) | Q5: Обсяг ДС кредит (середні, поділено на кількість банк.днів) | R5: Кошти в НБУ (кор.рахунок) (кредит) (код 1200) | S5: Кошти в НБУ (УСЬОГО) (кредит) (розділ 12) | T5: Проценти за поточними вкладами ДГ (код 7040) | U5: Проценти за строковими вкладами ДГ (код 7041) | V5: Кредити субʼєктам господарювання (р.20, р.23, 260) | W5: Кредити ЗДУ (р.21) | X5: Кредити фізичним особам (р. 22, 24, 262) | Y5: Кредити небанківським установам (265) | Z5: Прибуток звітного року (5040) | AA5: Збиток звітного року (5041) | AB5: Податок на прибуток (7900) | AC5: Інші податки (741) | AD5: Відрахування в резерви (770) | AE5: Загальні доходи (6) | AF5: Загальні витрати (7)
A6: 2 | B6: 1 | C6: АТ "Укрексімбанк" | D6: 322313 | E6: =' 2АТ "Укрексімбанк" '!$P$1139 | F6: =' 2АТ "Укрексімбанк" '!$P$1138 | G6: =' 2АТ "Укрексімбанк" '!$P$1150 | H6: =' 2АТ "Укрексімбанк" '!$P$1148 | I6: =' 2АТ "Укрексімбанк" '!$P$1149 | J6: =' 2АТ "Укрексімбанк" '!$P$1144 | K6: =IFERROR(E6/J6*100,0) | L6: =IFERROR(E6/SUM(E6:E6)*100,0) | M6: =IFERROR((E6+F6)/J6*100,0) | N6: =IFERROR(F6/J6*100,0) | O6: =IFERROR(F6/SUM(F6:F6)*100,0) | P6: =' 2АТ "Укрексімбанк" '!$J$1140 | Q6: =' 2АТ "Укрексімбанк" '!$N$1141 | R6: =' 2АТ "Укрексімбанк" '!$M$1142 | S6: =' 2АТ "Укрексімбанк" '!$M$1143 | T6: =' 2АТ "Укрексімбанк" '!$P$1151 | U6: =' 2АТ "Укрексімбанк" '!$P$1152 | V6: =' 2АТ "Укрексімбанк" '!$P$1154 | W6: =' 2АТ "Укрексімбанк" '!$P$1155 | X6: =' 2АТ "Укрексімбанк" '!$P$1156 | Y6: =' 2АТ "Укрексімбанк" '!$P$1157 | Z6: =' 2АТ "Укрексімбанк" '!$P$1158 | AA6: =' 2АТ "Укрексімбанк" '!$P$1159 | AB6: =' 2АТ "Укрексімбанк" '!$P$1160 | AC6: =' 2АТ "Укрексімбанк" '!$P$1161 | AD6: =' 2АТ "Укрексімбанк" '!$P$1162 | AE6: =' 2АТ "Укрексімбанк" '!$P$1163 | AF6: =' 2АТ "Укрексімбанк" '!$P$1164
A7: Всього | E7: =IFERROR(SUM(E6:E6),0) | F7: =IFERROR(SUM(F6:F6),0) | G7: =IFERROR(SUM(G6:G6),0) | H7: =IFERROR(SUM(H6:H6),0) | I7: =IFERROR(SUM(I6:I6),0) | J7: =IFERROR(SUM(J6:J6),0) | K7: =IFERROR(E7/J7*100,0) | L7: =IFERROR(E7/SUM(E6:E6)*100,0) | M7: =IFERROR((E7+F7)/J7*100,0) | N7: =IFERROR(F7/J7*100,0) | O7: =IFERROR(F7/SUM(F6:F6)*100,0) | P7: =IFERROR(SUM(P6:P6),0) | Q7: =IFERROR(SUM(Q6:Q6),0) | R7: =IFERROR(SUM(R6:R6),0) | S7: =IFERROR(SUM(S6:S6),0) | T7: =IFERROR(SUM(T6:T6),0) | U7: =IFERROR(SUM(U6:U6),0) | V7: =IFERROR(SUM(V6:V6),0) | W7: =IFERROR(SUM(W6:W6),0) | ... AF7: =IFERROR(SUM(AF6:AF6),0)
A8: Державні банки | E8: =IFERROR(SUM(E6),0) | F8: =IFERROR(SUM(F6),0) | G8: =IFERROR(SUM(G6),0) | H8: =IFERROR(SUM(H6),0) | I8: =IFERROR(SUM(I6),0) | J8: =IFERROR(SUM(J6),0) | K8: =IFERROR(E8/J8*100,0) | L8: =IFERROR(E8/E7*100,0) | M8: =IFERROR(SUM(M6),0) | N8: =IFERROR(SUM(N6),0) | O8: =IFERROR(F8/F7*100,0) | P8: =IFERROR(SUM(P6),0) | Q8: =IFERROR(SUM(Q6),0) | R8: =IFERROR(SUM(R6),0) | S8: =IFERROR(SUM(S6),0) | T8: =IFERROR(SUM(T6),0) | U8: =IFERROR(SUM(U6),0) | V8: =IFERROR(SUM(V6),0) | W8: =IFERROR(SUM(W6),0) | ... AF8: =IFERROR(SUM(AF6),0)
A9: Банки з іноземним капіталом | E9: =0 | F9: =0 | G9: =0 | H9: =0 | I9: =0 | J9: =0 | K9: =IFERROR(E9/J9*100,0) | L9: =IFERROR(E9/E7*100,0) | M9: =0 | N9: =0 | O9: =IFERROR(F9/F7*100,0) | P9: =0 | Q9: =0 | R9: =0 | S9: =0 | T9: =0 | U9: =0 | V9: =0 | W9: =0 | ... AF9: =0
A10: Банки з українським приватним капіталом | E10: =IFERROR(E7-E8-E9,0) | F10: =IFERROR(F7-F8-F9,0) | G10: =IFERROR(G7-G8-G9,0) | H10: =IFERROR(H7-H8-H9,0) | I10: =IFERROR(I7-I8-I9,0) | J10: =IFERROR(J7-J8-J9,0) | K10: =IFERROR(E10/J10*100,0) | L10: =IFERROR(E10/E7*100,0) | M10: =IFERROR(M7-M8-M9,0) | N10: =IFERROR(N7-N8-N9,0) | O10: =IFERROR(F10/F7*100,0) | P10: =IFERROR(P7-P8-P9,0) | Q10: =IFERROR(Q7-Q8-Q9,0) | R10: =IFERROR(R7-R8-R9,0) | S10: =IFERROR(S7-S8-S9,0) | T10: =IFERROR(T7-T8-T9,0) | U10: =IFERROR(U7-U8-U9,0) | V10: =IFERROR(V7-V8-V9,0) | W10: =IFERROR(W7-W8-W9,0) | ... AF10: =IFERROR(AF7-AF8-AF9,0)
B12: Категорія | C12: ДС/ПД, % | H12: Категорія | I12: ДС до підсумку, %
B13: =A8 | C13: =IFERROR(K8,0) | H13: =A8 | I13: =IFERROR(L8,0)
B14: =A9 | C14: =IFERROR(K9,0) | H14: =A9 | I14: =IFERROR(L9,0)
B15: =A10 | C15: =IFERROR(K10,0) | H15: =A10 | I15: =IFERROR(L10,0)

Sheet Indicator_Summary
A1: ПРОЦЕНТНІ ДОХОДИ банків
B2: млрд | C2: %
A3: Депозитні сертифікати | B3: =SUM(Index!E6:E6)/1000000 | C3: =B3/B8 * 100
A4: ОВДП | B4: =SUM(Index!F6:F6)/1000000 | C4: =B4/B8 * 100
A5: Кредити бізнесу | B5: =SUM(Index!H6:H6)/1000000 | C5: =B5/B8 * 100
A6: Кредити населенню | B6: =SUM(Index!I6:I6)/1000000 | C6: =B6/B8 * 100
A7: Інші процентні доходи | B7: =B8 - (B3 +B4 +B5 +B6) | C7: =B7/B8 * 100
A8: ВСЬОГО | B8: =SUM(Index!J6:J6)/1000000 | C8: 100

Sheet Pivot_Data
A1: bank_code | B1: bank_name | C1: bank_class | D1: id | E1: indicator | F1: name | G1: category | H1: debit_total | I1: debit_nc | J1: debit_ic | K1: credit_total | L1: credit_nc | M1: credit_ic | N1: balance_total | O1: balance_nc | P1: balance_ic
A2: 2 | B2: АТ "Укрексімбанк" | C2: Державний | D2: 1001 | E2: (без привʼязки) | F2: Банкноти та монети в касі банку | G2: А | H2: 2881154.5 | I2: 1258377.3 | J2: 1622777.2 | K2: 2741564.6 | L2: 1220518.4 | M2: 1521046.2 | N2: 827366.58 | O2: 181416.63 | P2: 645949.94
A3: 2 | B3: АТ "Укрексімбанк" | C3: Державний | D3: 1002 | E3: (без привʼязки) | F3: Банкноти та монети в касі відділень банку | G3: А | H3: 421596.77 | I3: 177262.1 | J3: 244334.67 | K3: 420605.54 | L3: 178404.18 | M3: 242201.35 | N3: 68413.231 | O3: 15938.651 | P3: 52474.58
A4: 2 | B4: АТ "Укрексімбанк" | C4: Державний | D4: 1004 | E4: (без привʼязки) | F4: Банкноти та монети в банкоматах | G4: А | H4: 1424777.4 | I4: 1424777.4 | J4: 0 | K4: 1427186.2 | L4: 1427186.2 | M4: 0 | N4: 345970.89 | O4: 345970.89 | P4: 0
A5: 2 | B5: АТ "Укрексімбанк" | C5: Державний | D5: 1005 | E5: (без привʼязки) | F5: Банкноти та монети, інкасовані до перерахування | G5: А | H5: 94970.078 | I5: 94970.078 | J5: 0 | K5: 94970.078 | L5: 94970.078 | M5: 0 | N5: 0 | O5: 0 | P5: 0
A6: 2 | B6: АТ "Укрексімбанк" | C6: Державний | D6: 1006 | E6: (без привʼязки) | F6: Банкноти та монети на зберіганні в інкасаторській компанії | G6: А | H6: 0 | I6: 0 | J6: 0 | K6: 0 | L6: 0 | M6: 0 | N6: 0 | O6: 0 | P6: 0
A7: 2 | B7: АТ "Укрексімбанк" | C7: Державний | D7: 1007 | E7: (без привʼязки) | F7: Банкноти та монети в дорозі | G7: А | H7: 880991.48 | I7: 256979.65 | J7: 624011.83 | K7: 911560.8 | L7: 261956.45 | M7: 649604.35 | N7: 0 | O7: 0 | P7: 0
A8: 2 | B8: АТ "Укрексімбанк" | C8: Державний | D8: 1011 | E8: (без привʼязки) | F8: Дорожні чеки в касі банку | G8: А | H8: 0 | I8: 0 | J8: 0 | K8: 0 | L8: 0 | M8: 0 | N8: 0 | O8: 0 | P8: 0
A9: 2 | B9: АТ "Укрексімбанк" | C9: Державний | D9: 1012 | E9: (без привʼязки) | F9: Дорожні чеки в касі відділень банку | G9: А | H9: 0 | I9: 0 | J9: 0 | K9: 0 | L9: 0 | M9: 0 | N9: 0 | O9: 0 | P9: 0
A10: 2 | B10: АТ "Укрексімбанк" | C10: Державний | D10: 1090 | E10: (без привʼязки) | F10: Резерви за готівковими коштами, наявність яких є непідтвердженою | G10: П | H10: 533.62252 | I10: 0 | J10: 533.62252 | K10: 785.03309 | L10: 0 | M10: 785.03309 | N10: -50810.589 | O10: -5377.8999 | P10: -45432.689
A11: 2 | B11: АТ "Укрексімбанк" | C11: Державний | D11: 1101 | E11: (без привʼязки) | F11: Банківські метали в банку | G11: А | H11: 0 | I11: 0 | J11: 0 | K11: 0 | L11: 0 | M11: 0 | N11: 0 | O11: 0 | P11: 0
A12: 2 | B12: АТ "Укрексімбанк" | C12: Державний | D12: 1102 | E12: (без привʼязки) | F12: Банківські метали у відділенні банку | G12: А | H12: 0 | I12: 0 | J12: 0 | K12: 0 | L12: 0 | M12: 0 | N12: 0 | O12: 0 | P12: 0
A13: 2 | B13: АТ "Укрексімбанк" | C13: Державний | D13: 1107 | E13: (без привʼязки) | F13: Банківські метали в дорозі | G13: А | H13: 0 | I13: 0 | J13: 0 | K13: 0 | L13: 0 | M13: 0 | N13: 0 | O13: 0 | P13: 0
... A1303: 2 | B1303: АТ "Укрексімбанк" | C1303: Державний | D1303: 9916 | E1303: (без привʼязки) | F1303: 0 | G1303: П | H1303: 0 | I1303: 0 | J1303: 0 | K1303: 0 | L1303: 0 | M1303: 0 | N1303: 0 | O1303: 0 | P1303: 0

Sheet Зміст
B2: Оборотно-сальдовий баланс банку | C2: відповідно до підпункту 1 пункту 2 постанови Правління Національного банку України
C3: від 15 березня 2018 року № 11 “Про встановлення переліку інформації, що підлягає обов'язковому опублікуванню банками України” (зі змінами)
C4: за даними статистичної звітності з файлу 02X “Дані про обороти та залишки на рахунках”.
A6: NKB | B6: Назва | C6: МФО
A7: 2 | B7: АТ "Укрексімбанк" | C7: 322313
A8: 6 | B8: АТ "ОЩАДБАНК" | C8: 300465
A9: 29 | B9: АТ "БАНК АЛЬЯНС" | C9: 300119
A10: 36 | B10: АТ "Райффайзен Банк" | C10: 300335
A11: 43 | B11: АТ "АЛЬТБАНК" | C11: 320940
A12: 46 | B12: АТ КБ "ПриватБанк" | C12: 305299
A13: 49 | B13: Полікомбанк | C13: 353100
A14: 62 | B14: АТ "ТАСКОМБАНК" | C14: 339500
A15: 72 | B15: ПрАТ "БАНК ФАМІЛЬНИЙ" | C15: 334840
A16: 88 | B16: АТ "КРЕДОБАНК" | C16: 325365
A17: 91 | B17: АТ АКБ "Львів" | C17: 325268
... A66: 774 | B66: АТ "РВС БАНК"* | C66: 339072
A68: * Неплатоспроможний банк.

Sheet   2АТ "Укрексімбанк" 
A1: Зміст
B2: Оборотно-сальдовий баланс банку АТ "Укрексімбанк" за станом на 01.12.2025
B3: (тис грн)
A4: Номер з/п | B4: Клас/ розділ/ група/ рахунок | I4: Актив/ пасив | J4: Обороти за місяць | Q4: Сальдо
J5: дебет | M5: кредит | Q5: усього | R5: НВ | S5: ІВ
B6: номер | F6: назва | J6: усього | K6: НВ | L6: ІВ | M6: усього | O6: НВ | P6: ІВ
A7: 1 | B7: 2 | F7: 3 | I7: 4 | J7: 5 | K7: 6 | L7: 7 | M7: 8 | O7: 9 | P7: 10 | Q7: 11 | R7: 12 | S7: 13
A8: 1 | B8: Балансові рахунки
A9: 2 | B9: Активи
A10: 3 | B10: Класи 1 - 4
A11: 4 | B11: Клас 1 | C11: 10 | D11: 100 | F11: 1001 | H11: Банкноти та монети в касі банку | I11: А | J11: 2881154.5 | K11: 1258377.3 | L11: 1622777.2 | M11: 2741564.6 | O11: 1220518.4 | P11: 1521046.2 | Q11: 827366.58 | R11: 181416.63 | S11: 645949.94
A12: 5 | F12: 1002 | H12: Банкноти та монети в касі відділень банку | I12: А | J12: 421596.77 | K12: 177262.1 | L12: 244334.67 | M12: 420605.54 | O12: 178404.18 | P12: 242201.35 | Q12: 68413.231 | R12: 15938.651 | S12: 52474.58
A13: 6 | F13: 1004 | H13: Банкноти та монети в банкоматах | I13: А | J13: 1424777.4 | K13: 1424777.4 | L13: 0 | M13: 1427186.2 | O13: 1427186.2 | P13: 0 | Q13: 345970.89 | R13: 345970.89 | S13: 0
A14: 7 | F14: 1005 | H14: Банкноти та монети, інкасовані до перерахування | I14: А | J14: 94970.078 | K14: 94970.078 | L14: 0 | M14: 94970.078 | O14: 94970.078 | P14: 0 | Q14: 0 | R14: 0 | S14: 0
A15: 8 | F15: 1006 | H15: Банкноти та монети на зберіганні в інкасаторській компанії | I15: А | J15: 0 | K15: 0 | L15: 0 | M15: 0 | O15: 0 | P15: 0 | Q15: 0 | R15: 0 | S15: 0
A16: 9 | F16: 1007 | H16: Банкноти та монети в дорозі | I16: А | J16: 880991.48 | K16: 256979.65 | L16: 624011.83 | M16: 911560.8 | O16: 261956.45 | P16: 649604.35 | Q16: 0 | R16: 0 | S16: 0
A17: 10 | F17: Група 100 - Усього | J17: 5703490.3 | K17: 3212366.5 | L17: 2491123.7 | M17: 5595887.3 | O17: 3183035.4 | P17: 2412851.9 | Q17: 1241750.7 | R17: 543326.17 | S17: 698424.52
A18: 11 | D18: 101 | F18: 1011 | H18: Дорожні чеки в касі банку | I18: А | J18: 0 | K18: 0 | L18: 0 | M18: 0 | O18: 0 | P18: 0 | Q18: 0 | R18: 0 | S18: 0
A19: 12 | F19: 1012 | H19: Дорожні чеки в касі відділень банку | I19: А | J19: 0 | K19: 0 | L19: 0 | M19: 0 | O19: 0 | P19: 0 | Q19: 0 | R19: 0 | S19: 0
A20: 13 | F20: Група 101 - Усього | J20: 0 | K20: 0 | L20: 0 | M20: 0 | O20: 0 | P20: 0 | Q20: 0 | R20: 0 | S20: 0
A21: 14 | D21: 109 | F21: 1090 | H21: Резерви за готівковими коштами, наявність яких є непідтвердженою | I21: П | J21: 533.62252 | K21: 0 | L21: 533.62252 | M21: 785.03309 | O21: 0 | P21: 785.03309 | Q21: -50810.589 | R21: -5377.8999 | S21: -45432.689
A22: 15 | F22: Група 109 - Усього | J22: 533.62252 | K22: 0 | L22: 533.62252 | M22: 785.03309 | O22: 0 | P22: 785.03309 | Q22: -50810.589 | R22: -5377.8999 | S22: -45432.689
A23: 16 | D23: Розділ 10 - Усього | J23: 5704023.9 | K23: 3212366.5 | L23: 2491657.3 | M23: 5596672.3 | O23: 3183035.4 | P23: 2413636.9 | Q23: 1190940.1 | R23: 537948.27 | S23: 652991.84
A24: 17 | C24: 11 | D24: 110 | F24: 1101 | H24: Банківські метали в банку | I24: А | J24: 0 | K24: 0 | L24: 0 | M24: 0 | O24: 0 | P24: 0 | Q24: 0 | R24: 0 | S24: 0
A25: 18 | F25: 1102 | H25: Банківські метали у відділенні банку | I25: А | J25: 0 | K25: 0 | L25: 0 | M25: 0 | O25: 0 | P25: 0 | Q25: 0 | R25: 0 | S25: 0
A26: 19 | F26: 1107 | H26: Банківські метали в дорозі | I26: А | J26: 0 | K26: 0 | L26: 0 | M26: 0 | O26: 0 | P26: 0 | Q26: 0 | R26: 0 | S26: 0
A27: 20 | F27: Група 110 - Усього | J27: 0 | K27: 0 | L27: 0 | M27: 0 | O27: 0 | P27: 0 | Q27: 0 | R27: 0 | S27: 0
A28: 21 | D28: 119 | F28: 1190 | H28: Резерви за банківськими металами, наявність яких є непідтвердженою | I28: П | J28: 0 | K28: 0 | L28: 0 | M28: 0 | O28: 0 | P28: 0 | Q28: 0 | R28: 0 | S28: 0
A29: 22 | F29: Група 119 - Усього | J29: 0 | K29: 0 | L29: 0 | M29: 0 | O29: 0 | P29: 0 | Q29: 0 | R29: 0 | S29: 0
A30: 23 | D30: Розділ 11 - Усього | J30: 0 | K30: 0 | L30: 0 | M30: 0 | O30: 0 | P30: 0 | Q30: 0 | R30: 0 | S30: 0
A31: 24 | C31: 12 | D31: 120 | F31: 1200 | H31: Кореспондентський рахунок банку в Національному банку України | I31: А | J31: 5.6606691e+08 | K31: 5.6606691e+08 | L31: 0 | M31: 5.616171e+08 | O31: 5.616171e+08 | P31: 0 | Q31: 22042210 | R31: 22042210 | S31: 0
A32: 25 | F32: 1202 | H32: Кошти банків за рахунками умовного зберігання (ескроу) у Національному банку України | I32: А | J32: 0 | K32: 0 | L32: 0 | M32: 0 | O32: 0 | P32: 0 | Q32: 0 | R32: 0 | S32: 0
A33: 26 | F33: 1205 | H33: Кошти банків для забезпечення виконання зобов’язань перед Національним банком України за кредитами, наданими банкам, та операціями своп процентної ставки | I33: А | J33: 0 | K33: 0 | L33: 0 | M33: 0 | O33: 0 | P33: 0 | Q33: 0 | R33: 0 | S33: 0
A34: 27 | F34: 1208 | H34: Нараховані доходи за коштами на вимогу в Національному банку України | I34: А | J34: 0 | K34: 0 | L34: 0 | M34: 0 | O34: 0 | P34: 0 | Q34: 0 | R34: 0 | S34: 0
A35: 28 | F35: Група 120 - Усього | J35: 5.6606691e+08 | K35: 5.6606691e+08 | L35: 0 | M35: 5.616171e+08 | O35: 5.616171e+08 | P35: 0 | Q35: 22042210 | R35: 22042210 | S35: 0
A36: 29 | D36: Розділ 12 - Усього | J36: 5.6606691e+08 | K36: 5.6606691e+08 | L36: 0 | M36: 5.616171e+08 | O36: 5.616171e+08 | P36: 0 | Q36: 22042210 | R36: 22042210 | S36: 0
A37: 30 | C37: 14 | D37: 140 | F37: 1400 | H37: Облігації внутрішньої державної позики, що рефінансуються Національним банком України, які обліковуються за справедливою вартістю через прибутки/збитки | I37: А | J37: 9461457.4 | K37: 5951813 | L37: 3509644.4 | M37: 12068323 | O37: 8995306 | P37: 3073017.2 | Q37: 13863168 | R37: 13246549 | S37: 616618.88
A38: 31 | F38: 1405 | H38: Переоцінка боргових цінних паперів, що рефінансуються Національним банком України, які обліковуються за справедливою вартістю через прибутки/збитки | I38: А | J38: 374584.69 | K38: 372410.19 | L38: 2174.4995 | M38: 2627750.8 | O38: 2625165.2 | P38: 2585.535 | Q38: 6054103.6 | R38: 6053531 | S38: 572.58176
A39: 32 | I39: П | J39: 0 | K39: 0 | L39: 0 | M39: 0 | O39: 0 | P39: 0 | Q39: -57653.272 | R39: -57281.832 | S39: -371.44051
A40: 33 | F40: 1406 | H40: Неамортизована премія/дисконт за борговими цінними паперами, що рефінансуються Національним банком України, які обліковуються за справедливою вартістю через прибутки/збитки | I40: А | J40: 76966.686 | K40: 72049.045 | L40: 4917.6409 | M40: 60453.482 | O40: 56658.297 | P40: 3795.1846 | Q40: 704401.07 | R40: 703238.51 | S40: 1162.5606
A41: 34 | I41: П | J41: 0 | K41: 0 | L41: 0 | M41: 0 | O41: 0 | P41: 0 | Q41: -15932.686 | R41: -15929.243 | S41: -3.44265
A42: 35 | F42: 1408 | H42: Нараховані доходи за борговими цінними паперами, що рефінансуються Національним банком України, які обліковуються за справедливою вартістю через прибутки/збитки | I42: А | J42: 412462 | K42: 356747.44 | L42: 55714.563 | M42: 447665.85 | O42: 400664.44 | P42: 47001.414 | Q42: 385140.92 | R42: 375182.2 | S42: 9958.7297
A43: 36 | F43: Група 140 - Усього | J43: 10325471 | K43: 6753019.7 | L43: 3572451.1 | M43: 15204193 | O43: 12077794 | P43: 3126399.4 | Q43: 20933228 | R43: 20305290 | S43: 627937.87
A44: 37 | D44: 141 | F44: 1410 | H44: Облігації внутрішньої державної позики, що рефінансуються Національним банком України, які обліковуються за справедливою вартістю через інший сукупний дохід | I44: А | J44: 0 | K44: 0 | L44: 0 | M44: 720998 | O44: 720998 | P44: 0 | Q44: 19225235 | R44: 19225235 | S44: 0
A45: 38 | F45: 1411 | H45: Облігації зовнішньої державної позики, що рефінансуються Національним банком України, які обліковуються за справедливою вартістю через інший сукупний дохід | I45: А | J45: 0 | K45: 0 | L45: 0 | M45: 0 | O45: 0 | P45: 0 | Q45: 0 | R45: 0 | S45: 0
A46: 39 | F46: 1412 | H46: Боргові цінні папери органів державної влади та місцевого самоврядування, що рефінансуються Національним банком України, які обліковуються за справедливою вартістю через інший сукупний дохід | I46: А | J46: 0 | K46: 0 | L46: 0 | M46: 0 | O46: 0 | P46: 0 | Q46: 0 | R46: 0 | S46: 0
A47: 40 | F47: 1415 | H47: Переоцінка боргових цінних паперів, що рефінансуються Національним банком України, які обліковуються за справедливою вартістю через інший сукупний дохід | I47: А | J47: 116132.23 | K47: 116132.23 | L47: 0 | M47: 126706.95 | O47: 126706.95 | P47: 0 | Q47: 483199.92 | R47: 483199.92 | S47: 0
A48: 41 | I48: П | J48: 0 | K48: 0 | L48: 0 | M48: 0 | O48: 0 | P48: 0 | Q48: -387951.2 | R48: -387951.2 | S48: 0
A49: 42 | F49: 1416 | H49: Неамортизована премія/дисконт за борговими цінними паперами, що рефінансуються Національним банком України, які обліковуються за справедливою вартістю через інший сукупний дохід | I49: А | J49: 1309.7475 | K49: 1309.7475 | L49: 0 | M49: 7620.9061 | O49: 7620.9061 | P49: 0 | Q49: 113011.67 | R49: 113011.67 | S49: 0
A50: 43 | I50: П | J50: 0 | K50: 0 | L50: 0 | M50: 0 | O50: 0 | P50: 0 | Q50: -4001.6549 | R50: -4001.6549 | S50: 0
A51: 44 | F51: 1418 | H51: Нараховані доходи за борговими цінними паперами, що рефінансуються Національним банком України, які обліковуються за справедливою вартістю через інший сукупний дохід | I51: А | J51: 251493.08 | K51: 251493.08 | L51: 0 | M51: 114050.99 | O51: 114050.99 | P51: 0 | Q51: 861921.33 | R51: 861921.33 | S51: 0
A52: 45 | F52: 1419 | H52: Резерв за борговими цінними паперами,що рефінансуються Національним банком України, які обліковуються за справедливою вартістю через інший сукупний дохід | I52: П | J52: 15901.213 | K52: 15901.213 | L52: 0 | M52: 5274.7307 | O52: 5274.7307 | P52: 0 | Q52: -847399.97 | R52: -847399.97 | S52: 0
A53: 46 | F53: Група 141 - Усього | J53: 384836.28 | K53: 384836.28 | L53: 0 | M53: 974651.57 | O53: 974651.57 | P53: 0 | Q53: 19444015 | R53: 19444015 | S53: 0
A54: 47 | D54: 142 | F54: 1420 | H54: Облігації внутрішньої державної позики, що рефінансуються Національним банком України, які обліковуються за амортизованою собівартістю | I54: А | J54: 0 | K54: 0 | L54: 0 | M54: 0 | O54: 0 | P54: 0 | Q54: 26489557 | R54: 26489557 | S54: 0
A55: 48 | F55: 1426 | H55: Неамортизована премія/дисконт за борговими цінними паперами, що рефінансуються Національним банком України, які обліковуються за амортизованою собівартістю | I55: А | J55: 1421.729 | K55: 1421.729 | L55: 0 | M55: 6213.554 | O55: 6213.554 | P55: 0 | Q55: 145146.68 | R55: 145146.68 | S55: 0
A56: 49 | I56: П | J56: 0 | K56: 0 | L56: 0 | M56: 0 | O56: 0 | P56: 0 | Q56: -28830.501 | R56: -28830.501 | S56: 0
A57: 50 | F57: 1428 | H57: Нараховані доходи за борговими цінними паперами, що рефінансуються Національним банком України, які обліковуються за амортизованою собівартістю | I57: А | J57: 304571.1 | K57: 304571.1 | L57: 0 | M57: 50273.415 | O57: 50273.415 | P57: 0 | Q57: 824636.77 | R57: 824636.77 | S57: 0
A58: 51 | F58: 1429 | H58: Резерв за борговими цінними паперами,що рефінансуються Національним банком України, які обліковуються за амортизованою собівартістю | I58: П | J58: 18908.285 | K58: 18908.285 | L58: 0 | M58: 8973.7314 | O58: 8973.7314 | P58: 0 | Q58: -1319100.4 | R58: -1319100.4 | S58: 0
A59: 52 | F59: Група 142 - Усього | J59: 324901.11 | K59: 324901.11 | L59: 0 | M59: 65460.701 | O59: 65460.701 | P59: 0 | Q59: 26111410 | R59: 26111410 | S59: 0
A60: 53 | D60: 143 | F60: 1430 | H60: Депозитні сертифікати Національного банку України, розміщені в банках України, що обліковуються за справедливою вартістю через інший сукупний дохід | I60: А | J60: 0 | K60: 0 | L60: 0 | M60: 0 | O60: 0 | P60: 0 | Q60: 0 | R60: 0 | S60: 0
A61: 54 | F61: 1435 | H61: Переоцінка депозитних сертифікатів Національного банку України, розміщених у банках України, що обліковуються за справедливою вартістю через інший сукупний дохід | I61: А | J61: 0 | K61: 0 | L61: 0 | M61: 0 | O61: 0 | P61: 0 | Q61: 0 | R61: 0 | S61: 0
A62: 55 | F62: 1436 | H62: Неамортизована премія/дисконт за депозитними сертифікатами Національного банку України, розміщеними в банках України, що обліковуються за справедливою вартістю через інший сукупний дохід | I62: А | J62: 0 | K62: 0 | L62: 0 | M62: 0 | O62: 0 | P62: 0 | Q62: 0 | R62: 0 | S62: 0
A63: 56 | I63: П | J63: 0 | K63: 0 | L63: 0 | M63: 0 | O63: 0 | P63: 0 | Q63: 0 | R63: 0 | S63: 0
A64: 57 | F64: 1438 | H64: Нараховані доходи за депозитними сертифікатами Національного банку України, розміщеними в банках України, що обліковуються за справедливою вартістю через інший сукупний дохід | I64: А | J64: 0 | K64: 0 | L64: 0 | M64: 0 | O64: 0 | P64: 0 | Q64: 0 | R64: 0 | S64: 0
A65: 58 | F65: Група 143 - Усього | J65: 0 | K65: 0 | L65: 0 | M65: 0 | O65: 0 | P65: 0 | Q65: 0 | R65: 0 | S65: 0
A66: 59 | D66: 144 | F66: 1440 | H66: Депозитні сертифікати Національного банку України, розміщені в банках України, що обліковуються за амортизованою собівартістю | I66: А | J66: 304000000 | K66: 304000000 | L66: 0 | M66: 299000000 | O66: 299000000 | P66: 0 | Q66: 25000000 | R66: 25000000 | S66: 0
A67: 60 | F67: 1446 | H67: Неамортизована премія/дисконт за депозитними сертифікатами Національного банку України, розміщеними в банках України, що обліковуються за амортизованою собівартістю | I67: А | J67: 17.385 | K67: 17.385 | L67: 0 | M67: 13.785 | O67: 13.785 | P67: 0 | Q67: 0 | R67: 0 | S67: 0
A68: 61 | I68: П | J68: 0 | K68: 0 | L68: 0 | M68: 0 | O68: 0 | P68: 0 | Q68: 0 | R68: 0 | S68: 0
A69: 62 | F69: 1448 | H69: Нараховані доходи за депозитними сертифікатами Національного банку України, розміщеними в банках України, що обліковуються за амортизованою собівартістю | I69: А | J69: 206808.51 | K69: 206808.51 | L69: 0 | M69: 183452.45 | O69: 183452.45 | P69: 0 | Q69: 31849.25 | R69: 31849.25 | S69: 0
A70: 63 | F70: Група 144 - Усього | J70: 3.0420683e+08 | K70: 3.0420683e+08 | L70: 0 | M70: 2.9918347e+08 | O70: 2.9918347e+08 | P70: 0 | Q70: 25031849 | R70: 25031849 | S70: 0
A71: 64 | D71: Розділ 14 - Усього | J71: 3.1524203e+08 | K71: 3.1166958e+08 | L71: 3572451.1 | M71: 3.1542777e+08 | O71: 3.1230137e+08 | P71: 3126399.4 | Q71: 91520501 | R71: 90892564 | S71: 627937.87
A72: 65 | C72: 15 | D72: 150 | F72: 1500 | H72: Кореспондентські рахунки, що відкриті в інших банках | I72: А | J72: 3.1363892e+08 | K72: 0 | L72: 3.1363892e+08 | M72: 3.2641004e+08 | O72: 0 | P72: 3.2641004e+08 | Q72: 19367439 | R72: 0 | S72: 19367439
A73: 66 | F73: 1508 | H73: Нараховані доходи за коштами на вимогу в інших банках | I73: А | J73: 0 | K73: 0 | L73: 0 | M73: 0 | O73: 0 | P73: 0 | Q73: 0 | R73: 0 | S73: 0
A74: 67 | F74: 1509 | H74: Резерв за коштами на вимогу в інших банках | I74: П | J74: 9061.1933 | K74: 0 | L74: 9061.1933 | M74: 1399.0083 | O74: 0 | P74: 1399.0083 | Q74: -48755.225 | R74: 0 | S74: -48755.225
A75: 68 | F75: Група 150 - Усього | J75: 3.1364798e+08 | K75: 0 | L75: 3.1364798e+08 | M75: 3.2641144e+08 | O75: 0 | P75: 3.2641144e+08 | Q75: 19318684 | R75: 0 | S75: 19318684
A76: 69 | D76: 151 | F76: 1510 | H76: Депозити овернайт, що розміщені в інших банках, які обліковуються за амортизованою собівартістю | I76: А | J76: 74603214 | K76: 0 | L76: 74603214 | M76: 72046728 | O76: 0 | P76: 72046728 | Q76: 4142955.3 | R76: 0 | S76: 4142955.3
A77: 70 | F77: 1513 | H77: Строкові вклади (депозити), що розміщені в інших банках, які обліковуються за амортизованою собівартістю | I77: А | J77: 86228495 | K77: 0 | L77: 86228495 | M77: 91098120 | O77: 0 | P77: 91098120 | Q77: 17639998 | R77: 0 | S77: 17639998
A78: 71 | F78: 1516 | H78: Неамортизована премія/дисконт за строковими вкладами (депозитами), що розміщені в інших банках, які обліковуються за амортизованою собівартістю | I78: А | J78: 4.0487 | K78: 0 | L78: 4.0487 | M78: 3.80429 | O78: 0 | P78: 3.80429 | Q78: 0 | R78: 0 | S78: 0
A79: 72 | I79: П | J79: 0 | K79: 0 | L79: 0 | M79: 0 | O79: 0 | P79: 0 | Q79: -0.41685 | R79: 0 | S79: -0.41685
A80: 73 | F80: 1518 | H80: Нараховані доходи за строковими вкладами (депозитами), що розміщені в інших банках, які обліковуються за амортизованою собівартістю | I80: А | J80: 52849.531 | K80: 0 | L80: 52849.531 | M80: 49276.997 | O80: 0 | P80: 49276.997 | Q80: 8688.0442 | R80: 0 | S80: 8688.0442
A81: 74 | F81: 1519 | H81: Резерв за строковими вкладами (депозитами), що розміщені в інших банках, які обліковуються за амортизованою собівартістю | I81: П | J81: 17599.6 | K81: 0 | L81: 17599.6 | M81: 15879.439 | O81: 0 | P81: 15879.439 | Q81: -15515.792 | R81: 0 | S81: -15515.792
A82: 75 | F82: Група 151 - Усього | J82: 1.6090216e+08 | K82: 0 | L82: 1.6090216e+08 | M82: 1.6321001e+08 | O82: 0 | P82: 1.6321001e+08 | Q82: 21776125 | R82: 0 | S82: 21776125
A83: 76 | D83: 152 | F83: 1521 | H83: Кредити овернайт, що надані іншим банкам,які обліковуються за амортизованою собівартістю | I83: А | J83: 0 | K83: 0 | L83: 0 | M83: 0 | O83: 0 | P83: 0 | Q83: 0 | R83: 0 | S83: 0
A84: 77 | F84: 1522 | H84: Кредити, що надані іншим банкам за операціями репо, які обліковуються за амортизованою собівартістю | I84: А | J84: 0 | K84: 0 | L84: 0 | M84: 0 | O84: 0 | P84: 0 | Q84: 0 | R84: 0 | S84: 0
A85: 78 | F85: 1524 | H85: Інші кредити, що надані іншим банкам, які обліковуються за амортизованою собівартістю | I85: А | J85: 2.02856 | K85: 0 | L85: 2.02856 | M85: 1.34819 | O85: 0 | P85: 1.34819 | Q85: 128.90196 | R85: 0 | S85: 128.90196
A86: 79 | F86: 1526 | H86: Неамортизована премія/дисконт за кредитами, що надані іншим банкам, які обліковуються за амортизованою собівартістю | I86: А | J86: 0 | K86: 0 | L86: 0 | M86: 0 | O86: 0 | P86: 0 | Q86: 0 | R86: 0 | S86: 0
A87: 80 | I87: П | J87: 0 | K87: 0 | L87: 0 | M87: 0 | O87: 0 | P87: 0 | Q87: 0 | R87: 0 | S87: 0
A88: 81 | F88: 1528 | H88: Нараховані доходи за кредитами, що надані іншим банкам, які обліковуються за амортизованою собівартістю | I88: А | J88: 0 | K88: 0 | L88: 0 | M88: 0 | O88: 0 | P88: 0 | Q88: 0 | R88: 0 | S88: 0
A89: 82 | F89: 1529 | H89: Резерв за кредитами, що надані іншим банкам, які обліковуються за амортизованою собівартістю | I89: П | J89: 1.34819 | K89: 0 | L89: 1.34819 | M89: 2.02856 | O89: 0 | P89: 2.02856 | Q89: -128.90196 | R89: 0 | S89: -128.90196
A90: 83 | F90: Група 152 - Усього | J90: 3.37675 | K90: 0 | L90: 3.37675 | M90: 3.37675 | O90: 0 | P90: 3.37675 | Q90: 0 | R90: 0 | S90: 0
A91: 84 | D91: Розділ 15 - Усього | J91: 4.7455014e+08 | K91: 0 | L91: 4.7455014e+08 | M91: 4.8962145e+08 | O91: 0 | P91: 4.8962145e+08 | Q91: 41094809 | R91: 0 | S91: 41094809
A92: 85 | C92: 16 | D92: 160 | F92: 1600 | H92: Кореспондентські рахунки інших банків | I92: А | J92: 1.7744514e+08 | K92: 1.1679258e+08 | L92: 60652553 | M92: 1.7927967e+08 | O92: 1.1871715e+08 | P92: 60562517 | Q92: 0 | R92: 0 | S92: 0
A93: 86 | F93: Група 160 - Усього | J93: 1.7744514e+08 | K93: 1.1679258e+08 | L93: 60652553 | M93: 1.7927967e+08 | O93: 1.1871715e+08 | P93: 60562517 | Q93: 0 | R93: 0 | S93: 0
A94: 87 | D94: Розділ 16 - Усього | J94: 1.7744514e+08 | K94: 1.1679258e+08 | L94: 60652553 | M94: 1.7927967e+08 | O94: 1.1871715e+08 | P94: 60562517 | Q94: 0 | R94: 0 | S94: 0
A95: 88 | C95: 18 | D95: 181 | F95: 1811 | H95: Дебіторська заборгованість за операціями з готівкою | I95: А | J95: 2967453.3 | K95: 1944259 | L95: 1023194.3 | M95: 2967553.3 | O95: 1944359 | P95: 1023194.3 | Q95: 4200 | R95: 4200 | S95: 0
A96: 89 | F96: 1819 | H96: Інша дебіторська заборгованість за операціями з банками | I96: А | J96: 34369.644 | K96: 2968.9512 | L96: 31400.693 | M96: 14188.135 | O96: 2375.0529 | P96: 11813.083 | Q96: 20181.508 | R96: 593.89829 | S96: 19587.61
A97: 90 | F97: Група 181 - Усього | J97: 3001823 | K97: 1947228 | L97: 1054595 | M97: 2981741.5 | O97: 1946734.1 | P97: 1035007.4 | Q97: 24381.508 | R97: 4793.8983 | S97: 19587.61
A98: 91 | D98: 183 | F98: 1832 | H98: Кошти банків у розрахунках | I98: А | J98: 18562.838 | K98: 0 | L98: 18562.838 | M98: 20387.93 | O98: 0 | P98: 20387.93 | Q98: 954406.21 | R98: 20 | S98: 954386.21
A99: 92 | F99: 1839 | H99: Резерви за коштами банків у розрахунках | I99: П | J99: 17.24608 | K99: 0 | L99: 17.24608 | M99: 18.66862 | O99: 0 | P99: 18.66862 | Q99: -1049.6683 | R99: 0 | S99: -1049.6683
A100: 93 | F100: Група 183 - Усього | J100: 18580.084 | K100: 0 | L100: 18580.084 | M100: 20406.598 | O100: 0 | P100: 20406.598 | Q100: 953356.54 | R100: 20 | S100: 953336.54
...
